Workbook

Sheet Summary
A1: Job Summary & Net Profit / Net Loss
A3: Job Name | B3: "All Jobs (200)" | D3: Biggest Expense Item: | E3: =IFERROR(INDEX(_Data!C2:C8001,MATCH(MAX(_Data!E2:E8001),_Data!E2:E8001,0)),"")
A4: Client | B4: "200 separate job pages" | D4: Biggest Expense Amount: | E4: =IFERROR(MAX(_Data!E2:E8001),"")
A5: Start Date | B5: =IF(COUNTA(_Data!A2:A8001)=0,"",MIN(_Data!A2:A8001)) | D5: Most Expensive Category: | E5: =IFERROR(INDEX(_Data!B2:B8001,MATCH(MAX(_Data!E2:E8001),_Data!E2:E8001,0)),"")
A6: End Date | B6: =IF(COUNTA(_Data!A2:A8001)=0,"",MAX(_Data!A2:A8001))
A7: Contract Price | B7: =SUM('Job Tracker'!B9,'Job 002'!B9,'Job 003'!B9,'Job 004'!B9,'Job 005'!B9,'Job 006'!B9,'Job 007'!B9,'Job 008'!B9,'Job 009'!B9,'Job 010'!B9,'Job 011'!B9,'Job 012'!B9,'Job 013'!B9,'Job 014'!B9,'Job 015'!B9,'Job 016'!B9,'Job 017'!B9,'Job 018'!B9,'Job 019'!B9,'Job 020'!B9,'Job 021'!B9,'Job 022'!B9,'Job 023'!B9,'Job 024'!B9,'Job 025'!B9,'Job 026'!B9,'Job 027'!B9,'Job 028'!B9,'Job 029'!B9,'Job 030'!B9,'Job 031'!B9,'Job 032'!B9,'Job 033'!B9,'Job 034'!B9,'Job 035'!B9,'Job 036'!B9,'Job 037'!B9,'Job 038'!B9,'Job 039'!B9,'Job 040'!B9,'Job 041'!B9,'Job 042'!B9,'Job 043'!B9,'Job 044'!B9,'Job 045'!B9,'Job 046'!B9,'Job 047'!B9,'Job 048'!B9,'Job 049'!B9,'Job 050'!B9,'Job 051'!B9,'Job 052'!B9,'Job 053'!B9,'Job 054'!B9,'Job 055'!B9,'Job 056'!B9,'Job 057'!B9,'Job 058'!B9,'Job 059'!B9,'Job 060'!B9,'Job 061'!B9,'Job 062'!B9,'Job 063'!B9,'Job 064'!B9,'Job 065'!B9,'Job 066'!B9,'Job 067'!B9,'Job 068'!B9,'Job 069'!B9,'Job 070'!B9,'Job 071'!B9,'Job 072'!B9,'Job 073'!B9,'Job 074'!B9,'Job 075'!B9,'Job 076'!B9,'Job 077'!B9,'Job 078'!B9,'Job 079'!B9,'Job 080'!B9,'Job 081'!B9,'Job 082'!B9,'Job 083'!B9,'Job 084'!B9,'Job 085'!B9,'Job 086'!B9,'Job 087'!B9,'Job 088'!B9,'Job 089'!B9,'Job 090'!B9,'Job 091'!B9,'Job 092'!B9,'Job 093'!B9,'Job 094'!B9,'Job 095'!B9,'Job 096'!B9,'Job 097'!B9,'Job 098'!B9,'Job 099'!B9,'Job 100'!B9,'Job 101'!B9,'Job 102'!B9,'Job 103'!B9,'Job 104'!B9,'Job 105'!B9,'Job 106'!B9,'Job 107'!B9,'Job 108'!B9,'Job 109'!B9,'Job 110'!B9,'Job 111'!B9,'Job 112'!B9,'Job 113'!B9,'Job 114'!B9,'Job 115'!B9,'Job 116'!B9,'Job 117'!B9,'Job 118'!B9,'Job 119'!B9,'Job 120'!B9,'Job 121'!B9,'Job 122'!B9,'Job 123'!B9,'Job 124'!B9,'Job 125'!B9,'Job 126'!B9,'Job 127'!B9,'Job 128'!B9,'Job 129'!B9,'Job 130'!B9,'Job 131'!B9,'Job 132'!B9,'Job 133'!B9,'Job 134'!B9,'Job 135'!B9,'Job 136'!B9,'Job 137'!B9,'Job 138'!B9,'Job 139'!B9,'Job 140'!B9,'Job 141'!B9,'Job 142'!B9,'Job 143'!B9,'Job 144'!B9,'Job 145'!B9,'Job 146'!B9,'Job 147'!B9,'Job 148'!B9,'Job 149'!B9,'Job 150'!B9,'Job 151'!B9,'Job 152'!B9,'Job 153'!B9,'Job 154'!B9,'Job 155'!B9,'Job 156'!B9,'Job 157'!B9,'Job 158'!B9,'Job 159'!B9,'Job 160'!B9,'Job 161'!B9,'Job 162'!B9,'Job 163'!B9,'Job 164'!B9,'Job 165'!B9,'Job 166'!B9,'Job 167'!B9,'Job 168'!B9,'Job 169'!B9,'Job 170'!B9,'Job 171'!B9,'Job 172'!B9,'Job 173'!B9,'Job 174'!B9,'Job 175'!B9,'Job 176'!B9,'Job 177'!B9,'Job 178'!B9,'Job 179'!B9,'Job 180'!B9,'Job 181'!B9,'Job 182'!B9,'Job 183'!B9,'Job 184'!B9,'Job 185'!B9,'Job 186'!B9,'Job 187'!B9,'Job 188'!B9,'Job 189'!B9,'Job 190'!B9,'Job 191'!B9,'Job 192'!B9,'Job 193'!B9,'Job 194'!B9,'Job 195'!B9,'Job 196'!B9,'Job 197'!B9,'Job 198'!B9,'Job 199'!B9,'Job 200'!B9)
A8: Change Orders | B8: =SUM('Job Tracker'!B10,'Job 002'!B10,'Job 003'!B10,'Job 004'!B10,'Job 005'!B10,'Job 006'!B10,'Job 007'!B10,'Job 008'!B10,'Job 009'!B10,'Job 010'!B10,'Job 011'!B10,'Job 012'!B10,'Job 013'!B10,'Job 014'!B10,'Job 015'!B10,'Job 016'!B10,'Job 017'!B10,'Job 018'!B10,'Job 019'!B10,'Job 020'!B10,'Job 021'!B10,'Job 022'!B10,'Job 023'!B10,'Job 024'!B10,'Job 025'!B10,'Job 026'!B10,'Job 027'!B10,'Job 028'!B10,'Job 029'!B10,'Job 030'!B10,'Job 031'!B10,'Job 032'!B10,'Job 033'!B10,'Job 034'!B10,'Job 035'!B10,'Job 036'!B10,'Job 037'!B10,'Job 038'!B10,'Job 039'!B10,'Job 040'!B10,'Job 041'!B10,'Job 042'!B10,'Job 043'!B10,'Job 044'!B10,'Job 045'!B10,'Job 046'!B10,'Job 047'!B10,'Job 048'!B10,'Job 049'!B10,'Job 050'!B10,'Job 051'!B10,'Job 052'!B10,'Job 053'!B10,'Job 054'!B10,'Job 055'!B10,'Job 056'!B10,'Job 057'!B10,'Job 058'!B10,'Job 059'!B10,'Job 060'!B10,'Job 061'!B10,'Job 062'!B10,'Job 063'!B10,'Job 064'!B10,'Job 065'!B10,'Job 066'!B10,'Job 067'!B10,'Job 068'!B10,'Job 069'!B10,'Job 070'!B10,'Job 071'!B10,'Job 072'!B10,'Job 073'!B10,'Job 074'!B10,'Job 075'!B10,'Job 076'!B10,'Job 077'!B10,'Job 078'!B10,'Job 079'!B10,'Job 080'!B10,'Job 081'!B10,'Job 082'!B10,'Job 083'!B10,'Job 084'!B10,'Job 085'!B10,'Job 086'!B10,'Job 087'!B10,'Job 088'!B10,'Job 089'!B10,'Job 090'!B10,'Job 091'!B10,'Job 092'!B10,'Job 093'!B10,'Job 094'!B10,'Job 095'!B10,'Job 096'!B10,'Job 097'!B10,'Job 098'!B10,'Job 099'!B10,'Job 100'!B10,'Job 101'!B10,'Job 102'!B10,'Job 103'!B10,'Job 104'!B10,'Job 105'!B10,'Job 106'!B10,'Job 107'!B10,'Job 108'!B10,'Job 109'!B10,'Job 110'!B10,'Job 111'!B10,'Job 112'!B10,'Job 113'!B10,'Job 114'!B10,'Job 115'!B10,'Job 116'!B10,'Job 117'!B10,'Job 118'!B10,'Job 119'!B10,'Job 120'!B10,'Job 121'!B10,'Job 122'!B10,'Job 123'!B10,'Job 124'!B10,'Job 125'!B10,'Job 126'!B10,'Job 127'!B10,'Job 128'!B10,'Job 129'!B10,'Job 130'!B10,'Job 131'!B10,'Job 132'!B10,'Job 133'!B10,'Job 134'!B10,'Job 135'!B10,'Job 136'!B10,'Job 137'!B10,'Job 138'!B10,'Job 139'!B10,'Job 140'!B10,'Job 141'!B10,'Job 142'!B10,'Job 143'!B10,'Job 144'!B10,'Job 145'!B10,'Job 146'!B10,'Job 147'!B10,'Job 148'!B10,'Job 149'!B10,'Job 150'!B10,'Job 151'!B10,'Job 152'!B10,'Job 153'!B10,'Job 154'!B10,'Job 155'!B10,'Job 156'!B10,'Job 157'!B10,'Job 158'!B10,'Job 159'!B10,'Job 160'!B10,'Job 161'!B10,'Job 162'!B10,'Job 163'!B10,'Job 164'!B10,'Job 165'!B10,'Job 166'!B10,'Job 167'!B10,'Job 168'!B10,'Job 169'!B10,'Job 170'!B10,'Job 171'!B10,'Job 172'!B10,'Job 173'!B10,'Job 174'!B10,'Job 175'!B10,'Job 176'!B10,'Job 177'!B10,'Job 178'!B10,'Job 179'!B10,'Job 180'!B10,'Job 181'!B10,'Job 182'!B10,'Job 183'!B10,'Job 184'!B10,'Job 185'!B10,'Job 186'!B10,'Job 187'!B10,'Job 188'!B10,'Job 189'!B10,'Job 190'!B10,'Job 191'!B10,'Job 192'!B10,'Job 193'!B10,'Job 194'!B10,'Job 195'!B10,'Job 196'!B10,'Job 197'!B10,'Job 198'!B10,'Job 199'!B10,'Job 200'!B10)
A9: Total Budget | B9: =SUM('Job Tracker'!B12,'Job 002'!B12,'Job 003'!B12,'Job 004'!B12,'Job 005'!B12,'Job 006'!B12,'Job 007'!B12,'Job 008'!B12,'Job 009'!B12,'Job 010'!B12,'Job 011'!B12,'Job 012'!B12,'Job 013'!B12,'Job 014'!B12,'Job 015'!B12,'Job 016'!B12,'Job 017'!B12,'Job 018'!B12,'Job 019'!B12,'Job 020'!B12,'Job 021'!B12,'Job 022'!B12,'Job 023'!B12,'Job 024'!B12,'Job 025'!B12,'Job 026'!B12,'Job 027'!B12,'Job 028'!B12,'Job 029'!B12,'Job 030'!B12,'Job 031'!B12,'Job 032'!B12,'Job 033'!B12,'Job 034'!B12,'Job 035'!B12,'Job 036'!B12,'Job 037'!B12,'Job 038'!B12,'Job 039'!B12,'Job 040'!B12,'Job 041'!B12,'Job 042'!B12,'Job 043'!B12,'Job 044'!B12,'Job 045'!B12,'Job 046'!B12,'Job 047'!B12,'Job 048'!B12,'Job 049'!B12,'Job 050'!B12,'Job 051'!B12,'Job 052'!B12,'Job 053'!B12,'Job 054'!B12,'Job 055'!B12,'Job 056'!B12,'Job 057'!B12,'Job 058'!B12,'Job 059'!B12,'Job 060'!B12,'Job 061'!B12,'Job 062'!B12,'Job 063'!B12,'Job 064'!B12,'Job 065'!B12,'Job 066'!B12,'Job 067'!B12,'Job 068'!B12,'Job 069'!B12,'Job 070'!B12,'Job 071'!B12,'Job 072'!B12,'Job 073'!B12,'Job 074'!B12,'Job 075'!B12,'Job 076'!B12,'Job 077'!B12,'Job 078'!B12,'Job 079'!B12,'Job 080'!B12,'Job 081'!B12,'Job 082'!B12,'Job 083'!B12,'Job 084'!B12,'Job 085'!B12,'Job 086'!B12,'Job 087'!B12,'Job 088'!B12,'Job 089'!B12,'Job 090'!B12,'Job 091'!B12,'Job 092'!B12,'Job 093'!B12,'Job 094'!B12,'Job 095'!B12,'Job 096'!B12,'Job 097'!B12,'Job 098'!B12,'Job 099'!B12,'Job 100'!B12,'Job 101'!B12,'Job 102'!B12,'Job 103'!B12,'Job 104'!B12,'Job 105'!B12,'Job 106'!B12,'Job 107'!B12,'Job 108'!B12,'Job 109'!B12,'Job 110'!B12,'Job 111'!B12,'Job 112'!B12,'Job 113'!B12,'Job 114'!B12,'Job 115'!B12,'Job 116'!B12,'Job 117'!B12,'Job 118'!B12,'Job 119'!B12,'Job 120'!B12,'Job 121'!B12,'Job 122'!B12,'Job 123'!B12,'Job 124'!B12,'Job 125'!B12,'Job 126'!B12,'Job 127'!B12,'Job 128'!B12,'Job 129'!B12,'Job 130'!B12,'Job 131'!B12,'Job 132'!B12,'Job 133'!B12,'Job 134'!B12,'Job 135'!B12,'Job 136'!B12,'Job 137'!B12,'Job 138'!B12,'Job 139'!B12,'Job 140'!B12,'Job 141'!B12,'Job 142'!B12,'Job 143'!B12,'Job 144'!B12,'Job 145'!B12,'Job 146'!B12,'Job 147'!B12,'Job 148'!B12,'Job 149'!B12,'Job 150'!B12,'Job 151'!B12,'Job 152'!B12,'Job 153'!B12,'Job 154'!B12,'Job 155'!B12,'Job 156'!B12,'Job 157'!B12,'Job 158'!B12,'Job 159'!B12,'Job 160'!B12,'Job 161'!B12,'Job 162'!B12,'Job 163'!B12,'Job 164'!B12,'Job 165'!B12,'Job 166'!B12,'Job 167'!B12,'Job 168'!B12,'Job 169'!B12,'Job 170'!B12,'Job 171'!B12,'Job 172'!B12,'Job 173'!B12,'Job 174'!B12,'Job 175'!B12,'Job 176'!B12,'Job 177'!B12,'Job 178'!B12,'Job 179'!B12,'Job 180'!B12,'Job 181'!B12,'Job 182'!B12,'Job 183'!B12,'Job 184'!B12,'Job 185'!B12,'Job 186'!B12,'Job 187'!B12,'Job 188'!B12,'Job 189'!B12,'Job 190'!B12,'Job 191'!B12,'Job 192'!B12,'Job 193'!B12,'Job 194'!B12,'Job 195'!B12,'Job 196'!B12,'Job 197'!B12,'Job 198'!B12,'Job 199'!B12,'Job 200'!B12)
A10: Total Expenses | B10: =SUM('Job Tracker'!B59,'Job 002'!B59,'Job 003'!B59,'Job 004'!B59,'Job 005'!B59,'Job 006'!B59,'Job 007'!B59,'Job 008'!B59,'Job 009'!B59,'Job 010'!B59,'Job 011'!B59,'Job 012'!B59,'Job 013'!B59,'Job 014'!B59,'Job 015'!B59,'Job 016'!B59,'Job 017'!B59,'Job 018'!B59,'Job 019'!B59,'Job 020'!B59,'Job 021'!B59,'Job 022'!B59,'Job 023'!B59,'Job 024'!B59,'Job 025'!B59,'Job 026'!B59,'Job 027'!B59,'Job 028'!B59,'Job 029'!B59,'Job 030'!B59,'Job 031'!B59,'Job 032'!B59,'Job 033'!B59,'Job 034'!B59,'Job 035'!B59,'Job 036'!B59,'Job 037'!B59,'Job 038'!B59,'Job 039'!B59,'Job 040'!B59,'Job 041'!B59,'Job 042'!B59,'Job 043'!B59,'Job 044'!B59,'Job 045'!B59,'Job 046'!B59,'Job 047'!B59,'Job 048'!B59,'Job 049'!B59,'Job 050'!B59,'Job 051'!B59,'Job 052'!B59,'Job 053'!B59,'Job 054'!B59,'Job 055'!B59,'Job 056'!B59,'Job 057'!B59,'Job 058'!B59,'Job 059'!B59,'Job 060'!B59,'Job 061'!B59,'Job 062'!B59,'Job 063'!B59,'Job 064'!B59,'Job 065'!B59,'Job 066'!B59,'Job 067'!B59,'Job 068'!B59,'Job 069'!B59,'Job 070'!B59,'Job 071'!B59,'Job 072'!B59,'Job 073'!B59,'Job 074'!B59,'Job 075'!B59,'Job 076'!B59,'Job 077'!B59,'Job 078'!B59,'Job 079'!B59,'Job 080'!B59,'Job 081'!B59,'Job 082'!B59,'Job 083'!B59,'Job 084'!B59,'Job 085'!B59,'Job 086'!B59,'Job 087'!B59,'Job 088'!B59,'Job 089'!B59,'Job 090'!B59,'Job 091'!B59,'Job 092'!B59,'Job 093'!B59,'Job 094'!B59,'Job 095'!B59,'Job 096'!B59,'Job 097'!B59,'Job 098'!B59,'Job 099'!B59,'Job 100'!B59,'Job 101'!B59,'Job 102'!B59,'Job 103'!B59,'Job 104'!B59,'Job 105'!B59,'Job 106'!B59,'Job 107'!B59,'Job 108'!B59,'Job 109'!B59,'Job 110'!B59,'Job 111'!B59,'Job 112'!B59,'Job 113'!B59,'Job 114'!B59,'Job 115'!B59,'Job 116'!B59,'Job 117'!B59,'Job 118'!B59,'Job 119'!B59,'Job 120'!B59,'Job 121'!B59,'Job 122'!B59,'Job 123'!B59,'Job 124'!B59,'Job 125'!B59,'Job 126'!B59,'Job 127'!B59,'Job 128'!B59,'Job 129'!B59,'Job 130'!B59,'Job 131'!B59,'Job 132'!B59,'Job 133'!B59,'Job 134'!B59,'Job 135'!B59,'Job 136'!B59,'Job 137'!B59,'Job 138'!B59,'Job 139'!B59,'Job 140'!B59,'Job 141'!B59,'Job 142'!B59,'Job 143'!B59,'Job 144'!B59,'Job 145'!B59,'Job 146'!B59,'Job 147'!B59,'Job 148'!B59,'Job 149'!B59,'Job 150'!B59,'Job 151'!B59,'Job 152'!B59,'Job 153'!B59,'Job 154'!B59,'Job 155'!B59,'Job 156'!B59,'Job 157'!B59,'Job 158'!B59,'Job 159'!B59,'Job 160'!B59,'Job 161'!B59,'Job 162'!B59,'Job 163'!B59,'Job 164'!B59,'Job 165'!B59,'Job 166'!B59,'Job 167'!B59,'Job 168'!B59,'Job 169'!B59,'Job 170'!B59,'Job 171'!B59,'Job 172'!B59,'Job 173'!B59,'Job 174'!B59,'Job 175'!B59,'Job 176'!B59,'Job 177'!B59,'Job 178'!B59,'Job 179'!B59,'Job 180'!B59,'Job 181'!B59,'Job 182'!B59,'Job 183'!B59,'Job 184'!B59,'Job 185'!B59,'Job 186'!B59,'Job 187'!B59,'Job 188'!B59,'Job 189'!B59,'Job 190'!B59,'Job 191'!B59,'Job 192'!B59,'Job 193'!B59,'Job 194'!B59,'Job 195'!B59,'Job 196'!B59,'Job 197'!B59,'Job 198'!B59,'Job 199'!B59,'Job 200'!B59)
A11: Profit Before Tax | B11: =B9-B10
A12: Tax Amount | B12: =SUM('Job Tracker'!B61,'Job 002'!B61,'Job 003'!B61,'Job 004'!B61,'Job 005'!B61,'Job 006'!B61,'Job 007'!B61,'Job 008'!B61,'Job 009'!B61,'Job 010'!B61,'Job 011'!B61,'Job 012'!B61,'Job 013'!B61,'Job 014'!B61,'Job 015'!B61,'Job 016'!B61,'Job 017'!B61,'Job 018'!B61,'Job 019'!B61,'Job 020'!B61,'Job 021'!B61,'Job 022'!B61,'Job 023'!B61,'Job 024'!B61,'Job 025'!B61,'Job 026'!B61,'Job 027'!B61,'Job 028'!B61,'Job 029'!B61,'Job 030'!B61,'Job 031'!B61,'Job 032'!B61,'Job 033'!B61,'Job 034'!B61,'Job 035'!B61,'Job 036'!B61,'Job 037'!B61,'Job 038'!B61,'Job 039'!B61,'Job 040'!B61,'Job 041'!B61,'Job 042'!B61,'Job 043'!B61,'Job 044'!B61,'Job 045'!B61,'Job 046'!B61,'Job 047'!B61,'Job 048'!B61,'Job 049'!B61,'Job 050'!B61,'Job 051'!B61,'Job 052'!B61,'Job 053'!B61,'Job 054'!B61,'Job 055'!B61,'Job 056'!B61,'Job 057'!B61,'Job 058'!B61,'Job 059'!B61,'Job 060'!B61,'Job 061'!B61,'Job 062'!B61,'Job 063'!B61,'Job 064'!B61,'Job 065'!B61,'Job 066'!B61,'Job 067'!B61,'Job 068'!B61,'Job 069'!B61,'Job 070'!B61,'Job 071'!B61,'Job 072'!B61,'Job 073'!B61,'Job 074'!B61,'Job 075'!B61,'Job 076'!B61,'Job 077'!B61,'Job 078'!B61,'Job 079'!B61,'Job 080'!B61,'Job 081'!B61,'Job 082'!B61,'Job 083'!B61,'Job 084'!B61,'Job 085'!B61,'Job 086'!B61,'Job 087'!B61,'Job 088'!B61,'Job 089'!B61,'Job 090'!B61,'Job 091'!B61,'Job 092'!B61,'Job 093'!B61,'Job 094'!B61,'Job 095'!B61,'Job 096'!B61,'Job 097'!B61,'Job 098'!B61,'Job 099'!B61,'Job 100'!B61,'Job 101'!B61,'Job 102'!B61,'Job 103'!B61,'Job 104'!B61,'Job 105'!B61,'Job 106'!B61,'Job 107'!B61,'Job 108'!B61,'Job 109'!B61,'Job 110'!B61,'Job 111'!B61,'Job 112'!B61,'Job 113'!B61,'Job 114'!B61,'Job 115'!B61,'Job 116'!B61,'Job 117'!B61,'Job 118'!B61,'Job 119'!B61,'Job 120'!B61,'Job 121'!B61,'Job 122'!B61,'Job 123'!B61,'Job 124'!B61,'Job 125'!B61,'Job 126'!B61,'Job 127'!B61,'Job 128'!B61,'Job 129'!B61,'Job 130'!B61,'Job 131'!B61,'Job 132'!B61,'Job 133'!B61,'Job 134'!B61,'Job 135'!B61,'Job 136'!B61,'Job 137'!B61,'Job 138'!B61,'Job 139'!B61,'Job 140'!B61,'Job 141'!B61,'Job 142'!B61,'Job 143'!B61,'Job 144'!B61,'Job 145'!B61,'Job 146'!B61,'Job 147'!B61,'Job 148'!B61,'Job 149'!B61,'Job 150'!B61,'Job 151'!B61,'Job 152'!B61,'Job 153'!B61,'Job 154'!B61,'Job 155'!B61,'Job 156'!B61,'Job 157'!B61,'Job 158'!B61,'Job 159'!B61,'Job 160'!B61,'Job 161'!B61,'Job 162'!B61,'Job 163'!B61,'Job 164'!B61,'Job 165'!B61,'Job 166'!B61,'Job 167'!B61,'Job 168'!B61,'Job 169'!B61,'Job 170'!B61,'Job 171'!B61,'Job 172'!B61,'Job 173'!B61,'Job 174'!B61,'Job 175'!B61,'Job 176'!B61,'Job 177'!B61,'Job 178'!B61,'Job 179'!B61,'Job 180'!B61,'Job 181'!B61,'Job 182'!B61,'Job 183'!B61,'Job 184'!B61,'Job 185'!B61,'Job 186'!B61,'Job 187'!B61,'Job 188'!B61,'Job 189'!B61,'Job 190'!B61,'Job 191'!B61,'Job 192'!B61,'Job 193'!B61,'Job 194'!B61,'Job 195'!B61,'Job 196'!B61,'Job 197'!B61,'Job 198'!B61,'Job 199'!B61,'Job 200'!B61)
A13: Net Profit | B13: =MAX(SUM('Job Tracker'!B62,'Job 002'!B62,'Job 003'!B62,'Job 004'!B62,'Job 005'!B62,'Job 006'!B62,'Job 007'!B62,'Job 008'!B62,'Job 009'!B62,'Job 010'!B62,'Job 011'!B62,'Job 012'!B62,'Job 013'!B62,'Job 014'!B62,'Job 015'!B62,'Job 016'!B62,'Job 017'!B62,'Job 018'!B62,'Job 019'!B62,'Job 020'!B62,'Job 021'!B62,'Job 022'!B62,'Job 023'!B62,'Job 024'!B62,'Job 025'!B62,'Job 026'!B62,'Job 027'!B62,'Job 028'!B62,'Job 029'!B62,'Job 030'!B62,'Job 031'!B62,'Job 032'!B62,'Job 033'!B62,'Job 034'!B62,'Job 035'!B62,'Job 036'!B62,'Job 037'!B62,'Job 038'!B62,'Job 039'!B62,'Job 040'!B62,'Job 041'!B62,'Job 042'!B62,'Job 043'!B62,'Job 044'!B62,'Job 045'!B62,'Job 046'!B62,'Job 047'!B62,'Job 048'!B62,'Job 049'!B62,'Job 050'!B62,'Job 051'!B62,'Job 052'!B62,'Job 053'!B62,'Job 054'!B62,'Job 055'!B62,'Job 056'!B62,'Job 057'!B62,'Job 058'!B62,'Job 059'!B62,'Job 060'!B62,'Job 061'!B62,'Job 062'!B62,'Job 063'!B62,'Job 064'!B62,'Job 065'!B62,'Job 066'!B62,'Job 067'!B62,'Job 068'!B62,'Job 069'!B62,'Job 070'!B62,'Job 071'!B62,'Job 072'!B62,'Job 073'!B62,'Job 074'!B62,'Job 075'!B62,'Job 076'!B62,'Job 077'!B62,'Job 078'!B62,'Job 079'!B62,'Job 080'!B62,'Job 081'!B62,'Job 082'!B62,'Job 083'!B62,'Job 084'!B62,'Job 085'!B62,'Job 086'!B62,'Job 087'!B62,'Job 088'!B62,'Job 089'!B62,'Job 090'!B62,'Job 091'!B62,'Job 092'!B62,'Job 093'!B62,'Job 094'!B62,'Job 095'!B62,'Job 096'!B62,'Job 097'!B62,'Job 098'!B62,'Job 099'!B62,'Job 100'!B62,'Job 101'!B62,'Job 102'!B62,'Job 103'!B62,'Job 104'!B62,'Job 105'!B62,'Job 106'!B62,'Job 107'!B62,'Job 108'!B62,'Job 109'!B62,'Job 110'!B62,'Job 111'!B62,'Job 112'!B62,'Job 113'!B62,'Job 114'!B62,'Job 115'!B62,'Job 116'!B62,'Job 117'!B62,'Job 118'!B62,'Job 119'!B62,'Job 120'!B62,'Job 121'!B62,'Job 122'!B62,'Job 123'!B62,'Job 124'!B62,'Job 125'!B62,'Job 126'!B62,'Job 127'!B62,'Job 128'!B62,'Job 129'!B62,'Job 130'!B62,'Job 131'!B62,'Job 132'!B62,'Job 133'!B62,'Job 134'!B62,'Job 135'!B62,'Job 136'!B62,'Job 137'!B62,'Job 138'!B62,'Job 139'!B62,'Job 140'!B62,'Job 141'!B62,'Job 142'!B62,'Job 143'!B62,'Job 144'!B62,'Job 145'!B62,'Job 146'!B62,'Job 147'!B62,'Job 148'!B62,'Job 149'!B62,'Job 150'!B62,'Job 151'!B62,'Job 152'!B62,'Job 153'!B62,'Job 154'!B62,'Job 155'!B62,'Job 156'!B62,'Job 157'!B62,'Job 158'!B62,'Job 159'!B62,'Job 160'!B62,'Job 161'!B62,'Job 162'!B62,'Job 163'!B62,'Job 164'!B62,'Job 165'!B62,'Job 166'!B62,'Job 167'!B62,'Job 168'!B62,'Job 169'!B62,'Job 170'!B62,'Job 171'!B62,'Job 172'!B62,'Job 173'!B62,'Job 174'!B62,'Job 175'!B62,'Job 176'!B62,'Job 177'!B62,'Job 178'!B62,'Job 179'!B62,'Job 180'!B62,'Job 181'!B62,'Job 182'!B62,'Job 183'!B62,'Job 184'!B62,'Job 185'!B62,'Job 186'!B62,'Job 187'!B62,'Job 188'!B62,'Job 189'!B62,'Job 190'!B62,'Job 191'!B62,'Job 192'!B62,'Job 193'!B62,'Job 194'!B62,'Job 195'!B62,'Job 196'!B62,'Job 197'!B62,'Job 198'!B62,'Job 199'!B62,'Job 200'!B62),0)
A14: Net Loss | B14: =MAX(-SUM('Job Tracker'!B62,'Job 002'!B62,'Job 003'!B62,'Job 004'!B62,'Job 005'!B62,'Job 006'!B62,'Job 007'!B62,'Job 008'!B62,'Job 009'!B62,'Job 010'!B62,'Job 011'!B62,'Job 012'!B62,'Job 013'!B62,'Job 014'!B62,'Job 015'!B62,'Job 016'!B62,'Job 017'!B62,'Job 018'!B62,'Job 019'!B62,'Job 020'!B62,'Job 021'!B62,'Job 022'!B62,'Job 023'!B62,'Job 024'!B62,'Job 025'!B62,'Job 026'!B62,'Job 027'!B62,'Job 028'!B62,'Job 029'!B62,'Job 030'!B62,'Job 031'!B62,'Job 032'!B62,'Job 033'!B62,'Job 034'!B62,'Job 035'!B62,'Job 036'!B62,'Job 037'!B62,'Job 038'!B62,'Job 039'!B62,'Job 040'!B62,'Job 041'!B62,'Job 042'!B62,'Job 043'!B62,'Job 044'!B62,'Job 045'!B62,'Job 046'!B62,'Job 047'!B62,'Job 048'!B62,'Job 049'!B62,'Job 050'!B62,'Job 051'!B62,'Job 052'!B62,'Job 053'!B62,'Job 054'!B62,'Job 055'!B62,'Job 056'!B62,'Job 057'!B62,'Job 058'!B62,'Job 059'!B62,'Job 060'!B62,'Job 061'!B62,'Job 062'!B62,'Job 063'!B62,'Job 064'!B62,'Job 065'!B62,'Job 066'!B62,'Job 067'!B62,'Job 068'!B62,'Job 069'!B62,'Job 070'!B62,'Job 071'!B62,'Job 072'!B62,'Job 073'!B62,'Job 074'!B62,'Job 075'!B62,'Job 076'!B62,'Job 077'!B62,'Job 078'!B62,'Job 079'!B62,'Job 080'!B62,'Job 081'!B62,'Job 082'!B62,'Job 083'!B62,'Job 084'!B62,'Job 085'!B62,'Job 086'!B62,'Job 087'!B62,'Job 088'!B62,'Job 089'!B62,'Job 090'!B62,'Job 091'!B62,'Job 092'!B62,'Job 093'!B62,'Job 094'!B62,'Job 095'!B62,'Job 096'!B62,'Job 097'!B62,'Job 098'!B62,'Job 099'!B62,'Job 100'!B62,'Job 101'!B62,'Job 102'!B62,'Job 103'!B62,'Job 104'!B62,'Job 105'!B62,'Job 106'!B62,'Job 107'!B62,'Job 108'!B62,'Job 109'!B62,'Job 110'!B62,'Job 111'!B62,'Job 112'!B62,'Job 113'!B62,'Job 114'!B62,'Job 115'!B62,'Job 116'!B62,'Job 117'!B62,'Job 118'!B62,'Job 119'!B62,'Job 120'!B62,'Job 121'!B62,'Job 122'!B62,'Job 123'!B62,'Job 124'!B62,'Job 125'!B62,'Job 126'!B62,'Job 127'!B62,'Job 128'!B62,'Job 129'!B62,'Job 130'!B62,'Job 131'!B62,'Job 132'!B62,'Job 133'!B62,'Job 134'!B62,'Job 135'!B62,'Job 136'!B62,'Job 137'!B62,'Job 138'!B62,'Job 139'!B62,'Job 140'!B62,'Job 141'!B62,'Job 142'!B62,'Job 143'!B62,'Job 144'!B62,'Job 145'!B62,'Job 146'!B62,'Job 147'!B62,'Job 148'!B62,'Job 149'!B62,'Job 150'!B62,'Job 151'!B62,'Job 152'!B62,'Job 153'!B62,'Job 154'!B62,'Job 155'!B62,'Job 156'!B62,'Job 157'!B62,'Job 158'!B62,'Job 159'!B62,'Job 160'!B62,'Job 161'!B62,'Job 162'!B62,'Job 163'!B62,'Job 164'!B62,'Job 165'!B62,'Job 166'!B62,'Job 167'!B62,'Job 168'!B62,'Job 169'!B62,'Job 170'!B62,'Job 171'!B62,'Job 172'!B62,'Job 173'!B62,'Job 174'!B62,'Job 175'!B62,'Job 176'!B62,'Job 177'!B62,'Job 178'!B62,'Job 179'!B62,'Job 180'!B62,'Job 181'!B62,'Job 182'!B62,'Job 183'!B62,'Job 184'!B62,'Job 185'!B62,'Job 186'!B62,'Job 187'!B62,'Job 188'!B62,'Job 189'!B62,'Job 190'!B62,'Job 191'!B62,'Job 192'!B62,'Job 193'!B62,'Job 194'!B62,'Job 195'!B62,'Job 196'!B62,'Job 197'!B62,'Job 198'!B62,'Job 199'!B62,'Job 200'!B62),0)
A19: Category | B19: Total | D19: Pie Chart Data
A20: Materials | B20: =SUMIF(_Data!$B$2:$B$8001,A20,_Data!$E$2:$E$8001)
A21: Labor | B21: =SUMIF(_Data!$B$2:$B$8001,A21,_Data!$E$2:$E$8001)
A22: Gas | B22: =SUMIF(_Data!$B$2:$B$8001,A22,_Data!$E$2:$E$8001)
A23: Toll | B23: =SUMIF(_Data!$B$2:$B$8001,A23,_Data!$E$2:$E$8001)
A24: Equipment | B24: =SUMIF(_Data!$B$2:$B$8001,A24,_Data!$E$2:$E$8001)
A25: Subcontractor | B25: =SUMIF(_Data!$B$2:$B$8001,A25,_Data!$E$2:$E$8001)
A26: Permits | B26: =SUMIF(_Data!$B$2:$B$8001,A26,_Data!$E$2:$E$8001)
A27: Misc | B27: =SUMIF(_Data!$B$2:$B$8001,A27,_Data!$E$2:$E$8001)
A28: Total | B28: =SUM(B20:B27)

Sheet Profit Pie
A1: Expense Pie Chart
A3: This chart shows where the money went by category.
A5: Category | B5: Total
A6: Materials | B6: =Summary!B20
A7: Labor | B7: =Summary!B21
A8: Gas | B8: =Summary!B22
A9: Toll | B9: =Summary!B23
A10: Equipment | B10: =Summary!B24
A11: Subcontractor | B11: =Summary!B25
A12: Permits | B12: =Summary!B26
A13: Misc | B13: =Summary!B27
A14: Use the tracker sheet to add receipts; this chart updates from the category totals.

Sheet Top Expenses
A1: Top Expense Items
A3: Biggest expense by line item and a quick list of the highest costs.
A5: Biggest Item | B5: =IFERROR(INDEX(_Data!C2:C8001,MATCH(MAX(_Data!E2:E8001),_Data!E2:E8001,0)),"") | D5: Amount | E5: =IFERROR(MAX(_Data!E2:E8001),"")
A8: Date | B8: Type | C8: Description | D8: Vendor | E8: Cost
A9: =IF(E9="","",INDEX(_Data!$A$2:$A$8001,MATCH(E9,_Data!$E$2:$E$8001,0))) | B9: =IF(E9="","",INDEX(_Data!$B$2:$B$8001,MATCH(E9,_Data!$E$2:$E$8001,0))) | C9: =IF(E9="","",INDEX(_Data!$C$2:$C$8001,MATCH(E9,_Data!$E$2:$E$8001,0))) | D9: =IF(E9="","",INDEX(_Data!$D$2:$D$8001,MATCH(E9,_Data!$E$2:$E$8001,0))) | E9: =IFERROR(LARGE(_Data!$E$2:$E$8001,1),"")
A10: =IF(E10="","",INDEX(_Data!$A$2:$A$8001,MATCH(E10,_Data!$E$2:$E$8001,0))) | B10: =IF(E10="","",INDEX(_Data!$B$2:$B$8001,MATCH(E10,_Data!$E$2:$E$8001,0))) | C10: =IF(E10="","",INDEX(_Data!$C$2:$C$8001,MATCH(E10,_Data!$E$2:$E$8001,0))) | D10: =IF(E10="","",INDEX(_Data!$D$2:$D$8001,MATCH(E10,_Data!$E$2:$E$8001,0))) | E10: =IFERROR(LARGE(_Data!$E$2:$E$8001,2),"")
A11: =IF(E11="","",INDEX(_Data!$A$2:$A$8001,MATCH(E11,_Data!$E$2:$E$8001,0))) | B11: =IF(E11="","",INDEX(_Data!$B$2:$B$8001,MATCH(E11,_Data!$E$2:$E$8001,0))) | C11: =IF(E11="","",INDEX(_Data!$C$2:$C$8001,MATCH(E11,_Data!$E$2:$E$8001,0))) | D11: =IF(E11="","",INDEX(_Data!$D$2:$D$8001,MATCH(E11,_Data!$E$2:$E$8001,0))) | E11: =IFERROR(LARGE(_Data!$E$2:$E$8001,3),"")
A12: =IF(E12="","",INDEX(_Data!$A$2:$A$8001,MATCH(E12,_Data!$E$2:$E$8001,0))) | B12: =IF(E12="","",INDEX(_Data!$B$2:$B$8001,MATCH(E12,_Data!$E$2:$E$8001,0))) | C12: =IF(E12="","",INDEX(_Data!$C$2:$C$8001,MATCH(E12,_Data!$E$2:$E$8001,0))) | D12: =IF(E12="","",INDEX(_Data!$D$2:$D$8001,MATCH(E12,_Data!$E$2:$E$8001,0))) | E12: =IFERROR(LARGE(_Data!$E$2:$E$8001,4),"")
A13: =IF(E13="","",INDEX(_Data!$A$2:$A$8001,MATCH(E13,_Data!$E$2:$E$8001,0))) | B13: =IF(E13="","",INDEX(_Data!$B$2:$B$8001,MATCH(E13,_Data!$E$2:$E$8001,0))) | C13: =IF(E13="","",INDEX(_Data!$C$2:$C$8001,MATCH(E13,_Data!$E$2:$E$8001,0))) | D13: =IF(E13="","",INDEX(_Data!$D$2:$D$8001,MATCH(E13,_Data!$E$2:$E$8001,0))) | E13: =IFERROR(LARGE(_Data!$E$2:$E$8001,5),"")
A14: =IF(E14="","",INDEX(_Data!$A$2:$A$8001,MATCH(E14,_Data!$E$2:$E$8001,0))) | B14: =IF(E14="","",INDEX(_Data!$B$2:$B$8001,MATCH(E14,_Data!$E$2:$E$8001,0))) | C14: =IF(E14="","",INDEX(_Data!$C$2:$C$8001,MATCH(E14,_Data!$E$2:$E$8001,0))) | D14: =IF(E14="","",INDEX(_Data!$D$2:$D$8001,MATCH(E14,_Data!$E$2:$E$8001,0))) | E14: =IFERROR(LARGE(_Data!$E$2:$E$8001,6),"")
A15: =IF(E15="","",INDEX(_Data!$A$2:$A$8001,MATCH(E15,_Data!$E$2:$E$8001,0))) | B15: =IF(E15="","",INDEX(_Data!$B$2:$B$8001,MATCH(E15,_Data!$E$2:$E$8001,0))) | C15: =IF(E15="","",INDEX(_Data!$C$2:$C$8001,MATCH(E15,_Data!$E$2:$E$8001,0))) | D15: =IF(E15="","",INDEX(_Data!$D$2:$D$8001,MATCH(E15,_Data!$E$2:$E$8001,0))) | E15: =IFERROR(LARGE(_Data!$E$2:$E$8001,7),"")
A16: =IF(E16="","",INDEX(_Data!$A$2:$A$8001,MATCH(E16,_Data!$E$2:$E$8001,0))) | B16: =IF(E16="","",INDEX(_Data!$B$2:$B$8001,MATCH(E16,_Data!$E$2:$E$8001,0))) | C16: =IF(E16="","",INDEX(_Data!$C$2:$C$8001,MATCH(E16,_Data!$E$2:$E$8001,0))) | D16: =IF(E16="","",INDEX(_Data!$D$2:$D$8001,MATCH(E16,_Data!$E$2:$E$8001,0))) | E16: =IFERROR(LARGE(_Data!$E$2:$E$8001,8),"")
A17: =IF(E17="","",INDEX(_Data!$A$2:$A$8001,MATCH(E17,_Data!$E$2:$E$8001,0))) | B17: =IF(E17="","",INDEX(_Data!$B$2:$B$8001,MATCH(E17,_Data!$E$2:$E$8001,0))) | C17: =IF(E17="","",INDEX(_Data!$C$2:$C$8001,MATCH(E17,_Data!$E$2:$E$8001,0))) | D17: =IF(E17="","",INDEX(_Data!$D$2:$D$8001,MATCH(E17,_Data!$E$2:$E$8001,0))) | E17: =IFERROR(LARGE(_Data!$E$2:$E$8001,9),"")
A18: =IF(E18="","",INDEX(_Data!$A$2:$A$8001,MATCH(E18,_Data!$E$2:$E$8001,0))) | B18: =IF(E18="","",INDEX(_Data!$B$2:$B$8001,MATCH(E18,_Data!$E$2:$E$8001,0))) | C18: =IF(E18="","",INDEX(_Data!$C$2:$C$8001,MATCH(E18,_Data!$E$2:$E$8001,0))) | D18: =IF(E18="","",INDEX(_Data!$D$2:$D$8001,MATCH(E18,_Data!$E$2:$E$8001,0))) | E18: =IFERROR(LARGE(_Data!$E$2:$E$8001,10),"")
A21: These rows show the largest costs, so you can spot where your money is going fastest.

Sheet Job Tracker
A1: Hammer Brick & Home LLC - Job Tracker
A3: Job Name:
A4: Client:
A5: Address:
A6: Start Date:
A7: End Date:
A9: Contract Price:
A10: Change Orders:
A11: Tax Rate:
A12: Total Budget: | B12: =B9+B10
A15: Expense Log (enter one line per receipt)
A16: Date | B16: Type | C16: Description | D16: Vendor | E16: Cost
A59: Total Expenses: | B59: =SUM(E17:E56) | D59: Most Expensive Item: | E59: =IFERROR(INDEX(C17:C56,MATCH(MAX(E17:E56),E17:E56,0)),"")
A60: Profit Before Tax: | B60: =B12-B59 | D60: Largest Expense: | E60: =MAX(E17:E56)
A61: Tax Amount: | B61: =IF(B60>0,B60*$B$11,0)
A62: Net Profit: | B62: =B60-B61
A63: Net Loss: | B63: =IF(B62<0,ABS(B62),0)
A64: Tip: | B64: Enter every receipt on its own row so the summaries and chart stay accurate.

Sheet Job 002
A1: Hammer Brick & Home LLC - Job Tracker
A3: Job Name:
A4: Client:
A5: Address:
A6: Start Date:
A7: End Date:
A9: Contract Price:
A10: Change Orders:
A11: Tax Rate:
A12: Total Budget: | B12: =B9+B10
A15: Expense Log (enter one line per receipt)
A16: Date | B16: Type | C16: Description | D16: Vendor | E16: Cost
A59: Total Expenses: | B59: =SUM(E17:E56) | D59: Most Expensive Item: | E59: =IFERROR(INDEX(C17:C56,MATCH(MAX(E17:E56),E17:E56,0)),"")
A60: Profit Before Tax: | B60: =B12-B59 | D60: Largest Expense: | E60: =MAX(E17:E56)
A61: Tax Amount: | B61: =IF(B60>0,B60*$B$11,0)
A62: Net Profit: | B62: =B60-B61
A63: Net Loss: | B63: =IF(B62<0,ABS(B62),0)
A64: Tip: | B64: Enter every receipt on its own row so the summaries and chart stay accurate.

Sheet Job 003
A1: Hammer Brick & Home LLC - Job Tracker
A3: Job Name:
A4: Client:
A5: Address:
A6: Start Date:
A7: End Date:
A9: Contract Price:
A10: Change Orders:
A11: Tax Rate:
A12: Total Budget: | B12: =B9+B10
A15: Expense Log (enter one line per receipt)
A16: Date | B16: Type | C16: Description | D16: Vendor | E16: Cost
A59: Total Expenses: | B59: =SUM(E17:E56) | D59: Most Expensive Item: | E59: =IFERROR(INDEX(C17:C56,MATCH(MAX(E17:E56),E17:E56,0)),"")
A60: Profit Before Tax: | B60: =B12-B59 | D60: Largest Expense: | E60: =MAX(E17:E56)
A61: Tax Amount: | B61: =IF(B60>0,B60*$B$11,0)
A62: Net Profit: | B62: =B60-B61
A63: Net Loss: | B63: =IF(B62<0,ABS(B62),0)
A64: Tip: | B64: Enter every receipt on its own row so the summaries and chart stay accurate.

Sheet Job 004
A1: Hammer Brick & Home LLC - Job Tracker
A3: Job Name:
A4: Client:
A5: Address:
A6: Start Date:
A7: End Date:
A9: Contract Price:
A10: Change Orders:
A11: Tax Rate:
A12: Total Budget: | B12: =B9+B10
A15: Expense Log (enter one line per receipt)
A16: Date | B16: Type | C16: Description | D16: Vendor | E16: Cost
A59: Total Expenses: | B59: =SUM(E17:E56) | D59: Most Expensive Item: | E59: =IFERROR(INDEX(C17:C56,MATCH(MAX(E17:E56),E17:E56,0)),"")
A60: Profit Before Tax: | B60: =B12-B59 | D60: Largest Expense: | E60: =MAX(E17:E56)
A61: Tax Amount: | B61: =IF(B60>0,B60*$B$11,0)
A62: Net Profit: | B62: =B60-B61
A63: Net Loss: | B63: =IF(B62<0,ABS(B62),0)
A64: Tip: | B64: Enter every receipt on its own row so the summaries and chart stay accurate.

Sheet Job 005
A1: Hammer Brick & Home LLC - Job Tracker
A3: Job Name:
A4: Client:
A5: Address:
A6: Start Date:
A7: End Date:
A9: Contract Price:
A10: Change Orders:
A11: Tax Rate:
A12: Total Budget: | B12: =B9+B10
A15: Expense Log (enter one line per receipt)
A16: Date | B16: Type | C16: Description | D16: Vendor | E16: Cost
A59: Total Expenses: | B59: =SUM(E17:E56) | D59: Most Expensive Item: | E59: =IFERROR(INDEX(C17:C56,MATCH(MAX(E17:E56),E17:E56,0)),"")
A60: Profit Before Tax: | B60: =B12-B59 | D60: Largest Expense: | E60: =MAX(E17:E56)
A61: Tax Amount: | B61: =IF(B60>0,B60*$B$11,0)
A62: Net Profit: | B62: =B60-B61
A63: Net Loss: | B63: =IF(B62<0,ABS(B62),0)
A64: Tip: | B64: Enter every receipt on its own row so the summaries and chart stay accurate.

Sheet Job 006
A1: Hammer Brick & Home LLC - Job Tracker
A3: Job Name:
A4: Client:
A5: Address:
A6: Start Date:
A7: End Date:
A9: Contract Price:
A10: Change Orders:
A11: Tax Rate:
A12: Total Budget: | B12: =B9+B10
A15: Expense Log (enter one line per receipt)
A16: Date | B16: Type | C16: Description | D16: Vendor | E16: Cost
A59: Total Expenses: | B59: =SUM(E17:E56) | D59: Most Expensive Item: | E59: =IFERROR(INDEX(C17:C56,MATCH(MAX(E17:E56),E17:E56,0)),"")
A60: Profit Before Tax: | B60: =B12-B59 | D60: Largest Expense: | E60: =MAX(E17:E56)
A61: Tax Amount: | B61: =IF(B60>0,B60*$B$11,0)
A62: Net Profit: | B62: =B60-B61
A63: Net Loss: | B63: =IF(B62<0,ABS(B62),0)
A64: Tip: | B64: Enter every receipt on its own row so the summaries and chart stay accurate.

Sheet Job 007
A1: Hammer Brick & Home LLC - Job Tracker
A3: Job Name:
A4: Client:
A5: Address:
A6: Start Date:
A7: End Date:
A9: Contract Price:
A10: Change Orders:
A11: Tax Rate:
A12: Total Budget: | B12: =B9+B10
A15: Expense Log (enter one line per receipt)
A16: Date | B16: Type | C16: Description | D16: Vendor | E16: Cost
A59: Total Expenses: | B59: =SUM(E17:E56) | D59: Most Expensive Item: | E59: =IFERROR(INDEX(C17:C56,MATCH(MAX(E17:E56),E17:E56,0)),"")
A60: Profit Before Tax: | B60: =B12-B59 | D60: Largest Expense: | E60: =MAX(E17:E56)
A61: Tax Amount: | B61: =IF(B60>0,B60*$B$11,0)
A62: Net Profit: | B62: =B60-B61
A63: Net Loss: | B63: =IF(B62<0,ABS(B62),0)
A64: Tip: | B64: Enter every receipt on its own row so the summaries and chart stay accurate.

Sheet Job 008
A1: Hammer Brick & Home LLC - Job Tracker
A3: Job Name:
A4: Client:
A5: Address:
A6: Start Date:
A7: End Date:
A9: Contract Price:
A10: Change Orders:
A11: Tax Rate:
A12: Total Budget: | B12: =B9+B10
A15: Expense Log (enter one line per receipt)
A16: Date | B16: Type | C16: Description | D16: Vendor | E16: Cost
A59: Total Expenses: | B59: =SUM(E17:E56) | D59: Most Expensive Item: | E59: =IFERROR(INDEX(C17:C56,MATCH(MAX(E17:E56),E17:E56,0)),"")
A60: Profit Before Tax: | B60: =B12-B59 | D60: Largest Expense: | E60: =MAX(E17:E56)
A61: Tax Amount: | B61: =IF(B60>0,B60*$B$11,0)
A62: Net Profit: | B62: =B60-B61
A63: Net Loss: | B63: =IF(B62<0,ABS(B62),0)
A64: Tip: | B64: Enter every receipt on its own row so the summaries and chart stay accurate.

Sheet Job 009
A1: Hammer Brick & Home LLC - Job Tracker
A3: Job Name:
A4: Client:
A5: Address:
A6: Start Date:
A7: End Date:
A9: Contract Price:
A10: Change Orders:
A11: Tax Rate:
A12: Total Budget: | B12: =B9+B10
A15: Expense Log (enter one line per receipt)
A16: Date | B16: Type | C16: Description | D16: Vendor | E16: Cost
A59: Total Expenses: | B59: =SUM(E17:E56) | D59: Most Expensive Item: | E59: =IFERROR(INDEX(C17:C56,MATCH(MAX(E17:E56),E17:E56,0)),"")
A60: Profit Before Tax: | B60: =B12-B59 | D60: Largest Expense: | E60: =MAX(E17:E56)
A61: Tax Amount: | B61: =IF(B60>0,B60*$B$11,0)
A62: Net Profit: | B62: =B60-B61
A63: Net Loss: | B63: =IF(B62<0,ABS(B62),0)
A64: Tip: | B64: Enter every receipt on its own row so the summaries and chart stay accurate.

Sheet Job 010
A1: Hammer Brick & Home LLC - Job Tracker
A3: Job Name:
A4: Client:
A5: Address:
A6: Start Date:
A7: End Date:
A9: Contract Price:
A10: Change Orders:
A11: Tax Rate:
A12: Total Budget: | B12: =B9+B10
A15: Expense Log (enter one line per receipt)
A16: Date | B16: Type | C16: Description | D16: Vendor | E16: Cost
A59: Total Expenses: | B59: =SUM(E17:E56) | D59: Most Expensive Item: | E59: =IFERROR(INDEX(C17:C56,MATCH(MAX(E17:E56),E17:E56,0)),"")
A60: Profit Before Tax: | B60: =B12-B59 | D60: Largest Expense: | E60: =MAX(E17:E56)
A61: Tax Amount: | B61: =IF(B60>0,B60*$B$11,0)
A62: Net Profit: | B62: =B60-B61
A63: Net Loss: | B63: =IF(B62<0,ABS(B62),0)
A64: Tip: | B64: Enter every receipt on its own row so the summaries and chart stay accurate.

Sheet Job 011
A1: Hammer Brick & Home LLC - Job Tracker
A3: Job Name:
A4: Client:
A5: Address:
A6: Start Date:
A7: End Date:
A9: Contract Price:
A10: Change Orders:
A11: Tax Rate:
A12: Total Budget: | B12: =B9+B10
A15: Expense Log (enter one line per receipt)
A16: Date | B16: Type | C16: Description | D16: Vendor | E16: Cost
A59: Total Expenses: | B59: =SUM(E17:E56) | D59: Most Expensive Item: | E59: =IFERROR(INDEX(C17:C56,MATCH(MAX(E17:E56),E17:E56,0)),"")
A60: Profit Before Tax: | B60: =B12-B59 | D60: Largest Expense: | E60: =MAX(E17:E56)
A61: Tax Amount: | B61: =IF(B60>0,B60*$B$11,0)
A62: Net Profit: | B62: =B60-B61
A63: Net Loss: | B63: =IF(B62<0,ABS(B62),0)
A64: Tip: | B64: Enter every receipt on its own row so the summaries and chart stay accurate.

Sheet Job 012
A1: Hammer Brick & Home LLC - Job Tracker
A3: Job Name:
A4: Client:
A5: Address:
A6: Start Date:
A7: End Date:
A9: Contract Price:
A10: Change Orders:
A11: Tax Rate:
A12: Total Budget: | B12: =B9+B10
A15: Expense Log (enter one line per receipt)
A16: Date | B16: Type | C16: Description | D16: Vendor | E16: Cost
A59: Total Expenses: | B59: =SUM(E17:E56) | D59: Most Expensive Item: | E59: =IFERROR(INDEX(C17:C56,MATCH(MAX(E17:E56),E17:E56,0)),"")
A60: Profit Before Tax: | B60: =B12-B59 | D60: Largest Expense: | E60: =MAX(E17:E56)
A61: Tax Amount: | B61: =IF(B60>0,B60*$B$11,0)
A62: Net Profit: | B62: =B60-B61
A63: Net Loss: | B63: =IF(B62<0,ABS(B62),0)
A64: Tip: | B64: Enter every receipt on its own row so the summaries and chart stay accurate.

Sheet Job 013
A1: Hammer Brick & Home LLC - Job Tracker
A3: Job Name:
A4: Client:
A5: Address:
A6: Start Date:
A7: End Date:
A9: Contract Price:
A10: Change Orders:
A11: Tax Rate:
A12: Total Budget: | B12: =B9+B10
A15: Expense Log (enter one line per receipt)
A16: Date | B16: Type | C16: Description | D16: Vendor | E16: Cost
A59: Total Expenses: | B59: =SUM(E17:E56) | D59: Most Expensive Item: | E59: =IFERROR(INDEX(C17:C56,MATCH(MAX(E17:E56),E17:E56,0)),"")
A60: Profit Before Tax: | B60: =B12-B59 | D60: Largest Expense: | E60: =MAX(E17:E56)
A61: Tax Amount: | B61: =IF(B60>0,B60*$B$11,0)
A62: Net Profit: | B62: =B60-B61
A63: Net Loss: | B63: =IF(B62<0,ABS(B62),0)
A64: Tip: | B64: Enter every receipt on its own row so the summaries and chart stay accurate.

Sheet Job 014
A1: Hammer Brick & Home LLC - Job Tracker
A3: Job Name:
A4: Client:
A5: Address:
A6: Start Date:
A7: End Date:
A9: Contract Price:
A10: Change Orders:
A11: Tax Rate:
A12: Total Budget: | B12: =B9+B10
A15: Expense Log (enter one line per receipt)
A16: Date | B16: Type | C16: Description | D16: Vendor | E16: Cost
A59: Total Expenses: | B59: =SUM(E17:E56) | D59: Most Expensive Item: | E59: =IFERROR(INDEX(C17:C56,MATCH(MAX(E17:E56),E17:E56,0)),"")
A60: Profit Before Tax: | B60: =B12-B59 | D60: Largest Expense: | E60: =MAX(E17:E56)
A61: Tax Amount: | B61: =IF(B60>0,B60*$B$11,0)
A62: Net Profit: | B62: =B60-B61
A63: Net Loss: | B63: =IF(B62<0,ABS(B62),0)
A64: Tip: | B64: Enter every receipt on its own row so the summaries and chart stay accurate.

Sheet Job 015
A1: Hammer Brick & Home LLC - Job Tracker
A3: Job Name:
A4: Client:
A5: Address:
A6: Start Date:
A7: End Date:
A9: Contract Price:
A10: Change Orders:
A11: Tax Rate:
A12: Total Budget: | B12: =B9+B10
A15: Expense Log (enter one line per receipt)
A16: Date | B16: Type | C16: Description | D16: Vendor | E16: Cost
A59: Total Expenses: | B59: =SUM(E17:E56) | D59: Most Expensive Item: | E59: =IFERROR(INDEX(C17:C56,MATCH(MAX(E17:E56),E17:E56,0)),"")
A60: Profit Before Tax: | B60: =B12-B59 | D60: Largest Expense: | E60: =MAX(E17:E56)
A61: Tax Amount: | B61: =IF(B60>0,B60*$B$11,0)
A62: Net Profit: | B62: =B60-B61
A63: Net Loss: | B63: =IF(B62<0,ABS(B62),0)
A64: Tip: | B64: Enter every receipt on its own row so the summaries and chart stay accurate.

Sheet Job 016
A1: Hammer Brick & Home LLC - Job Tracker
A3: Job Name:
A4: Client:
A5: Address:
A6: Start Date:
A7: End Date:
A9: Contract Price:
A10: Change Orders:
A11: Tax Rate:
A12: Total Budget: | B12: =B9+B10
A15: Expense Log (enter one line per receipt)
A16: Date | B16: Type | C16: Description | D16: Vendor | E16: Cost
A59: Total Expenses: | B59: =SUM(E17:E56) | D59: Most Expensive Item: | E59: =IFERROR(INDEX(C17:C56,MATCH(MAX(E17:E56),E17:E56,0)),"")
A60: Profit Before Tax: | B60: =B12-B59 | D60: Largest Expense: | E60: =MAX(E17:E56)
A61: Tax Amount: | B61: =IF(B60>0,B60*$B$11,0)
A62: Net Profit: | B62: =B60-B61
A63: Net Loss: | B63: =IF(B62<0,ABS(B62),0)
A64: Tip: | B64: Enter every receipt on its own row so the summaries and chart stay accurate.

Sheet Job 017
A1: Hammer Brick & Home LLC - Job Tracker
A3: Job Name:
A4: Client:
A5: Address:
A6: Start Date:
A7: End Date:
A9: Contract Price:
A10: Change Orders:
A11: Tax Rate:
A12: Total Budget: | B12: =B9+B10
A15: Expense Log (enter one line per receipt)
A16: Date | B16: Type | C16: Description | D16: Vendor | E16: Cost
A59: Total Expenses: | B59: =SUM(E17:E56) | D59: Most Expensive Item: | E59: =IFERROR(INDEX(C17:C56,MATCH(MAX(E17:E56),E17:E56,0)),"")
A60: Profit Before Tax: | B60: =B12-B59 | D60: Largest Expense: | E60: =MAX(E17:E56)
A61: Tax Amount: | B61: =IF(B60>0,B60*$B$11,0)
A62: Net Profit: | B62: =B60-B61
A63: Net Loss: | B63: =IF(B62<0,ABS(B62),0)
A64: Tip: | B64: Enter every receipt on its own row so the summaries and chart stay accurate.

Sheet Job 018
A1: Hammer Brick & Home LLC - Job Tracker
A3: Job Name:
A4: Client:
A5: Address:
A6: Start Date:
A7: End Date:
A9: Contract Price:
A10: Change Orders:
A11: Tax Rate:
A12: Total Budget: | B12: =B9+B10
A15: Expense Log (enter one line per receipt)
A16: Date | B16: Type | C16: Description | D16: Vendor | E16: Cost
A59: Total Expenses: | B59: =SUM(E17:E56) | D59: Most Expensive Item: | E59: =IFERROR(INDEX(C17:C56,MATCH(MAX(E17:E56),E17:E56,0)),"")
A60: Profit Before Tax: | B60: =B12-B59 | D60: Largest Expense: | E60: =MAX(E17:E56)
A61: Tax Amount: | B61: =IF(B60>0,B60*$B$11,0)
A62: Net Profit: | B62: =B60-B61
A63: Net Loss: | B63: =IF(B62<0,ABS(B62),0)
A64: Tip: | B64: Enter every receipt on its own row so the summaries and chart stay accurate.

Sheet Job 019
A1: Hammer Brick & Home LLC - Job Tracker
A3: Job Name:
A4: Client:
A5: Address:
A6: Start Date:
A7: End Date:
A9: Contract Price:
A10: Change Orders:
A11: Tax Rate:
A12: Total Budget: | B12: =B9+B10
A15: Expense Log (enter one line per receipt)
A16: Date | B16: Type | C16: Description | D16: Vendor | E16: Cost
A59: Total Expenses: | B59: =SUM(E17:E56) | D59: Most Expensive Item: | E59: =IFERROR(INDEX(C17:C56,MATCH(MAX(E17:E56),E17:E56,0)),"")
A60: Profit Before Tax: | B60: =B12-B59 | D60: Largest Expense: | E60: =MAX(E17:E56)
A61: Tax Amount: | B61: =IF(B60>0,B60*$B$11,0)
A62: Net Profit: | B62: =B60-B61
A63: Net Loss: | B63: =IF(B62<0,ABS(B62),0)
A64: Tip: | B64: Enter every receipt on its own row so the summaries and chart stay accurate.

Sheet Job 020
A1: Hammer Brick & Home LLC - Job Tracker
A3: Job Name:
A4: Client:
A5: Address:
A6: Start Date:
A7: End Date:
A9: Contract Price:
A10: Change Orders:
A11: Tax Rate:
A12: Total Budget: | B12: =B9+B10
A15: Expense Log (enter one line per receipt)
A16: Date | B16: Type | C16: Description | D16: Vendor | E16: Cost
A59: Total Expenses: | B59: =SUM(E17:E56) | D59: Most Expensive Item: | E59: =IFERROR(INDEX(C17:C56,MATCH(MAX(E17:E56),E17:E56,0)),"")
A60: Profit Before Tax: | B60: =B12-B59 | D60: Largest Expense: | E60: =MAX(E17:E56)
A61: Tax Amount: | B61: =IF(B60>0,B60*$B$11,0)
A62: Net Profit: | B62: =B60-B61
A63: Net Loss: | B63: =IF(B62<0,ABS(B62),0)
A64: Tip: | B64: Enter every receipt on its own row so the summaries and chart stay accurate.

Sheet Job 021
A1: Hammer Brick & Home LLC - Job Tracker
A3: Job Name:
A4: Client:
A5: Address:
A6: Start Date:
A7: End Date:
A9: Contract Price:
A10: Change Orders:
A11: Tax Rate:
A12: Total Budget: | B12: =B9+B10
A15: Expense Log (enter one line per receipt)
A16: Date | B16: Type | C16: Description | D16: Vendor | E16: Cost
A59: Total Expenses: | B59: =SUM(E17:E56) | D59: Most Expensive Item: | E59: =IFERROR(INDEX(C17:C56,MATCH(MAX(E17:E56),E17:E56,0)),"")
A60: Profit Before Tax: | B60: =B12-B59 | D60: Largest Expense: | E60: =MAX(E17:E56)
A61: Tax Amount: | B61: =IF(B60>0,B60*$B$11,0)
A62: Net Profit: | B62: =B60-B61
A63: Net Loss: | B63: =IF(B62<0,ABS(B62),0)
A64: Tip: | B64: Enter every receipt on its own row so the summaries and chart stay accurate.

Sheet Job 022
A1: Hammer Brick & Home LLC - Job Tracker
A3: Job Name:
A4: Client:
A5: Address:
A6: Start Date:
A7: End Date:
A9: Contract Price:
A10: Change Orders:
A11: Tax Rate:
A12: Total Budget: | B12: =B9+B10
A15: Expense Log (enter one line per receipt)
A16: Date | B16: Type | C16: Description | D16: Vendor | E16: Cost
A59: Total Expenses: | B59: =SUM(E17:E56) | D59: Most Expensive Item: | E59: =IFERROR(INDEX(C17:C56,MATCH(MAX(E17:E56),E17:E56,0)),"")
A60: Profit Before Tax: | B60: =B12-B59 | D60: Largest Expense: | E60: =MAX(E17:E56)
A61: Tax Amount: | B61: =IF(B60>0,B60*$B$11,0)
A62: Net Profit: | B62: =B60-B61
A63: Net Loss: | B63: =IF(B62<0,ABS(B62),0)
A64: Tip: | B64: Enter every receipt on its own row so the summaries and chart stay accurate.

Sheet Job 023
A1: Hammer Brick & Home LLC - Job Tracker
A3: Job Name:
A4: Client:
A5: Address:
A6: Start Date:
A7: End Date:
A9: Contract Price:
A10: Change Orders:
A11: Tax Rate:
A12: Total Budget: | B12: =B9+B10
A15: Expense Log (enter one line per receipt)
A16: Date | B16: Type | C16: Description | D16: Vendor | E16: Cost
A59: Total Expenses: | B59: =SUM(E17:E56) | D59: Most Expensive Item: | E59: =IFERROR(INDEX(C17:C56,MATCH(MAX(E17:E56),E17:E56,0)),"")
A60: Profit Before Tax: | B60: =B12-B59 | D60: Largest Expense: | E60: =MAX(E17:E56)
A61: Tax Amount: | B61: =IF(B60>0,B60*$B$11,0)
A62: Net Profit: | B62: =B60-B61
A63: Net Loss: | B63: =IF(B62<0,ABS(B62),0)
A64: Tip: | B64: Enter every receipt on its own row so the summaries and chart stay accurate.

Sheet Job 024
A1: Hammer Brick & Home LLC - Job Tracker
A3: Job Name:
A4: Client:
A5: Address:
A6: Start Date:
A7: End Date:
A9: Contract Price:
A10: Change Orders:
A11: Tax Rate:
A12: Total Budget: | B12: =B9+B10
A15: Expense Log (enter one line per receipt)
A16: Date | B16: Type | C16: Description | D16: Vendor | E16: Cost
A59: Total Expenses: | B59: =SUM(E17:E56) | D59: Most Expensive Item: | E59: =IFERROR(INDEX(C17:C56,MATCH(MAX(E17:E56),E17:E56,0)),"")
A60: Profit Before Tax: | B60: =B12-B59 | D60: Largest Expense: | E60: =MAX(E17:E56)
A61: Tax Amount: | B61: =IF(B60>0,B60*$B$11,0)
A62: Net Profit: | B62: =B60-B61
A63: Net Loss: | B63: =IF(B62<0,ABS(B62),0)
A64: Tip: | B64: Enter every receipt on its own row so the summaries and chart stay accurate.

Sheet Job 025
A1: Hammer Brick & Home LLC - Job Tracker
A3: Job Name:
A4: Client:
A5: Address:
A6: Start Date:
A7: End Date:
A9: Contract Price:
A10: Change Orders:
A11: Tax Rate:
A12: Total Budget: | B12: =B9+B10
A15: Expense Log (enter one line per receipt)
A16: Date | B16: Type | C16: Description | D16: Vendor | E16: Cost
A59: Total Expenses: | B59: =SUM(E17:E56) | D59: Most Expensive Item: | E59: =IFERROR(INDEX(C17:C56,MATCH(MAX(E17:E56),E17:E56,0)),"")
A60: Profit Before Tax: | B60: =B12-B59 | D60: Largest Expense: | E60: =MAX(E17:E56)
A61: Tax Amount: | B61: =IF(B60>0,B60*$B$11,0)
A62: Net Profit: | B62: =B60-B61
A63: Net Loss: | B63: =IF(B62<0,ABS(B62),0)
A64: Tip: | B64: Enter every receipt on its own row so the summaries and chart stay accurate.

Sheet Job 026
A1: Hammer Brick & Home LLC - Job Tracker
A3: Job Name:
A4: Client:
A5: Address:
A6: Start Date:
A7: End Date:
A9: Contract Price:
A10: Change Orders:
A11: Tax Rate:
A12: Total Budget: | B12: =B9+B10
A15: Expense Log (enter one line per receipt)
A16: Date | B16: Type | C16: Description | D16: Vendor | E16: Cost
A59: Total Expenses: | B59: =SUM(E17:E56) | D59: Most Expensive Item: | E59: =IFERROR(INDEX(C17:C56,MATCH(MAX(E17:E56),E17:E56,0)),"")
A60: Profit Before Tax: | B60: =B12-B59 | D60: Largest Expense: | E60: =MAX(E17:E56)
A61: Tax Amount: | B61: =IF(B60>0,B60*$B$11,0)
A62: Net Profit: | B62: =B60-B61
A63: Net Loss: | B63: =IF(B62<0,ABS(B62),0)
A64: Tip: | B64: Enter every receipt on its own row so the summaries and chart stay accurate.

Sheet Job 027
A1: Hammer Brick & Home LLC - Job Tracker
A3: Job Name:
A4: Client:
A5: Address:
A6: Start Date:
A7: End Date:
A9: Contract Price:
A10: Change Orders:
A11: Tax Rate:
A12: Total Budget: | B12: =B9+B10
A15: Expense Log (enter one line per receipt)
A16: Date | B16: Type | C16: Description | D16: Vendor | E16: Cost
A59: Total Expenses: | B59: =SUM(E17:E56) | D59: Most Expensive Item: | E59: =IFERROR(INDEX(C17:C56,MATCH(MAX(E17:E56),E17:E56,0)),"")
A60: Profit Before Tax: | B60: =B12-B59 | D60: Largest Expense: | E60: =MAX(E17:E56)
A61: Tax Amount: | B61: =IF(B60>0,B60*$B$11,0)
A62: Net Profit: | B62: =B60-B61
A63: Net Loss: | B63: =IF(B62<0,ABS(B62),0)
A64: Tip: | B64: Enter every receipt on its own row so the summaries and chart stay accurate.

Sheet Job 028
A1: Hammer Brick & Home LLC - Job Tracker
A3: Job Name:
A4: Client:
A5: Address:
A6: Start Date:
A7: End Date:
A9: Contract Price:
A10: Change Orders:
A11: Tax Rate:
A12: Total Budget: | B12: =B9+B10
A15: Expense Log (enter one line per receipt)
A16: Date | B16: Type | C16: Description | D16: Vendor | E16: Cost
A59: Total Expenses: | B59: =SUM(E17:E56) | D59: Most Expensive Item: | E59: =IFERROR(INDEX(C17:C56,MATCH(MAX(E17:E56),E17:E56,0)),"")
A60: Profit Before Tax: | B60: =B12-B59 | D60: Largest Expense: | E60: =MAX(E17:E56)
A61: Tax Amount: | B61: =IF(B60>0,B60*$B$11,0)
A62: Net Profit: | B62: =B60-B61
A63: Net Loss: | B63: =IF(B62<0,ABS(B62),0)
A64: Tip: | B64: Enter every receipt on its own row so the summaries and chart stay accurate.

Sheet Job 029
A1: Hammer Brick & Home LLC - Job Tracker
A3: Job Name:
A4: Client:
A5: Address:
A6: Start Date:
A7: End Date:
A9: Contract Price:
A10: Change Orders:
A11: Tax Rate:
A12: Total Budget: | B12: =B9+B10
A15: Expense Log (enter one line per receipt)
A16: Date | B16: Type | C16: Description | D16: Vendor | E16: Cost
A59: Total Expenses: | B59: =SUM(E17:E56) | D59: Most Expensive Item: | E59: =IFERROR(INDEX(C17:C56,MATCH(MAX(E17:E56),E17:E56,0)),"")
A60: Profit Before Tax: | B60: =B12-B59 | D60: Largest Expense: | E60: =MAX(E17:E56)
A61: Tax Amount: | B61: =IF(B60>0,B60*$B$11,0)
A62: Net Profit: | B62: =B60-B61
A63: Net Loss: | B63: =IF(B62<0,ABS(B62),0)
A64: Tip: | B64: Enter every receipt on its own row so the summaries and chart stay accurate.

Sheet Job 030
A1: Hammer Brick & Home LLC - Job Tracker
A3: Job Name:
A4: Client:
A5: Address:
A6: Start Date:
A7: End Date:
A9: Contract Price:
A10: Change Orders:
A11: Tax Rate:
A12: Total Budget: | B12: =B9+B10
A15: Expense Log (enter one line per receipt)
A16: Date | B16: Type | C16: Description | D16: Vendor | E16: Cost
A59: Total Expenses: | B59: =SUM(E17:E56) | D59: Most Expensive Item: | E59: =IFERROR(INDEX(C17:C56,MATCH(MAX(E17:E56),E17:E56,0)),"")
A60: Profit Before Tax: | B60: =B12-B59 | D60: Largest Expense: | E60: =MAX(E17:E56)
A61: Tax Amount: | B61: =IF(B60>0,B60*$B$11,0)
A62: Net Profit: | B62: =B60-B61
A63: Net Loss: | B63: =IF(B62<0,ABS(B62),0)
A64: Tip: | B64: Enter every receipt on its own row so the summaries and chart stay accurate.

Sheet Job 031
A1: Hammer Brick & Home LLC - Job Tracker
A3: Job Name:
A4: Client:
A5: Address:
A6: Start Date:
A7: End Date:
A9: Contract Price:
A10: Change Orders:
A11: Tax Rate:
A12: Total Budget: | B12: =B9+B10
A15: Expense Log (enter one line per receipt)
A16: Date | B16: Type | C16: Description | D16: Vendor | E16: Cost
A59: Total Expenses: | B59: =SUM(E17:E56) | D59: Most Expensive Item: | E59: =IFERROR(INDEX(C17:C56,MATCH(MAX(E17:E56),E17:E56,0)),"")
A60: Profit Before Tax: | B60: =B12-B59 | D60: Largest Expense: | E60: =MAX(E17:E56)
A61: Tax Amount: | B61: =IF(B60>0,B60*$B$11,0)
A62: Net Profit: | B62: =B60-B61
A63: Net Loss: | B63: =IF(B62<0,ABS(B62),0)
A64: Tip: | B64: Enter every receipt on its own row so the summaries and chart stay accurate.

Sheet Job 032
A1: Hammer Brick & Home LLC - Job Tracker
A3: Job Name:
A4: Client:
A5: Address:
A6: Start Date:
A7: End Date:
A9: Contract Price:
A10: Change Orders:
A11: Tax Rate:
A12: Total Budget: | B12: =B9+B10
A15: Expense Log (enter one line per receipt)
A16: Date | B16: Type | C16: Description | D16: Vendor | E16: Cost
A59: Total Expenses: | B59: =SUM(E17:E56) | D59: Most Expensive Item: | E59: =IFERROR(INDEX(C17:C56,MATCH(MAX(E17:E56),E17:E56,0)),"")
A60: Profit Before Tax: | B60: =B12-B59 | D60: Largest Expense: | E60: =MAX(E17:E56)
A61: Tax Amount: | B61: =IF(B60>0,B60*$B$11,0)
A62: Net Profit: | B62: =B60-B61
A63: Net Loss: | B63: =IF(B62<0,ABS(B62),0)
A64: Tip: | B64: Enter every receipt on its own row so the summaries and chart stay accurate.

Sheet Job 033
A1: Hammer Brick & Home LLC - Job Tracker
A3: Job Name:
A4: Client:
A5: Address:
A6: Start Date:
A7: End Date:
A9: Contract Price:
A10: Change Orders:
A11: Tax Rate:
A12: Total Budget: | B12: =B9+B10
A15: Expense Log (enter one line per receipt)
A16: Date | B16: Type | C16: Description | D16: Vendor | E16: Cost
A59: Total Expenses: | B59: =SUM(E17:E56) | D59: Most Expensive Item: | E59: =IFERROR(INDEX(C17:C56,MATCH(MAX(E17:E56),E17:E56,0)),"")
A60: Profit Before Tax: | B60: =B12-B59 | D60: Largest Expense: | E60: =MAX(E17:E56)
A61: Tax Amount: | B61: =IF(B60>0,B60*$B$11,0)
A62: Net Profit: | B62: =B60-B61
A63: Net Loss: | B63: =IF(B62<0,ABS(B62),0)
A64: Tip: | B64: Enter every receipt on its own row so the summaries and chart stay accurate.

Sheet Job 034
A1: Hammer Brick & Home LLC - Job Tracker
A3: Job Name:
A4: Client:
A5: Address:
A6: Start Date:
A7: End Date:
A9: Contract Price:
A10: Change Orders:
A11: Tax Rate:
A12: Total Budget: | B12: =B9+B10
A15: Expense Log (enter one line per receipt)
A16: Date | B16: Type | C16: Description | D16: Vendor | E16: Cost
A59: Total Expenses: | B59: =SUM(E17:E56) | D59: Most Expensive Item: | E59: =IFERROR(INDEX(C17:C56,MATCH(MAX(E17:E56),E17:E56,0)),"")
A60: Profit Before Tax: | B60: =B12-B59 | D60: Largest Expense: | E60: =MAX(E17:E56)
A61: Tax Amount: | B61: =IF(B60>0,B60*$B$11,0)
A62: Net Profit: | B62: =B60-B61
A63: Net Loss: | B63: =IF(B62<0,ABS(B62),0)
A64: Tip: | B64: Enter every receipt on its own row so the summaries and chart stay accurate.

Sheet Job 035
A1: Hammer Brick & Home LLC - Job Tracker
A3: Job Name:
A4: Client:
A5: Address:
A6: Start Date:
A7: End Date:
A9: Contract Price:
A10: Change Orders:
A11: Tax Rate:
A12: Total Budget: | B12: =B9+B10
A15: Expense Log (enter one line per receipt)
A16: Date | B16: Type | C16: Description | D16: Vendor | E16: Cost
A59: Total Expenses: | B59: =SUM(E17:E56) | D59: Most Expensive Item: | E59: =IFERROR(INDEX(C17:C56,MATCH(MAX(E17:E56),E17:E56,0)),"")
A60: Profit Before Tax: | B60: =B12-B59 | D60: Largest Expense: | E60: =MAX(E17:E56)
A61: Tax Amount: | B61: =IF(B60>0,B60*$B$11,0)
A62: Net Profit: | B62: =B60-B61
A63: Net Loss: | B63: =IF(B62<0,ABS(B62),0)
A64: Tip: | B64: Enter every receipt on its own row so the summaries and chart stay accurate.

Sheet Job 036
A1: Hammer Brick & Home LLC - Job Tracker
A3: Job Name:
A4: Client:
A5: Address:
A6: Start Date:
A7: End Date:
A9: Contract Price:
A10: Change Orders:
A11: Tax Rate:
A12: Total Budget: | B12: =B9+B10
A15: Expense Log (enter one line per receipt)
A16: Date | B16: Type | C16: Description | D16: Vendor | E16: Cost
A59: Total Expenses: | B59: =SUM(E17:E56) | D59: Most Expensive Item: | E59: =IFERROR(INDEX(C17:C56,MATCH(MAX(E17:E56),E17:E56,0)),"")
A60: Profit Before Tax: | B60: =B12-B59 | D60: Largest Expense: | E60: =MAX(E17:E56)
A61: Tax Amount: | B61: =IF(B60>0,B60*$B$11,0)
A62: Net Profit: | B62: =B60-B61
A63: Net Loss: | B63: =IF(B62<0,ABS(B62),0)
A64: Tip: | B64: Enter every receipt on its own row so the summaries and chart stay accurate.

Sheet Job 037
A1: Hammer Brick & Home LLC - Job Tracker
A3: Job Name:
A4: Client:
A5: Address:
A6: Start Date:
A7: End Date:
A9: Contract Price:
A10: Change Orders:
A11: Tax Rate:
A12: Total Budget: | B12: =B9+B10
A15: Expense Log (enter one line per receipt)
A16: Date | B16: Type | C16: Description | D16: Vendor | E16: Cost
A59: Total Expenses: | B59: =SUM(E17:E56) | D59: Most Expensive Item: | E59: =IFERROR(INDEX(C17:C56,MATCH(MAX(E17:E56),E17:E56,0)),"")
A60: Profit Before Tax: | B60: =B12-B59 | D60: Largest Expense: | E60: =MAX(E17:E56)
A61: Tax Amount: | B61: =IF(B60>0,B60*$B$11,0)
A62: Net Profit: | B62: =B60-B61
A63: Net Loss: | B63: =IF(B62<0,ABS(B62),0)
A64: Tip: | B64: Enter every receipt on its own row so the summaries and chart stay accurate.

Sheet Job 038
A1: Hammer Brick & Home LLC - Job Tracker
A3: Job Name:
A4: Client:
A5: Address:
A6: Start Date:
A7: End Date:
A9: Contract Price:
A10: Change Orders:
A11: Tax Rate:
A12: Total Budget: | B12: =B9+B10
A15: Expense Log (enter one line per receipt)
A16: Date | B16: Type | C16: Description | D16: Vendor | E16: Cost
A59: Total Expenses: | B59: =SUM(E17:E56) | D59: Most Expensive Item: | E59: =IFERROR(INDEX(C17:C56,MATCH(MAX(E17:E56),E17:E56,0)),"")
A60: Profit Before Tax: | B60: =B12-B59 | D60: Largest Expense: | E60: =MAX(E17:E56)
A61: Tax Amount: | B61: =IF(B60>0,B60*$B$11,0)
A62: Net Profit: | B62: =B60-B61
A63: Net Loss: | B63: =IF(B62<0,ABS(B62),0)
A64: Tip: | B64: Enter every receipt on its own row so the summaries and chart stay accurate.

Sheet Job 039
A1: Hammer Brick & Home LLC - Job Tracker
A3: Job Name:
A4: Client:
A5: Address:
A6: Start Date:
A7: End Date:
A9: Contract Price:
A10: Change Orders:
A11: Tax Rate:
A12: Total Budget: | B12: =B9+B10
A15: Expense Log (enter one line per receipt)
A16: Date | B16: Type | C16: Description | D16: Vendor | E16: Cost
A59: Total Expenses: | B59: =SUM(E17:E56) | D59: Most Expensive Item: | E59: =IFERROR(INDEX(C17:C56,MATCH(MAX(E17:E56),E17:E56,0)),"")
A60: Profit Before Tax: | B60: =B12-B59 | D60: Largest Expense: | E60: =MAX(E17:E56)
A61: Tax Amount: | B61: =IF(B60>0,B60*$B$11,0)
A62: Net Profit: | B62: =B60-B61
A63: Net Loss: | B63: =IF(B62<0,ABS(B62),0)
A64: Tip: | B64: Enter every receipt on its own row so the summaries and chart stay accurate.

Sheet Job 040
A1: Hammer Brick & Home LLC - Job Tracker
A3: Job Name:
A4: Client:
A5: Address:
A6: Start Date:
A7: End Date:
A9: Contract Price:
A10: Change Orders:
A11: Tax Rate:
A12: Total Budget: | B12: =B9+B10
A15: Expense Log (enter one line per receipt)
A16: Date | B16: Type | C16: Description | D16: Vendor | E16: Cost
A59: Total Expenses: | B59: =SUM(E17:E56) | D59: Most Expensive Item: | E59: =IFERROR(INDEX(C17:C56,MATCH(MAX(E17:E56),E17:E56,0)),"")
A60: Profit Before Tax: | B60: =B12-B59 | D60: Largest Expense: | E60: =MAX(E17:E56)
A61: Tax Amount: | B61: =IF(B60>0,B60*$B$11,0)
A62: Net Profit: | B62: =B60-B61
A63: Net Loss: | B63: =IF(B62<0,ABS(B62),0)
A64: Tip: | B64: Enter every receipt on its own row so the summaries and chart stay accurate.

Sheet Job 041
A1: Hammer Brick & Home LLC - Job Tracker
A3: Job Name:
A4: Client:
A5: Address:
A6: Start Date:
A7: End Date:
A9: Contract Price:
A10: Change Orders:
A11: Tax Rate:
A12: Total Budget: | B12: =B9+B10
A15: Expense Log (enter one line per receipt)
A16: Date | B16: Type | C16: Description | D16: Vendor | E16: Cost
A59: Total Expenses: | B59: =SUM(E17:E56) | D59: Most Expensive Item: | E59: =IFERROR(INDEX(C17:C56,MATCH(MAX(E17:E56),E17:E56,0)),"")
A60: Profit Before Tax: | B60: =B12-B59 | D60: Largest Expense: | E60: =MAX(E17:E56)
A61: Tax Amount: | B61: =IF(B60>0,B60*$B$11,0)
A62: Net Profit: | B62: =B60-B61
A63: Net Loss: | B63: =IF(B62<0,ABS(B62),0)
A64: Tip: | B64: Enter every receipt on its own row so the summaries and chart stay accurate.

Sheet Job 042
A1: Hammer Brick & Home LLC - Job Tracker
A3: Job Name:
A4: Client:
A5: Address:
A6: Start Date:
A7: End Date:
A9: Contract Price:
A10: Change Orders:
A11: Tax Rate:
A12: Total Budget: | B12: =B9+B10
A15: Expense Log (enter one line per receipt)
A16: Date | B16: Type | C16: Description | D16: Vendor | E16: Cost
A59: Total Expenses: | B59: =SUM(E17:E56) | D59: Most Expensive Item: | E59: =IFERROR(INDEX(C17:C56,MATCH(MAX(E17:E56),E17:E56,0)),"")
A60: Profit Before Tax: | B60: =B12-B59 | D60: Largest Expense: | E60: =MAX(E17:E56)
A61: Tax Amount: | B61: =IF(B60>0,B60*$B$11,0)
A62: Net Profit: | B62: =B60-B61
A63: Net Loss: | B63: =IF(B62<0,ABS(B62),0)
A64: Tip: | B64: Enter every receipt on its own row so the summaries and chart stay accurate.

Sheet Job 043
A1: Hammer Brick & Home LLC - Job Tracker
A3: Job Name:
A4: Client:
A5: Address:
A6: Start Date:
A7: End Date:
A9: Contract Price:
A10: Change Orders:
A11: Tax Rate:
A12: Total Budget: | B12: =B9+B10
A15: Expense Log (enter one line per receipt)
A16: Date | B16: Type | C16: Description | D16: Vendor | E16: Cost
A59: Total Expenses: | B59: =SUM(E17:E56) | D59: Most Expensive Item: | E59: =IFERROR(INDEX(C17:C56,MATCH(MAX(E17:E56),E17:E56,0)),"")
A60: Profit Before Tax: | B60: =B12-B59 | D60: Largest Expense: | E60: =MAX(E17:E56)
A61: Tax Amount: | B61: =IF(B60>0,B60*$B$11,0)
A62: Net Profit: | B62: =B60-B61
A63: Net Loss: | B63: =IF(B62<0,ABS(B62),0)
A64: Tip: | B64: Enter every receipt on its own row so the summaries and chart stay accurate.

Sheet Job 044
A1: Hammer Brick & Home LLC - Job Tracker
A3: Job Name:
A4: Client:
A5: Address:
A6: Start Date:
A7: End Date:
A9: Contract Price:
A10: Change Orders:
A11: Tax Rate:
A12: Total Budget: | B12: =B9+B10
A15: Expense Log (enter one line per receipt)
A16: Date | B16: Type | C16: Description | D16: Vendor | E16: Cost
A59: Total Expenses: | B59: =SUM(E17:E56) | D59: Most Expensive Item: | E59: =IFERROR(INDEX(C17:C56,MATCH(MAX(E17:E56),E17:E56,0)),"")
A60: Profit Before Tax: | B60: =B12-B59 | D60: Largest Expense: | E60: =MAX(E17:E56)
A61: Tax Amount: | B61: =IF(B60>0,B60*$B$11,0)
A62: Net Profit: | B62: =B60-B61
A63: Net Loss: | B63: =IF(B62<0,ABS(B62),0)
A64: Tip: | B64: Enter every receipt on its own row so the summaries and chart stay accurate.

Sheet Job 045
A1: Hammer Brick & Home LLC - Job Tracker
A3: Job Name:
A4: Client:
A5: Address:
A6: Start Date:
A7: End Date:
A9: Contract Price:
A10: Change Orders:
A11: Tax Rate:
A12: Total Budget: | B12: =B9+B10
A15: Expense Log (enter one line per receipt)
A16: Date | B16: Type | C16: Description | D16: Vendor | E16: Cost
A59: Total Expenses: | B59: =SUM(E17:E56) | D59: Most Expensive Item: | E59: =IFERROR(INDEX(C17:C56,MATCH(MAX(E17:E56),E17:E56,0)),"")
A60: Profit Before Tax: | B60: =B12-B59 | D60: Largest Expense: | E60: =MAX(E17:E56)
A61: Tax Amount: | B61: =IF(B60>0,B60*$B$11,0)
A62: Net Profit: | B62: =B60-B61
A63: Net Loss: | B63: =IF(B62<0,ABS(B62),0)
A64: Tip: | B64: Enter every receipt on its own row so the summaries and chart stay accurate.

Sheet Job 046
A1: Hammer Brick & Home LLC - Job Tracker
A3: Job Name:
A4: Client:
A5: Address:
A6: Start Date:
A7: End Date:
A9: Contract Price:
A10: Change Orders:
A11: Tax Rate:
A12: Total Budget: | B12: =B9+B10
A15: Expense Log (enter one line per receipt)
A16: Date | B16: Type | C16: Description | D16: Vendor | E16: Cost
A59: Total Expenses: | B59: =SUM(E17:E56) | D59: Most Expensive Item: | E59: =IFERROR(INDEX(C17:C56,MATCH(MAX(E17:E56),E17:E56,0)),"")
A60: Profit Before Tax: | B60: =B12-B59 | D60: Largest Expense: | E60: =MAX(E17:E56)
A61: Tax Amount: | B61: =IF(B60>0,B60*$B$11,0)
A62: Net Profit: | B62: =B60-B61
A63: Net Loss: | B63: =IF(B62<0,ABS(B62),0)
A64: Tip: | B64: Enter every receipt on its own row so the summaries and chart stay accurate.

Sheet Job 047
A1: Hammer Brick & Home LLC - Job Tracker
A3: Job Name:
A4: Client:
A5: Address:
A6: Start Date:
A7: End Date:
A9: Contract Price:
A10: Change Orders:
A11: Tax Rate:
A12: Total Budget: | B12: =B9+B10
A15: Expense Log (enter one line per receipt)
A16: Date | B16: Type | C16: Description | D16: Vendor | E16: Cost
A59: Total Expenses: | B59: =SUM(E17:E56) | D59: Most Expensive Item: | E59: =IFERROR(INDEX(C17:C56,MATCH(MAX(E17:E56),E17:E56,0)),"")
A60: Profit Before Tax: | B60: =B12-B59 | D60: Largest Expense: | E60: =MAX(E17:E56)
A61: Tax Amount: | B61: =IF(B60>0,B60*$B$11,0)
A62: Net Profit: | B62: =B60-B61
A63: Net Loss: | B63: =IF(B62<0,ABS(B62),0)
A64: Tip: | B64: Enter every receipt on its own row so the summaries and chart stay accurate.

Sheet Job 048
A1: Hammer Brick & Home LLC - Job Tracker
A3: Job Name:
A4: Client:
A5: Address:
A6: Start Date:
A7: End Date:
A9: Contract Price:
A10: Change Orders:
A11: Tax Rate:
A12: Total Budget: | B12: =B9+B10
A15: Expense Log (enter one line per receipt)
A16: Date | B16: Type | C16: Description | D16: Vendor | E16: Cost
A59: Total Expenses: | B59: =SUM(E17:E56) | D59: Most Expensive Item: | E59: =IFERROR(INDEX(C17:C56,MATCH(MAX(E17:E56),E17:E56,0)),"")
A60: Profit Before Tax: | B60: =B12-B59 | D60: Largest Expense: | E60: =MAX(E17:E56)
A61: Tax Amount: | B61: =IF(B60>0,B60*$B$11,0)
A62: Net Profit: | B62: =B60-B61
A63: Net Loss: | B63: =IF(B62<0,ABS(B62),0)
A64: Tip: | B64: Enter every receipt on its own row so the summaries and chart stay accurate.

Sheet Job 049
A1: Hammer Brick & Home LLC - Job Tracker
A3: Job Name:
A4: Client:
A5: Address:
A6: Start Date:
A7: End Date:
A9: Contract Price:
A10: Change Orders:
A11: Tax Rate:
A12: Total Budget: | B12: =B9+B10
A15: Expense Log (enter one line per receipt)
A16: Date | B16: Type | C16: Description | D16: Vendor | E16: Cost
A59: Total Expenses: | B59: =SUM(E17:E56) | D59: Most Expensive Item: | E59: =IFERROR(INDEX(C17:C56,MATCH(MAX(E17:E56),E17:E56,0)),"")
A60: Profit Before Tax: | B60: =B12-B59 | D60: Largest Expense: | E60: =MAX(E17:E56)
A61: Tax Amount: | B61: =IF(B60>0,B60*$B$11,0)
A62: Net Profit: | B62: =B60-B61
A63: Net Loss: | B63: =IF(B62<0,ABS(B62),0)
A64: Tip: | B64: Enter every receipt on its own row so the summaries and chart stay accurate.

Sheet Job 050
A1: Hammer Brick & Home LLC - Job Tracker
A3: Job Name:
A4: Client:
A5: Address:
A6: Start Date:
A7: End Date:
A9: Contract Price:
A10: Change Orders:
A11: Tax Rate:
A12: Total Budget: | B12: =B9+B10
A15: Expense Log (enter one line per receipt)
A16: Date | B16: Type | C16: Description | D16: Vendor | E16: Cost
A59: Total Expenses: | B59: =SUM(E17:E56) | D59: Most Expensive Item: | E59: =IFERROR(INDEX(C17:C56,MATCH(MAX(E17:E56),E17:E56,0)),"")
A60: Profit Before Tax: | B60: =B12-B59 | D60: Largest Expense: | E60: =MAX(E17:E56)
A61: Tax Amount: | B61: =IF(B60>0,B60*$B$11,0)
A62: Net Profit: | B62: =B60-B61
A63: Net Loss: | B63: =IF(B62<0,ABS(B62),0)
A64: Tip: | B64: Enter every receipt on its own row so the summaries and chart stay accurate.

Sheet Job 051
A1: Hammer Brick & Home LLC - Job Tracker
A3: Job Name:
A4: Client:
A5: Address:
A6: Start Date:
A7: End Date:
A9: Contract Price:
A10: Change Orders:
A11: Tax Rate:
A12: Total Budget: | B12: =B9+B10
A15: Expense Log (enter one line per receipt)
A16: Date | B16: Type | C16: Description | D16: Vendor | E16: Cost
A59: Total Expenses: | B59: =SUM(E17:E56) | D59: Most Expensive Item: | E59: =IFERROR(INDEX(C17:C56,MATCH(MAX(E17:E56),E17:E56,0)),"")
A60: Profit Before Tax: | B60: =B12-B59 | D60: Largest Expense: | E60: =MAX(E17:E56)
A61: Tax Amount: | B61: =IF(B60>0,B60*$B$11,0)
A62: Net Profit: | B62: =B60-B61
A63: Net Loss: | B63: =IF(B62<0,ABS(B62),0)
A64: Tip: | B64: Enter every receipt on its own row so the summaries and chart stay accurate.

Sheet Job 052
A1: Hammer Brick & Home LLC - Job Tracker
A3: Job Name:
A4: Client:
A5: Address:
A6: Start Date:
A7: End Date:
A9: Contract Price:
A10: Change Orders:
A11: Tax Rate:
A12: Total Budget: | B12: =B9+B10
A15: Expense Log (enter one line per receipt)
A16: Date | B16: Type | C16: Description | D16: Vendor | E16: Cost
A59: Total Expenses: | B59: =SUM(E17:E56) | D59: Most Expensive Item: | E59: =IFERROR(INDEX(C17:C56,MATCH(MAX(E17:E56),E17:E56,0)),"")
A60: Profit Before Tax: | B60: =B12-B59 | D60: Largest Expense: | E60: =MAX(E17:E56)
A61: Tax Amount: | B61: =IF(B60>0,B60*$B$11,0)
A62: Net Profit: | B62: =B60-B61
A63: Net Loss: | B63: =IF(B62<0,ABS(B62),0)
A64: Tip: | B64: Enter every receipt on its own row so the summaries and chart stay accurate.

Sheet Job 053
A1: Hammer Brick & Home LLC - Job Tracker
A3: Job Name:
A4: Client:
A5: Address:
A6: Start Date:
A7: End Date:
A9: Contract Price:
A10: Change Orders:
A11: Tax Rate:
A12: Total Budget: | B12: =B9+B10
A15: Expense Log (enter one line per receipt)
A16: Date | B16: Type | C16: Description | D16: Vendor | E16: Cost
A59: Total Expenses: | B59: =SUM(E17:E56) | D59: Most Expensive Item: | E59: =IFERROR(INDEX(C17:C56,MATCH(MAX(E17:E56),E17:E56,0)),"")
A60: Profit Before Tax: | B60: =B12-B59 | D60: Largest Expense: | E60: =MAX(E17:E56)
A61: Tax Amount: | B61: =IF(B60>0,B60*$B$11,0)
A62: Net Profit: | B62: =B60-B61
A63: Net Loss: | B63: =IF(B62<0,ABS(B62),0)
A64: Tip: | B64: Enter every receipt on its own row so the summaries and chart stay accurate.

Sheet Job 054
A1: Hammer Brick & Home LLC - Job Tracker
A3: Job Name:
A4: Client:
A5: Address:
A6: Start Date:
A7: End Date:
A9: Contract Price:
A10: Change Orders:
A11: Tax Rate:
A12: Total Budget: | B12: =B9+B10
A15: Expense Log (enter one line per receipt)
A16: Date | B16: Type | C16: Description | D16: Vendor | E16: Cost
A59: Total Expenses: | B59: =SUM(E17:E56) | D59: Most Expensive Item: | E59: =IFERROR(INDEX(C17:C56,MATCH(MAX(E17:E56),E17:E56,0)),"")
A60: Profit Before Tax: | B60: =B12-B59 | D60: Largest Expense: | E60: =MAX(E17:E56)
A61: Tax Amount: | B61: =IF(B60>0,B60*$B$11,0)
A62: Net Profit: | B62: =B60-B61
A63: Net Loss: | B63: =IF(B62<0,ABS(B62),0)
A64: Tip: | B64: Enter every receipt on its own row so the summaries and chart stay accurate.

Sheet Job 055
A1: Hammer Brick & Home LLC - Job Tracker
A3: Job Name:
A4: Client:
A5: Address:
A6: Start Date:
A7: End Date:
A9: Contract Price:
A10: Change Orders:
A11: Tax Rate:
A12: Total Budget: | B12: =B9+B10
A15: Expense Log (enter one line per receipt)
A16: Date | B16: Type | C16: Description | D16: Vendor | E16: Cost
A59: Total Expenses: | B59: =SUM(E17:E56) | D59: Most Expensive Item: | E59: =IFERROR(INDEX(C17:C56,MATCH(MAX(E17:E56),E17:E56,0)),"")
A60: Profit Before Tax: | B60: =B12-B59 | D60: Largest Expense: | E60: =MAX(E17:E56)
A61: Tax Amount: | B61: =IF(B60>0,B60*$B$11,0)
A62: Net Profit: | B62: =B60-B61
A63: Net Loss: | B63: =IF(B62<0,ABS(B62),0)
A64: Tip: | B64: Enter every receipt on its own row so the summaries and chart stay accurate.

Sheet Job 056
A1: Hammer Brick & Home LLC - Job Tracker
A3: Job Name:
A4: Client:
A5: Address:
A6: Start Date:
A7: End Date:
A9: Contract Price:
A10: Change Orders:
A11: Tax Rate:
A12: Total Budget: | B12: =B9+B10
A15: Expense Log (enter one line per receipt)
A16: Date | B16: Type | C16: Description | D16: Vendor | E16: Cost
A59: Total Expenses: | B59: =SUM(E17:E56) | D59: Most Expensive Item: | E59: =IFERROR(INDEX(C17:C56,MATCH(MAX(E17:E56),E17:E56,0)),"")
A60: Profit Before Tax: | B60: =B12-B59 | D60: Largest Expense: | E60: =MAX(E17:E56)
A61: Tax Amount: | B61: =IF(B60>0,B60*$B$11,0)
A62: Net Profit: | B62: =B60-B61
A63: Net Loss: | B63: =IF(B62<0,ABS(B62),0)
A64: Tip: | B64: Enter every receipt on its own row so the summaries and chart stay accurate.

Sheet Job 057
A1: Hammer Brick & Home LLC - Job Tracker
A3: Job Name:
A4: Client:
A5: Address:
A6: Start Date:
A7: End Date:
A9: Contract Price:
A10: Change Orders:
A11: Tax Rate:
A12: Total Budget: | B12: =B9+B10
A15: Expense Log (enter one line per receipt)
A16: Date | B16: Type | C16: Description | D16: Vendor | E16: Cost
A59: Total Expenses: | B59: =SUM(E17:E56) | D59: Most Expensive Item: | E59: =IFERROR(INDEX(C17:C56,MATCH(MAX(E17:E56),E17:E56,0)),"")
A60: Profit Before Tax: | B60: =B12-B59 | D60: Largest Expense: | E60: =MAX(E17:E56)
A61: Tax Amount: | B61: =IF(B60>0,B60*$B$11,0)
A62: Net Profit: | B62: =B60-B61
A63: Net Loss: | B63: =IF(B62<0,ABS(B62),0)
A64: Tip: | B64: Enter every receipt on its own row so the summaries and chart stay accurate.

Sheet Job 058
A1: Hammer Brick & Home LLC - Job Tracker
A3: Job Name:
A4: Client:
A5: Address:
A6: Start Date:
A7: End Date:
A9: Contract Price:
A10: Change Orders:
A11: Tax Rate:
A12: Total Budget: | B12: =B9+B10
A15: Expense Log (enter one line per receipt)
A16: Date | B16: Type | C16: Description | D16: Vendor | E16: Cost
A59: Total Expenses: | B59: =SUM(E17:E56) | D59: Most Expensive Item: | E59: =IFERROR(INDEX(C17:C56,MATCH(MAX(E17:E56),E17:E56,0)),"")
A60: Profit Before Tax: | B60: =B12-B59 | D60: Largest Expense: | E60: =MAX(E17:E56)
A61: Tax Amount: | B61: =IF(B60>0,B60*$B$11,0)
A62: Net Profit: | B62: =B60-B61
A63: Net Loss: | B63: =IF(B62<0,ABS(B62),0)
A64: Tip: | B64: Enter every receipt on its own row so the summaries and chart stay accurate.

Sheet Job 059
A1: Hammer Brick & Home LLC - Job Tracker
A3: Job Name:
A4: Client:
A5: Address:
A6: Start Date:
A7: End Date:
A9: Contract Price:
A10: Change Orders:
A11: Tax Rate:
A12: Total Budget: | B12: =B9+B10
A15: Expense Log (enter one line per receipt)
A16: Date | B16: Type | C16: Description | D16: Vendor | E16: Cost
A59: Total Expenses: | B59: =SUM(E17:E56) | D59: Most Expensive Item: | E59: =IFERROR(INDEX(C17:C56,MATCH(MAX(E17:E56),E17:E56,0)),"")
A60: Profit Before Tax: | B60: =B12-B59 | D60: Largest Expense: | E60: =MAX(E17:E56)
A61: Tax Amount: | B61: =IF(B60>0,B60*$B$11,0)
A62: Net Profit: | B62: =B60-B61
A63: Net Loss: | B63: =IF(B62<0,ABS(B62),0)
A64: Tip: | B64: Enter every receipt on its own row so the summaries and chart stay accurate.

Sheet Job 060
A1: Hammer Brick & Home LLC - Job Tracker
A3: Job Name:
A4: Client:
A5: Address:
A6: Start Date:
A7: End Date:
A9: Contract Price:
A10: Change Orders:
A11: Tax Rate:
A12: Total Budget: | B12: =B9+B10
A15: Expense Log (enter one line per receipt)
A16: Date | B16: Type | C16: Description | D16: Vendor | E16: Cost
A59: Total Expenses: | B59: =SUM(E17:E56) | D59: Most Expensive Item: | E59: =IFERROR(INDEX(C17:C56,MATCH(MAX(E17:E56),E17:E56,0)),"")
A60: Profit Before Tax: | B60: =B12-B59 | D60: Largest Expense: | E60: =MAX(E17:E56)
A61: Tax Amount: | B61: =IF(B60>0,B60*$B$11,0)
A62: Net Profit: | B62: =B60-B61
A63: Net Loss: | B63: =IF(B62<0,ABS(B62),0)
A64: Tip: | B64: Enter every receipt on its own row so the summaries and chart stay accurate.

Sheet Job 061
A1: Hammer Brick & Home LLC - Job Tracker
A3: Job Name:
A4: Client:
A5: Address:
A6: Start Date:
A7: End Date:
A9: Contract Price:
A10: Change Orders:
A11: Tax Rate:
A12: Total Budget: | B12: =B9+B10
A15: Expense Log (enter one line per receipt)
A16: Date | B16: Type | C16: Description | D16: Vendor | E16: Cost
A59: Total Expenses: | B59: =SUM(E17:E56) | D59: Most Expensive Item: | E59: =IFERROR(INDEX(C17:C56,MATCH(MAX(E17:E56),E17:E56,0)),"")
A60: Profit Before Tax: | B60: =B12-B59 | D60: Largest Expense: | E60: =MAX(E17:E56)
A61: Tax Amount: | B61: =IF(B60>0,B60*$B$11,0)
A62: Net Profit: | B62: =B60-B61
A63: Net Loss: | B63: =IF(B62<0,ABS(B62),0)
A64: Tip: | B64: Enter every receipt on its own row so the summaries and chart stay accurate.

Sheet Job 062
A1: Hammer Brick & Home LLC - Job Tracker
A3: Job Name:
A4: Client:
A5: Address:
A6: Start Date:
A7: End Date:
A9: Contract Price:
A10: Change Orders:
A11: Tax Rate:
A12: Total Budget: | B12: =B9+B10
A15: Expense Log (enter one line per receipt)
A16: Date | B16: Type | C16: Description | D16: Vendor | E16: Cost
A59: Total Expenses: | B59: =SUM(E17:E56) | D59: Most Expensive Item: | E59: =IFERROR(INDEX(C17:C56,MATCH(MAX(E17:E56),E17:E56,0)),"")
A60: Profit Before Tax: | B60: =B12-B59 | D60: Largest Expense: | E60: =MAX(E17:E56)
A61: Tax Amount: | B61: =IF(B60>0,B60*$B$11,0)
A62: Net Profit: | B62: =B60-B61
A63: Net Loss: | B63: =IF(B62<0,ABS(B62),0)
A64: Tip: | B64: Enter every receipt on its own row so the summaries and chart stay accurate.

Sheet Job 063
A1: Hammer Brick & Home LLC - Job Tracker
A3: Job Name:
A4: Client:
A5: Address:
A6: Start Date:
A7: End Date:
A9: Contract Price:
A10: Change Orders:
A11: Tax Rate:
A12: Total Budget: | B12: =B9+B10
A15: Expense Log (enter one line per receipt)
A16: Date | B16: Type | C16: Description | D16: Vendor | E16: Cost
A59: Total Expenses: | B59: =SUM(E17:E56) | D59: Most Expensive Item: | E59: =IFERROR(INDEX(C17:C56,MATCH(MAX(E17:E56),E17:E56,0)),"")
A60: Profit Before Tax: | B60: =B12-B59 | D60: Largest Expense: | E60: =MAX(E17:E56)
A61: Tax Amount: | B61: =IF(B60>0,B60*$B$11,0)
A62: Net Profit: | B62: =B60-B61
A63: Net Loss: | B63: =IF(B62<0,ABS(B62),0)
A64: Tip: | B64: Enter every receipt on its own row so the summaries and chart stay accurate.

Sheet Job 064
A1: Hammer Brick & Home LLC - Job Tracker
A3: Job Name:
A4: Client:
A5: Address:
A6: Start Date:
A7: End Date:
A9: Contract Price:
A10: Change Orders:
A11: Tax Rate:
A12: Total Budget: | B12: =B9+B10
A15: Expense Log (enter one line per receipt)
A16: Date | B16: Type | C16: Description | D16: Vendor | E16: Cost
A59: Total Expenses: | B59: =SUM(E17:E56) | D59: Most Expensive Item: | E59: =IFERROR(INDEX(C17:C56,MATCH(MAX(E17:E56),E17:E56,0)),"")
A60: Profit Before Tax: | B60: =B12-B59 | D60: Largest Expense: | E60: =MAX(E17:E56)
A61: Tax Amount: | B61: =IF(B60>0,B60*$B$11,0)
A62: Net Profit: | B62: =B60-B61
A63: Net Loss: | B63: =IF(B62<0,ABS(B62),0)
A64: Tip: | B64: Enter every receipt on its own row so the summaries and chart stay accurate.

Sheet Job 065
A1: Hammer Brick & Home LLC - Job Tracker
A3: Job Name:
A4: Client:
A5: Address:
A6: Start Date:
A7: End Date:
A9: Contract Price:
A10: Change Orders:
A11: Tax Rate:
A12: Total Budget: | B12: =B9+B10
A15: Expense Log (enter one line per receipt)
A16: Date | B16: Type | C16: Description | D16: Vendor | E16: Cost
A59: Total Expenses: | B59: =SUM(E17:E56) | D59: Most Expensive Item: | E59: =IFERROR(INDEX(C17:C56,MATCH(MAX(E17:E56),E17:E56,0)),"")
A60: Profit Before Tax: | B60: =B12-B59 | D60: Largest Expense: | E60: =MAX(E17:E56)
A61: Tax Amount: | B61: =IF(B60>0,B60*$B$11,0)
A62: Net Profit: | B62: =B60-B61
A63: Net Loss: | B63: =IF(B62<0,ABS(B62),0)
A64: Tip: | B64: Enter every receipt on its own row so the summaries and chart stay accurate.

Sheet Job 066
A1: Hammer Brick & Home LLC - Job Tracker
A3: Job Name:
A4: Client:
A5: Address:
A6: Start Date:
A7: End Date:
A9: Contract Price:
A10: Change Orders:
A11: Tax Rate:
A12: Total Budget: | B12: =B9+B10
A15: Expense Log (enter one line per receipt)
A16: Date | B16: Type | C16: Description | D16: Vendor | E16: Cost
A59: Total Expenses: | B59: =SUM(E17:E56) | D59: Most Expensive Item: | E59: =IFERROR(INDEX(C17:C56,MATCH(MAX(E17:E56),E17:E56,0)),"")
A60: Profit Before Tax: | B60: =B12-B59 | D60: Largest Expense: | E60: =MAX(E17:E56)
A61: Tax Amount: | B61: =IF(B60>0,B60*$B$11,0)
A62: Net Profit: | B62: =B60-B61
A63: Net Loss: | B63: =IF(B62<0,ABS(B62),0)
A64: Tip: | B64: Enter every receipt on its own row so the summaries and chart stay accurate.

Sheet Job 067
A1: Hammer Brick & Home LLC - Job Tracker
A3: Job Name:
A4: Client:
A5: Address:
A6: Start Date:
A7: End Date:
A9: Contract Price:
A10: Change Orders:
A11: Tax Rate:
A12: Total Budget: | B12: =B9+B10
A15: Expense Log (enter one line per receipt)
A16: Date | B16: Type | C16: Description | D16: Vendor | E16: Cost
A59: Total Expenses: | B59: =SUM(E17:E56) | D59: Most Expensive Item: | E59: =IFERROR(INDEX(C17:C56,MATCH(MAX(E17:E56),E17:E56,0)),"")
A60: Profit Before Tax: | B60: =B12-B59 | D60: Largest Expense: | E60: =MAX(E17:E56)
A61: Tax Amount: | B61: =IF(B60>0,B60*$B$11,0)
A62: Net Profit: | B62: =B60-B61
A63: Net Loss: | B63: =IF(B62<0,ABS(B62),0)
A64: Tip: | B64: Enter every receipt on its own row so the summaries and chart stay accurate.

Sheet Job 068
A1: Hammer Brick & Home LLC - Job Tracker
A3: Job Name:
A4: Client:
A5: Address:
A6: Start Date:
A7: End Date:
A9: Contract Price:
A10: Change Orders:
A11: Tax Rate:
A12: Total Budget: | B12: =B9+B10
A15: Expense Log (enter one line per receipt)
A16: Date | B16: Type | C16: Description | D16: Vendor | E16: Cost
A59: Total Expenses: | B59: =SUM(E17:E56) | D59: Most Expensive Item: | E59: =IFERROR(INDEX(C17:C56,MATCH(MAX(E17:E56),E17:E56,0)),"")
A60: Profit Before Tax: | B60: =B12-B59 | D60: Largest Expense: | E60: =MAX(E17:E56)
A61: Tax Amount: | B61: =IF(B60>0,B60*$B$11,0)
A62: Net Profit: | B62: =B60-B61
A63: Net Loss: | B63: =IF(B62<0,ABS(B62),0)
A64: Tip: | B64: Enter every receipt on its own row so the summaries and chart stay accurate.

Sheet Job 069
A1: Hammer Brick & Home LLC - Job Tracker
A3: Job Name:
A4: Client:
A5: Address:
A6: Start Date:
A7: End Date:
A9: Contract Price:
A10: Change Orders:
A11: Tax Rate:
A12: Total Budget: | B12: =B9+B10
A15: Expense Log (enter one line per receipt)
A16: Date | B16: Type | C16: Description | D16: Vendor | E16: Cost
A59: Total Expenses: | B59: =SUM(E17:E56) | D59: Most Expensive Item: | E59: =IFERROR(INDEX(C17:C56,MATCH(MAX(E17:E56),E17:E56,0)),"")
A60: Profit Before Tax: | B60: =B12-B59 | D60: Largest Expense: | E60: =MAX(E17:E56)
A61: Tax Amount: | B61: =IF(B60>0,B60*$B$11,0)
A62: Net Profit: | B62: =B60-B61
A63: Net Loss: | B63: =IF(B62<0,ABS(B62),0)
A64: Tip: | B64: Enter every receipt on its own row so the summaries and chart stay accurate.

Sheet Job 070
A1: Hammer Brick & Home LLC - Job Tracker
A3: Job Name:
A4: Client:
A5: Address:
A6: Start Date:
A7: End Date:
A9: Contract Price:
A10: Change Orders:
A11: Tax Rate:
A12: Total Budget: | B12: =B9+B10
A15: Expense Log (enter one line per receipt)
A16: Date | B16: Type | C16: Description | D16: Vendor | E16: Cost
A59: Total Expenses: | B59: =SUM(E17:E56) | D59: Most Expensive Item: | E59: =IFERROR(INDEX(C17:C56,MATCH(MAX(E17:E56),E17:E56,0)),"")
A60: Profit Before Tax: | B60: =B12-B59 | D60: Largest Expense: | E60: =MAX(E17:E56)
A61: Tax Amount: | B61: =IF(B60>0,B60*$B$11,0)
A62: Net Profit: | B62: =B60-B61
A63: Net Loss: | B63: =IF(B62<0,ABS(B62),0)
A64: Tip: | B64: Enter every receipt on its own row so the summaries and chart stay accurate.

Sheet Job 071
A1: Hammer Brick & Home LLC - Job Tracker
A3: Job Name:
A4: Client:
A5: Address:
A6: Start Date:
A7: End Date:
A9: Contract Price:
A10: Change Orders:
A11: Tax Rate:
A12: Total Budget: | B12: =B9+B10
A15: Expense Log (enter one line per receipt)
A16: Date | B16: Type | C16: Description | D16: Vendor | E16: Cost
A59: Total Expenses: | B59: =SUM(E17:E56) | D59: Most Expensive Item: | E59: =IFERROR(INDEX(C17:C56,MATCH(MAX(E17:E56),E17:E56,0)),"")
A60: Profit Before Tax: | B60: =B12-B59 | D60: Largest Expense: | E60: =MAX(E17:E56)
A61: Tax Amount: | B61: =IF(B60>0,B60*$B$11,0)
A62: Net Profit: | B62: =B60-B61
A63: Net Loss: | B63: =IF(B62<0,ABS(B62),0)
A64: Tip: | B64: Enter every receipt on its own row so the summaries and chart stay accurate.

Sheet Job 072
A1: Hammer Brick & Home LLC - Job Tracker
A3: Job Name:
A4: Client:
A5: Address:
A6: Start Date:
A7: End Date:
A9: Contract Price:
A10: Change Orders:
A11: Tax Rate:
A12: Total Budget: | B12: =B9+B10
A15: Expense Log (enter one line per receipt)
A16: Date | B16: Type | C16: Description | D16: Vendor | E16: Cost
A59: Total Expenses: | B59: =SUM(E17:E56) | D59: Most Expensive Item: | E59: =IFERROR(INDEX(C17:C56,MATCH(MAX(E17:E56),E17:E56,0)),"")
A60: Profit Before Tax: | B60: =B12-B59 | D60: Largest Expense: | E60: =MAX(E17:E56)
A61: Tax Amount: | B61: =IF(B60>0,B60*$B$11,0)
A62: Net Profit: | B62: =B60-B61
A63: Net Loss: | B63: =IF(B62<0,ABS(B62),0)
A64: Tip: | B64: Enter every receipt on its own row so the summaries and chart stay accurate.

Sheet Job 073
A1: Hammer Brick & Home LLC - Job Tracker
A3: Job Name:
A4: Client:
A5: Address:
A6: Start Date:
A7: End Date:
A9: Contract Price:
A10: Change Orders:
A11: Tax Rate:
A12: Total Budget: | B12: =B9+B10
A15: Expense Log (enter one line per receipt)
A16: Date | B16: Type | C16: Description | D16: Vendor | E16: Cost
A59: Total Expenses: | B59: =SUM(E17:E56) | D59: Most Expensive Item: | E59: =IFERROR(INDEX(C17:C56,MATCH(MAX(E17:E56),E17:E56,0)),"")
A60: Profit Before Tax: | B60: =B12-B59 | D60: Largest Expense: | E60: =MAX(E17:E56)
A61: Tax Amount: | B61: =IF(B60>0,B60*$B$11,0)
A62: Net Profit: | B62: =B60-B61
A63: Net Loss: | B63: =IF(B62<0,ABS(B62),0)
A64: Tip: | B64: Enter every receipt on its own row so the summaries and chart stay accurate.

Sheet Job 074
A1: Hammer Brick & Home LLC - Job Tracker
A3: Job Name:
A4: Client:
A5: Address:
A6: Start Date:
A7: End Date:
A9: Contract Price:
A10: Change Orders:
A11: Tax Rate:
A12: Total Budget: | B12: =B9+B10
A15: Expense Log (enter one line per receipt)
A16: Date | B16: Type | C16: Description | D16: Vendor | E16: Cost
A59: Total Expenses: | B59: =SUM(E17:E56) | D59: Most Expensive Item: | E59: =IFERROR(INDEX(C17:C56,MATCH(MAX(E17:E56),E17:E56,0)),"")
A60: Profit Before Tax: | B60: =B12-B59 | D60: Largest Expense: | E60: =MAX(E17:E56)
A61: Tax Amount: | B61: =IF(B60>0,B60*$B$11,0)
A62: Net Profit: | B62: =B60-B61
A63: Net Loss: | B63: =IF(B62<0,ABS(B62),0)
A64: Tip: | B64: Enter every receipt on its own row so the summaries and chart stay accurate.

Sheet Job 075
A1: Hammer Brick & Home LLC - Job Tracker
A3: Job Name:
A4: Client:
A5: Address:
A6: Start Date:
A7: End Date:
A9: Contract Price:
A10: Change Orders:
A11: Tax Rate:
A12: Total Budget: | B12: =B9+B10
A15: Expense Log (enter one line per receipt)
A16: Date | B16: Type | C16: Description | D16: Vendor | E16: Cost
A59: Total Expenses: | B59: =SUM(E17:E56) | D59: Most Expensive Item: | E59: =IFERROR(INDEX(C17:C56,MATCH(MAX(E17:E56),E17:E56,0)),"")
A60: Profit Before Tax: | B60: =B12-B59 | D60: Largest Expense: | E60: =MAX(E17:E56)
A61: Tax Amount: | B61: =IF(B60>0,B60*$B$11,0)
A62: Net Profit: | B62: =B60-B61
A63: Net Loss: | B63: =IF(B62<0,ABS(B62),0)
A64: Tip: | B64: Enter every receipt on its own row so the summaries and chart stay accurate.

Sheet Job 076
A1: Hammer Brick & Home LLC - Job Tracker
A3: Job Name:
A4: Client:
A5: Address:
A6: Start Date:
A7: End Date:
A9: Contract Price:
A10: Change Orders:
A11: Tax Rate:
A12: Total Budget: | B12: =B9+B10
A15: Expense Log (enter one line per receipt)
A16: Date | B16: Type | C16: Description | D16: Vendor | E16: Cost
A59: Total Expenses: | B59: =SUM(E17:E56) | D59: Most Expensive Item: | E59: =IFERROR(INDEX(C17:C56,MATCH(MAX(E17:E56),E17:E56,0)),"")
A60: Profit Before Tax: | B60: =B12-B59 | D60: Largest Expense: | E60: =MAX(E17:E56)
A61: Tax Amount: | B61: =IF(B60>0,B60*$B$11,0)
A62: Net Profit: | B62: =B60-B61
A63: Net Loss: | B63: =IF(B62<0,ABS(B62),0)
A64: Tip: | B64: Enter every receipt on its own row so the summaries and chart stay accurate.

Sheet Job 077
A1: Hammer Brick & Home LLC - Job Tracker
A3: Job Name:
A4: Client:
A5: Address:
A6: Start Date:
A7: End Date:
A9: Contract Price:
A10: Change Orders:
A11: Tax Rate:
A12: Total Budget: | B12: =B9+B10
A15: Expense Log (enter one line per receipt)
A16: Date | B16: Type | C16: Description | D16: Vendor | E16: Cost
A59: Total Expenses: | B59: =SUM(E17:E56) | D59: Most Expensive Item: | E59: =IFERROR(INDEX(C17:C56,MATCH(MAX(E17:E56),E17:E56,0)),"")
A60: Profit Before Tax: | B60: =B12-B59 | D60: Largest Expense: | E60: =MAX(E17:E56)
A61: Tax Amount: | B61: =IF(B60>0,B60*$B$11,0)
A62: Net Profit: | B62: =B60-B61
A63: Net Loss: | B63: =IF(B62<0,ABS(B62),0)
A64: Tip: | B64: Enter every receipt on its own row so the summaries and chart stay accurate.

Sheet Job 078
A1: Hammer Brick & Home LLC - Job Tracker
A3: Job Name:
A4: Client:
A5: Address:
A6: Start Date:
A7: End Date:
A9: Contract Price:
A10: Change Orders:
A11: Tax Rate:
A12: Total Budget: | B12: =B9+B10
A15: Expense Log (enter one line per receipt)
A16: Date | B16: Type | C16: Description | D16: Vendor | E16: Cost
A59: Total Expenses: | B59: =SUM(E17:E56) | D59: Most Expensive Item: | E59: =IFERROR(INDEX(C17:C56,MATCH(MAX(E17:E56),E17:E56,0)),"")
A60: Profit Before Tax: | B60: =B12-B59 | D60: Largest Expense: | E60: =MAX(E17:E56)
A61: Tax Amount: | B61: =IF(B60>0,B60*$B$11,0)
A62: Net Profit: | B62: =B60-B61
A63: Net Loss: | B63: =IF(B62<0,ABS(B62),0)
A64: Tip: | B64: Enter every receipt on its own row so the summaries and chart stay accurate.

Sheet Job 079
A1: Hammer Brick & Home LLC - Job Tracker
A3: Job Name:
A4: Client:
A5: Address:
A6: Start Date:
A7: End Date:
A9: Contract Price:
A10: Change Orders:
A11: Tax Rate:
A12: Total Budget: | B12: =B9+B10
A15: Expense Log (enter one line per receipt)
A16: Date | B16: Type | C16: Description | D16: Vendor | E16: Cost
A59: Total Expenses: | B59: =SUM(E17:E56) | D59: Most Expensive Item: | E59: =IFERROR(INDEX(C17:C56,MATCH(MAX(E17:E56),E17:E56,0)),"")
A60: Profit Before Tax: | B60: =B12-B59 | D60: Largest Expense: | E60: =MAX(E17:E56)
A61: Tax Amount: | B61: =IF(B60>0,B60*$B$11,0)
A62: Net Profit: | B62: =B60-B61
A63: Net Loss: | B63: =IF(B62<0,ABS(B62),0)
A64: Tip: | B64: Enter every receipt on its own row so the summaries and chart stay accurate.

Sheet Job 080
A1: Hammer Brick & Home LLC - Job Tracker
A3: Job Name:
A4: Client:
A5: Address:
A6: Start Date:
A7: End Date:
A9: Contract Price:
A10: Change Orders:
A11: Tax Rate:
A12: Total Budget: | B12: =B9+B10
A15: Expense Log (enter one line per receipt)
A16: Date | B16: Type | C16: Description | D16: Vendor | E16: Cost
A59: Total Expenses: | B59: =SUM(E17:E56) | D59: Most Expensive Item: | E59: =IFERROR(INDEX(C17:C56,MATCH(MAX(E17:E56),E17:E56,0)),"")
A60: Profit Before Tax: | B60: =B12-B59 | D60: Largest Expense: | E60: =MAX(E17:E56)
A61: Tax Amount: | B61: =IF(B60>0,B60*$B$11,0)
A62: Net Profit: | B62: =B60-B61
A63: Net Loss: | B63: =IF(B62<0,ABS(B62),0)
A64: Tip: | B64: Enter every receipt on its own row so the summaries and chart stay accurate.

Sheet Job 081
A1: Hammer Brick & Home LLC - Job Tracker
A3: Job Name:
A4: Client:
A5: Address:
A6: Start Date:
A7: End Date:
A9: Contract Price:
A10: Change Orders:
A11: Tax Rate:
A12: Total Budget: | B12: =B9+B10
A15: Expense Log (enter one line per receipt)
A16: Date | B16: Type | C16: Description | D16: Vendor | E16: Cost
A59: Total Expenses: | B59: =SUM(E17:E56) | D59: Most Expensive Item: | E59: =IFERROR(INDEX(C17:C56,MATCH(MAX(E17:E56),E17:E56,0)),"")
A60: Profit Before Tax: | B60: =B12-B59 | D60: Largest Expense: | E60: =MAX(E17:E56)
A61: Tax Amount: | B61: =IF(B60>0,B60*$B$11,0)
A62: Net Profit: | B62: =B60-B61
A63: Net Loss: | B63: =IF(B62<0,ABS(B62),0)
A64: Tip: | B64: Enter every receipt on its own row so the summaries and chart stay accurate.

Sheet Job 082
A1: Hammer Brick & Home LLC - Job Tracker
A3: Job Name:
A4: Client:
A5: Address:
A6: Start Date:
A7: End Date:
A9: Contract Price:
A10: Change Orders:
A11: Tax Rate:
A12: Total Budget: | B12: =B9+B10
A15: Expense Log (enter one line per receipt)
A16: Date | B16: Type | C16: Description | D16: Vendor | E16: Cost
A59: Total Expenses: | B59: =SUM(E17:E56) | D59: Most Expensive Item: | E59: =IFERROR(INDEX(C17:C56,MATCH(MAX(E17:E56),E17:E56,0)),"")
A60: Profit Before Tax: | B60: =B12-B59 | D60: Largest Expense: | E60: =MAX(E17:E56)
A61: Tax Amount: | B61: =IF(B60>0,B60*$B$11,0)
A62: Net Profit: | B62: =B60-B61
A63: Net Loss: | B63: =IF(B62<0,ABS(B62),0)
A64: Tip: | B64: Enter every receipt on its own row so the summaries and chart stay accurate.

Sheet Job 083
A1: Hammer Brick & Home LLC - Job Tracker
A3: Job Name:
A4: Client:
A5: Address:
A6: Start Date:
A7: End Date:
A9: Contract Price:
A10: Change Orders:
A11: Tax Rate:
A12: Total Budget: | B12: =B9+B10
A15: Expense Log (enter one line per receipt)
A16: Date | B16: Type | C16: Description | D16: Vendor | E16: Cost
A59: Total Expenses: | B59: =SUM(E17:E56) | D59: Most Expensive Item: | E59: =IFERROR(INDEX(C17:C56,MATCH(MAX(E17:E56),E17:E56,0)),"")
A60: Profit Before Tax: | B60: =B12-B59 | D60: Largest Expense: | E60: =MAX(E17:E56)
A61: Tax Amount: | B61: =IF(B60>0,B60*$B$11,0)
A62: Net Profit: | B62: =B60-B61
A63: Net Loss: | B63: =IF(B62<0,ABS(B62),0)
A64: Tip: | B64: Enter every receipt on its own row so the summaries and chart stay accurate.

Sheet Job 084
A1: Hammer Brick & Home LLC - Job Tracker
A3: Job Name:
A4: Client:
A5: Address:
A6: Start Date:
A7: End Date:
A9: Contract Price:
A10: Change Orders:
A11: Tax Rate:
A12: Total Budget: | B12: =B9+B10
A15: Expense Log (enter one line per receipt)
A16: Date | B16: Type | C16: Description | D16: Vendor | E16: Cost
A59: Total Expenses: | B59: =SUM(E17:E56) | D59: Most Expensive Item: | E59: =IFERROR(INDEX(C17:C56,MATCH(MAX(E17:E56),E17:E56,0)),"")
A60: Profit Before Tax: | B60: =B12-B59 | D60: Largest Expense: | E60: =MAX(E17:E56)
A61: Tax Amount: | B61: =IF(B60>0,B60*$B$11,0)
A62: Net Profit: | B62: =B60-B61
A63: Net Loss: | B63: =IF(B62<0,ABS(B62),0)
A64: Tip: | B64: Enter every receipt on its own row so the summaries and chart stay accurate.

Sheet Job 085
A1: Hammer Brick & Home LLC - Job Tracker
A3: Job Name:
A4: Client:
A5: Address:
A6: Start Date:
A7: End Date:
A9: Contract Price:
A10: Change Orders:
A11: Tax Rate:
A12: Total Budget: | B12: =B9+B10
A15: Expense Log (enter one line per receipt)
A16: Date | B16: Type | C16: Description | D16: Vendor | E16: Cost
A59: Total Expenses: | B59: =SUM(E17:E56) | D59: Most Expensive Item: | E59: =IFERROR(INDEX(C17:C56,MATCH(MAX(E17:E56),E17:E56,0)),"")
A60: Profit Before Tax: | B60: =B12-B59 | D60: Largest Expense: | E60: =MAX(E17:E56)
A61: Tax Amount: | B61: =IF(B60>0,B60*$B$11,0)
A62: Net Profit: | B62: =B60-B61
A63: Net Loss: | B63: =IF(B62<0,ABS(B62),0)
A64: Tip: | B64: Enter every receipt on its own row so the summaries and chart stay accurate.

Sheet Job 086
A1: Hammer Brick & Home LLC - Job Tracker
A3: Job Name:
A4: Client:
A5: Address:
A6: Start Date:
A7: End Date:
A9: Contract Price:
A10: Change Orders:
A11: Tax Rate:
A12: Total Budget: | B12: =B9+B10
A15: Expense Log (enter one line per receipt)
A16: Date | B16: Type | C16: Description | D16: Vendor | E16: Cost
A59: Total Expenses: | B59: =SUM(E17:E56) | D59: Most Expensive Item: | E59: =IFERROR(INDEX(C17:C56,MATCH(MAX(E17:E56),E17:E56,0)),"")
A60: Profit Before Tax: | B60: =B12-B59 | D60: Largest Expense: | E60: =MAX(E17:E56)
A61: Tax Amount: | B61: =IF(B60>0,B60*$B$11,0)
A62: Net Profit: | B62: =B60-B61
A63: Net Loss: | B63: =IF(B62<0,ABS(B62),0)
A64: Tip: | B64: Enter every receipt on its own row so the summaries and chart stay accurate.

Sheet Job 087
A1: Hammer Brick & Home LLC - Job Tracker
A3: Job Name:
A4: Client:
A5: Address:
A6: Start Date:
A7: End Date:
A9: Contract Price:
A10: Change Orders:
A11: Tax Rate:
A12: Total Budget: | B12: =B9+B10
A15: Expense Log (enter one line per receipt)
A16: Date | B16: Type | C16: Description | D16: Vendor | E16: Cost
A59: Total Expenses: | B59: =SUM(E17:E56) | D59: Most Expensive Item: | E59: =IFERROR(INDEX(C17:C56,MATCH(MAX(E17:E56),E17:E56,0)),"")
A60: Profit Before Tax: | B60: =B12-B59 | D60: Largest Expense: | E60: =MAX(E17:E56)
A61: Tax Amount: | B61: =IF(B60>0,B60*$B$11,0)
A62: Net Profit: | B62: =B60-B61
A63: Net Loss: | B63: =IF(B62<0,ABS(B62),0)
A64: Tip: | B64: Enter every receipt on its own row so the summaries and chart stay accurate.

Sheet Job 088
A1: Hammer Brick & Home LLC - Job Tracker
A3: Job Name:
A4: Client:
A5: Address:
A6: Start Date:
A7: End Date:
A9: Contract Price:
A10: Change Orders:
A11: Tax Rate:
A12: Total Budget: | B12: =B9+B10
A15: Expense Log (enter one line per receipt)
A16: Date | B16: Type | C16: Description | D16: Vendor | E16: Cost
A59: Total Expenses: | B59: =SUM(E17:E56) | D59: Most Expensive Item: | E59: =IFERROR(INDEX(C17:C56,MATCH(MAX(E17:E56),E17:E56,0)),"")
A60: Profit Before Tax: | B60: =B12-B59 | D60: Largest Expense: | E60: =MAX(E17:E56)
A61: Tax Amount: | B61: =IF(B60>0,B60*$B$11,0)
A62: Net Profit: | B62: =B60-B61
A63: Net Loss: | B63: =IF(B62<0,ABS(B62),0)
A64: Tip: | B64: Enter every receipt on its own row so the summaries and chart stay accurate.

Sheet Job 089
A1: Hammer Brick & Home LLC - Job Tracker
A3: Job Name:
A4: Client:
A5: Address:
A6: Start Date:
A7: End Date:
A9: Contract Price:
A10: Change Orders:
A11: Tax Rate:
A12: Total Budget: | B12: =B9+B10
A15: Expense Log (enter one line per receipt)
A16: Date | B16: Type | C16: Description | D16: Vendor | E16: Cost
A59: Total Expenses: | B59: =SUM(E17:E56) | D59: Most Expensive Item: | E59: =IFERROR(INDEX(C17:C56,MATCH(MAX(E17:E56),E17:E56,0)),"")
A60: Profit Before Tax: | B60: =B12-B59 | D60: Largest Expense: | E60: =MAX(E17:E56)
A61: Tax Amount: | B61: =IF(B60>0,B60*$B$11,0)
A62: Net Profit: | B62: =B60-B61
A63: Net Loss: | B63: =IF(B62<0,ABS(B62),0)
A64: Tip: | B64: Enter every receipt on its own row so the summaries and chart stay accurate.

Sheet Job 090
A1: Hammer Brick & Home LLC - Job Tracker
A3: Job Name:
A4: Client:
A5: Address:
A6: Start Date:
A7: End Date:
A9: Contract Price:
A10: Change Orders:
A11: Tax Rate:
A12: Total Budget: | B12: =B9+B10
A15: Expense Log (enter one line per receipt)
A16: Date | B16: Type | C16: Description | D16: Vendor | E16: Cost
A59: Total Expenses: | B59: =SUM(E17:E56) | D59: Most Expensive Item: | E59: =IFERROR(INDEX(C17:C56,MATCH(MAX(E17:E56),E17:E56,0)),"")
A60: Profit Before Tax: | B60: =B12-B59 | D60: Largest Expense: | E60: =MAX(E17:E56)
A61: Tax Amount: | B61: =IF(B60>0,B60*$B$11,0)
A62: Net Profit: | B62: =B60-B61
A63: Net Loss: | B63: =IF(B62<0,ABS(B62),0)
A64: Tip: | B64: Enter every receipt on its own row so the summaries and chart stay accurate.

Sheet Job 091
A1: Hammer Brick & Home LLC - Job Tracker
A3: Job Name:
A4: Client:
A5: Address:
A6: Start Date:
A7: End Date:
A9: Contract Price:
A10: Change Orders:
A11: Tax Rate:
A12: Total Budget: | B12: =B9+B10
A15: Expense Log (enter one line per receipt)
A16: Date | B16: Type | C16: Description | D16: Vendor | E16: Cost
A59: Total Expenses: | B59: =SUM(E17:E56) | D59: Most Expensive Item: | E59: =IFERROR(INDEX(C17:C56,MATCH(MAX(E17:E56),E17:E56,0)),"")
A60: Profit Before Tax: | B60: =B12-B59 | D60: Largest Expense: | E60: =MAX(E17:E56)
A61: Tax Amount: | B61: =IF(B60>0,B60*$B$11,0)
A62: Net Profit: | B62: =B60-B61
A63: Net Loss: | B63: =IF(B62<0,ABS(B62),0)
A64: Tip: | B64: Enter every receipt on its own row so the summaries and chart stay accurate.

Sheet Job 092
A1: Hammer Brick & Home LLC - Job Tracker
A3: Job Name:
A4: Client:
A5: Address:
A6: Start Date:
A7: End Date:
A9: Contract Price:
A10: Change Orders:
A11: Tax Rate:
A12: Total Budget: | B12: =B9+B10
A15: Expense Log (enter one line per receipt)
A16: Date | B16: Type | C16: Description | D16: Vendor | E16: Cost
A59: Total Expenses: | B59: =SUM(E17:E56) | D59: Most Expensive Item: | E59: =IFERROR(INDEX(C17:C56,MATCH(MAX(E17:E56),E17:E56,0)),"")
A60: Profit Before Tax: | B60: =B12-B59 | D60: Largest Expense: | E60: =MAX(E17:E56)
A61: Tax Amount: | B61: =IF(B60>0,B60*$B$11,0)
A62: Net Profit: | B62: =B60-B61
A63: Net Loss: | B63: =IF(B62<0,ABS(B62),0)
A64: Tip: | B64: Enter every receipt on its own row so the summaries and chart stay accurate.

Sheet Job 093
A1: Hammer Brick & Home LLC - Job Tracker
A3: Job Name:
A4: Client:
A5: Address:
A6: Start Date:
A7: End Date:
A9: Contract Price:
A10: Change Orders:
A11: Tax Rate:
A12: Total Budget: | B12: =B9+B10
A15: Expense Log (enter one line per receipt)
A16: Date | B16: Type | C16: Description | D16: Vendor | E16: Cost
A59: Total Expenses: | B59: =SUM(E17:E56) | D59: Most Expensive Item: | E59: =IFERROR(INDEX(C17:C56,MATCH(MAX(E17:E56),E17:E56,0)),"")
A60: Profit Before Tax: | B60: =B12-B59 | D60: Largest Expense: | E60: =MAX(E17:E56)
A61: Tax Amount: | B61: =IF(B60>0,B60*$B$11,0)
A62: Net Profit: | B62: =B60-B61
A63: Net Loss: | B63: =IF(B62<0,ABS(B62),0)
A64: Tip: | B64: Enter every receipt on its own row so the summaries and chart stay accurate.

Sheet Job 094
A1: Hammer Brick & Home LLC - Job Tracker
A3: Job Name:
A4: Client:
A5: Address:
A6: Start Date:
A7: End Date:
A9: Contract Price:
A10: Change Orders:
A11: Tax Rate:
A12: Total Budget: | B12: =B9+B10
A15: Expense Log (enter one line per receipt)
A16: Date | B16: Type | C16: Description | D16: Vendor | E16: Cost
A59: Total Expenses: | B59: =SUM(E17:E56) | D59: Most Expensive Item: | E59: =IFERROR(INDEX(C17:C56,MATCH(MAX(E17:E56),E17:E56,0)),"")
A60: Profit Before Tax: | B60: =B12-B59 | D60: Largest Expense: | E60: =MAX(E17:E56)
A61: Tax Amount: | B61: =IF(B60>0,B60*$B$11,0)
A62: Net Profit: | B62: =B60-B61
A63: Net Loss: | B63: =IF(B62<0,ABS(B62),0)
A64: Tip: | B64: Enter every receipt on its own row so the summaries and chart stay accurate.

Sheet Job 095
A1: Hammer Brick & Home LLC - Job Tracker
A3: Job Name:
A4: Client:
A5: Address:
A6: Start Date:
A7: End Date:
A9: Contract Price:
A10: Change Orders:
A11: Tax Rate:
A12: Total Budget: | B12: =B9+B10
A15: Expense Log (enter one line per receipt)
A16: Date | B16: Type | C16: Description | D16: Vendor | E16: Cost
A59: Total Expenses: | B59: =SUM(E17:E56) | D59: Most Expensive Item: | E59: =IFERROR(INDEX(C17:C56,MATCH(MAX(E17:E56),E17:E56,0)),"")
A60: Profit Before Tax: | B60: =B12-B59 | D60: Largest Expense: | E60: =MAX(E17:E56)
A61: Tax Amount: | B61: =IF(B60>0,B60*$B$11,0)
A62: Net Profit: | B62: =B60-B61
A63: Net Loss: | B63: =IF(B62<0,ABS(B62),0)
A64: Tip: | B64: Enter every receipt on its own row so the summaries and chart stay accurate.

Sheet Job 096
A1: Hammer Brick & Home LLC - Job Tracker
A3: Job Name:
A4: Client:
A5: Address:
A6: Start Date:
A7: End Date:
A9: Contract Price:
A10: Change Orders:
A11: Tax Rate:
A12: Total Budget: | B12: =B9+B10
A15: Expense Log (enter one line per receipt)
A16: Date | B16: Type | C16: Description | D16: Vendor | E16: Cost
A59: Total Expenses: | B59: =SUM(E17:E56) | D59: Most Expensive Item: | E59: =IFERROR(INDEX(C17:C56,MATCH(MAX(E17:E56),E17:E56,0)),"")
A60: Profit Before Tax: | B60: =B12-B59 | D60: Largest Expense: | E60: =MAX(E17:E56)
A61: Tax Amount: | B61: =IF(B60>0,B60*$B$11,0)
A62: Net Profit: | B62: =B60-B61
A63: Net Loss: | B63: =IF(B62<0,ABS(B62),0)
A64: Tip: | B64: Enter every receipt on its own row so the summaries and chart stay accurate.

Sheet Job 097
A1: Hammer Brick & Home LLC - Job Tracker
A3: Job Name:
A4: Client:
A5: Address:
A6: Start Date:
A7: End Date:
A9: Contract Price:
A10: Change Orders:
A11: Tax Rate:
A12: Total Budget: | B12: =B9+B10
A15: Expense Log (enter one line per receipt)
A16: Date | B16: Type | C16: Description | D16: Vendor | E16: Cost
A59: Total Expenses: | B59: =SUM(E17:E56) | D59: Most Expensive Item: | E59: =IFERROR(INDEX(C17:C56,MATCH(MAX(E17:E56),E17:E56,0)),"")
A60: Profit Before Tax: | B60: =B12-B59 | D60: Largest Expense: | E60: =MAX(E17:E56)
A61: Tax Amount: | B61: =IF(B60>0,B60*$B$11,0)
A62: Net Profit: | B62: =B60-B61
A63: Net Loss: | B63: =IF(B62<0,ABS(B62),0)
A64: Tip: | B64: Enter every receipt on its own row so the summaries and chart stay accurate.

Sheet Job 098
A1: Hammer Brick & Home LLC - Job Tracker
A3: Job Name:
A4: Client:
A5: Address:
A6: Start Date:
A7: End Date:
A9: Contract Price:
A10: Change Orders:
A11: Tax Rate:
A12: Total Budget: | B12: =B9+B10
A15: Expense Log (enter one line per receipt)
A16: Date | B16: Type | C16: Description | D16: Vendor | E16: Cost
A59: Total Expenses: | B59: =SUM(E17:E56) | D59: Most Expensive Item: | E59: =IFERROR(INDEX(C17:C56,MATCH(MAX(E17:E56),E17:E56,0)),"")
A60: Profit Before Tax: | B60: =B12-B59 | D60: Largest Expense: | E60: =MAX(E17:E56)
A61: Tax Amount: | B61: =IF(B60>0,B60*$B$11,0)
A62: Net Profit: | B62: =B60-B61
A63: Net Loss: | B63: =IF(B62<0,ABS(B62),0)
A64: Tip: | B64: Enter every receipt on its own row so the summaries and chart stay accurate.

Sheet Job 099
A1: Hammer Brick & Home LLC - Job Tracker
A3: Job Name:
A4: Client:
A5: Address:
A6: Start Date:
A7: End Date:
A9: Contract Price:
A10: Change Orders:
A11: Tax Rate:
A12: Total Budget: | B12: =B9+B10
A15: Expense Log (enter one line per receipt)
A16: Date | B16: Type | C16: Description | D16: Vendor | E16: Cost
A59: Total Expenses: | B59: =SUM(E17:E56) | D59: Most Expensive Item: | E59: =IFERROR(INDEX(C17:C56,MATCH(MAX(E17:E56),E17:E56,0)),"")
A60: Profit Before Tax: | B60: =B12-B59 | D60: Largest Expense: | E60: =MAX(E17:E56)
A61: Tax Amount: | B61: =IF(B60>0,B60*$B$11,0)
A62: Net Profit: | B62: =B60-B61
A63: Net Loss: | B63: =IF(B62<0,ABS(B62),0)
A64: Tip: | B64: Enter every receipt on its own row so the summaries and chart stay accurate.

Sheet Job 100
A1: Hammer Brick & Home LLC - Job Tracker
A3: Job Name:
A4: Client:
A5: Address:
A6: Start Date:
A7: End Date:
A9: Contract Price:
A10: Change Orders:
A11: Tax Rate:
A12: Total Budget: | B12: =B9+B10
A15: Expense Log (enter one line per receipt)
A16: Date | B16: Type | C16: Description | D16: Vendor | E16: Cost
A59: Total Expenses: | B59: =SUM(E17:E56) | D59: Most Expensive Item: | E59: =IFERROR(INDEX(C17:C56,MATCH(MAX(E17:E56),E17:E56,0)),"")
A60: Profit Before Tax: | B60: =B12-B59 | D60: Largest Expense: | E60: =MAX(E17:E56)
A61: Tax Amount: | B61: =IF(B60>0,B60*$B$11,0)
A62: Net Profit: | B62: =B60-B61
A63: Net Loss: | B63: =IF(B62<0,ABS(B62),0)
A64: Tip: | B64: Enter every receipt on its own row so the summaries and chart stay accurate.

Sheet Job 101
A1: Hammer Brick & Home LLC - Job Tracker
A3: Job Name:
A4: Client:
A5: Address:
A6: Start Date:
A7: End Date:
A9: Contract Price:
A10: Change Orders:
A11: Tax Rate:
A12: Total Budget: | B12: =B9+B10
A15: Expense Log (enter one line per receipt)
A16: Date | B16: Type | C16: Description | D16: Vendor | E16: Cost
A59: Total Expenses: | B59: =SUM(E17:E56) | D59: Most Expensive Item: | E59: =IFERROR(INDEX(C17:C56,MATCH(MAX(E17:E56),E17:E56,0)),"")
A60: Profit Before Tax: | B60: =B12-B59 | D60: Largest Expense: | E60: =MAX(E17:E56)
A61: Tax Amount: | B61: =IF(B60>0,B60*$B$11,0)
A62: Net Profit: | B62: =B60-B61
A63: Net Loss: | B63: =IF(B62<0,ABS(B62),0)
A64: Tip: | B64: Enter every receipt on its own row so the summaries and chart stay accurate.

Sheet Job 102
A1: Hammer Brick & Home LLC - Job Tracker
A3: Job Name:
A4: Client:
A5: Address:
A6: Start Date:
A7: End Date:
A9: Contract Price:
A10: Change Orders:
A11: Tax Rate:
A12: Total Budget: | B12: =B9+B10
A15: Expense Log (enter one line per receipt)
A16: Date | B16: Type | C16: Description | D16: Vendor | E16: Cost
A59: Total Expenses: | B59: =SUM(E17:E56) | D59: Most Expensive Item: | E59: =IFERROR(INDEX(C17:C56,MATCH(MAX(E17:E56),E17:E56,0)),"")
A60: Profit Before Tax: | B60: =B12-B59 | D60: Largest Expense: | E60: =MAX(E17:E56)
A61: Tax Amount: | B61: =IF(B60>0,B60*$B$11,0)
A62: Net Profit: | B62: =B60-B61
A63: Net Loss: | B63: =IF(B62<0,ABS(B62),0)
A64: Tip: | B64: Enter every receipt on its own row so the summaries and chart stay accurate.

Sheet Job 103
A1: Hammer Brick & Home LLC - Job Tracker
A3: Job Name:
A4: Client:
A5: Address:
A6: Start Date:
A7: End Date:
A9: Contract Price:
A10: Change Orders:
A11: Tax Rate:
A12: Total Budget: | B12: =B9+B10
A15: Expense Log (enter one line per receipt)
A16: Date | B16: Type | C16: Description | D16: Vendor | E16: Cost
A59: Total Expenses: | B59: =SUM(E17:E56) | D59: Most Expensive Item: | E59: =IFERROR(INDEX(C17:C56,MATCH(MAX(E17:E56),E17:E56,0)),"")
A60: Profit Before Tax: | B60: =B12-B59 | D60: Largest Expense: | E60: =MAX(E17:E56)
A61: Tax Amount: | B61: =IF(B60>0,B60*$B$11,0)
A62: Net Profit: | B62: =B60-B61
A63: Net Loss: | B63: =IF(B62<0,ABS(B62),0)
A64: Tip: | B64: Enter every receipt on its own row so the summaries and chart stay accurate.

Sheet Job 104
A1: Hammer Brick & Home LLC - Job Tracker
A3: Job Name:
A4: Client:
A5: Address:
A6: Start Date:
A7: End Date:
A9: Contract Price:
A10: Change Orders:
A11: Tax Rate:
A12: Total Budget: | B12: =B9+B10
A15: Expense Log (enter one line per receipt)
A16: Date | B16: Type | C16: Description | D16: Vendor | E16: Cost
A59: Total Expenses: | B59: =SUM(E17:E56) | D59: Most Expensive Item: | E59: =IFERROR(INDEX(C17:C56,MATCH(MAX(E17:E56),E17:E56,0)),"")
A60: Profit Before Tax: | B60: =B12-B59 | D60: Largest Expense: | E60: =MAX(E17:E56)
A61: Tax Amount: | B61: =IF(B60>0,B60*$B$11,0)
A62: Net Profit: | B62: =B60-B61
A63: Net Loss: | B63: =IF(B62<0,ABS(B62),0)
A64: Tip: | B64: Enter every receipt on its own row so the summaries and chart stay accurate.

Sheet Job 105
A1: Hammer Brick & Home LLC - Job Tracker
A3: Job Name:
A4: Client:
A5: Address:
A6: Start Date:
A7: End Date:
A9: Contract Price:
A10: Change Orders:
A11: Tax Rate:
A12: Total Budget: | B12: =B9+B10
A15: Expense Log (enter one line per receipt)
A16: Date | B16: Type | C16: Description | D16: Vendor | E16: Cost
A59: Total Expenses: | B59: =SUM(E17:E56) | D59: Most Expensive Item: | E59: =IFERROR(INDEX(C17:C56,MATCH(MAX(E17:E56),E17:E56,0)),"")
A60: Profit Before Tax: | B60: =B12-B59 | D60: Largest Expense: | E60: =MAX(E17:E56)
A61: Tax Amount: | B61: =IF(B60>0,B60*$B$11,0)
A62: Net Profit: | B62: =B60-B61
A63: Net Loss: | B63: =IF(B62<0,ABS(B62),0)
A64: Tip: | B64: Enter every receipt on its own row so the summaries and chart stay accurate.

Sheet Job 106
A1: Hammer Brick & Home LLC - Job Tracker
A3: Job Name:
A4: Client:
A5: Address:
A6: Start Date:
A7: End Date:
A9: Contract Price:
A10: Change Orders:
A11: Tax Rate:
A12: Total Budget: | B12: =B9+B10
A15: Expense Log (enter one line per receipt)
A16: Date | B16: Type | C16: Description | D16: Vendor | E16: Cost
A59: Total Expenses: | B59: =SUM(E17:E56) | D59: Most Expensive Item: | E59: =IFERROR(INDEX(C17:C56,MATCH(MAX(E17:E56),E17:E56,0)),"")
A60: Profit Before Tax: | B60: =B12-B59 | D60: Largest Expense: | E60: =MAX(E17:E56)
A61: Tax Amount: | B61: =IF(B60>0,B60*$B$11,0)
A62: Net Profit: | B62: =B60-B61
A63: Net Loss: | B63: =IF(B62<0,ABS(B62),0)
A64: Tip: | B64: Enter every receipt on its own row so the summaries and chart stay accurate.

Sheet Job 107
A1: Hammer Brick & Home LLC - Job Tracker
A3: Job Name:
A4: Client:
A5: Address:
A6: Start Date:
A7: End Date:
A9: Contract Price:
A10: Change Orders:
A11: Tax Rate:
A12: Total Budget: | B12: =B9+B10
A15: Expense Log (enter one line per receipt)
A16: Date | B16: Type | C16: Description | D16: Vendor | E16: Cost
A59: Total Expenses: | B59: =SUM(E17:E56) | D59: Most Expensive Item: | E59: =IFERROR(INDEX(C17:C56,MATCH(MAX(E17:E56),E17:E56,0)),"")
A60: Profit Before Tax: | B60: =B12-B59 | D60: Largest Expense: | E60: =MAX(E17:E56)
A61: Tax Amount: | B61: =IF(B60>0,B60*$B$11,0)
A62: Net Profit: | B62: =B60-B61
A63: Net Loss: | B63: =IF(B62<0,ABS(B62),0)
A64: Tip: | B64: Enter every receipt on its own row so the summaries and chart stay accurate.

Sheet Job 108
A1: Hammer Brick & Home LLC - Job Tracker
A3: Job Name:
A4: Client:
A5: Address:
A6: Start Date:
A7: End Date:
A9: Contract Price:
A10: Change Orders:
A11: Tax Rate:
A12: Total Budget: | B12: =B9+B10
A15: Expense Log (enter one line per receipt)
A16: Date | B16: Type | C16: Description | D16: Vendor | E16: Cost
A59: Total Expenses: | B59: =SUM(E17:E56) | D59: Most Expensive Item: | E59: =IFERROR(INDEX(C17:C56,MATCH(MAX(E17:E56),E17:E56,0)),"")
A60: Profit Before Tax: | B60: =B12-B59 | D60: Largest Expense: | E60: =MAX(E17:E56)
A61: Tax Amount: | B61: =IF(B60>0,B60*$B$11,0)
A62: Net Profit: | B62: =B60-B61
A63: Net Loss: | B63: =IF(B62<0,ABS(B62),0)
A64: Tip: | B64: Enter every receipt on its own row so the summaries and chart stay accurate.

Sheet Job 109
A1: Hammer Brick & Home LLC - Job Tracker
A3: Job Name:
A4: Client:
A5: Address:
A6: Start Date:
A7: End Date:
A9: Contract Price:
A10: Change Orders:
A11: Tax Rate:
A12: Total Budget: | B12: =B9+B10
A15: Expense Log (enter one line per receipt)
A16: Date | B16: Type | C16: Description | D16: Vendor | E16: Cost
A59: Total Expenses: | B59: =SUM(E17:E56) | D59: Most Expensive Item: | E59: =IFERROR(INDEX(C17:C56,MATCH(MAX(E17:E56),E17:E56,0)),"")
A60: Profit Before Tax: | B60: =B12-B59 | D60: Largest Expense: | E60: =MAX(E17:E56)
A61: Tax Amount: | B61: =IF(B60>0,B60*$B$11,0)
A62: Net Profit: | B62: =B60-B61
A63: Net Loss: | B63: =IF(B62<0,ABS(B62),0)
A64: Tip: | B64: Enter every receipt on its own row so the summaries and chart stay accurate.

Sheet Job 110
A1: Hammer Brick & Home LLC - Job Tracker
A3: Job Name:
A4: Client:
A5: Address:
A6: Start Date:
A7: End Date:
A9: Contract Price:
A10: Change Orders:
A11: Tax Rate:
A12: Total Budget: | B12: =B9+B10
A15: Expense Log (enter one line per receipt)
A16: Date | B16: Type | C16: Description | D16: Vendor | E16: Cost
A59: Total Expenses: | B59: =SUM(E17:E56) | D59: Most Expensive Item: | E59: =IFERROR(INDEX(C17:C56,MATCH(MAX(E17:E56),E17:E56,0)),"")
A60: Profit Before Tax: | B60: =B12-B59 | D60: Largest Expense: | E60: =MAX(E17:E56)
A61: Tax Amount: | B61: =IF(B60>0,B60*$B$11,0)
A62: Net Profit: | B62: =B60-B61
A63: Net Loss: | B63: =IF(B62<0,ABS(B62),0)
A64: Tip: | B64: Enter every receipt on its own row so the summaries and chart stay accurate.

Sheet Job 111
A1: Hammer Brick & Home LLC - Job Tracker
A3: Job Name:
A4: Client:
A5: Address:
A6: Start Date:
A7: End Date:
A9: Contract Price:
A10: Change Orders:
A11: Tax Rate:
A12: Total Budget: | B12: =B9+B10
A15: Expense Log (enter one line per receipt)
A16: Date | B16: Type | C16: Description | D16: Vendor | E16: Cost
A59: Total Expenses: | B59: =SUM(E17:E56) | D59: Most Expensive Item: | E59: =IFERROR(INDEX(C17:C56,MATCH(MAX(E17:E56),E17:E56,0)),"")
A60: Profit Before Tax: | B60: =B12-B59 | D60: Largest Expense: | E60: =MAX(E17:E56)
A61: Tax Amount: | B61: =IF(B60>0,B60*$B$11,0)
A62: Net Profit: | B62: =B60-B61
A63: Net Loss: | B63: =IF(B62<0,ABS(B62),0)
A64: Tip: | B64: Enter every receipt on its own row so the summaries and chart stay accurate.

Sheet Job 112
A1: Hammer Brick & Home LLC - Job Tracker
A3: Job Name:
A4: Client:
A5: Address:
A6: Start Date:
A7: End Date:
A9: Contract Price:
A10: Change Orders:
A11: Tax Rate:
A12: Total Budget: | B12: =B9+B10
A15: Expense Log (enter one line per receipt)
A16: Date | B16: Type | C16: Description | D16: Vendor | E16: Cost
A59: Total Expenses: | B59: =SUM(E17:E56) | D59: Most Expensive Item: | E59: =IFERROR(INDEX(C17:C56,MATCH(MAX(E17:E56),E17:E56,0)),"")
A60: Profit Before Tax: | B60: =B12-B59 | D60: Largest Expense: | E60: =MAX(E17:E56)
A61: Tax Amount: | B61: =IF(B60>0,B60*$B$11,0)
A62: Net Profit: | B62: =B60-B61
A63: Net Loss: | B63: =IF(B62<0,ABS(B62),0)
A64: Tip: | B64: Enter every receipt on its own row so the summaries and chart stay accurate.

Sheet Job 113
A1: Hammer Brick & Home LLC - Job Tracker
A3: Job Name:
A4: Client:
A5: Address:
A6: Start Date:
A7: End Date:
A9: Contract Price:
A10: Change Orders:
A11: Tax Rate:
A12: Total Budget: | B12: =B9+B10
A15: Expense Log (enter one line per receipt)
A16: Date | B16: Type | C16: Description | D16: Vendor | E16: Cost
A59: Total Expenses: | B59: =SUM(E17:E56) | D59: Most Expensive Item: | E59: =IFERROR(INDEX(C17:C56,MATCH(MAX(E17:E56),E17:E56,0)),"")
A60: Profit Before Tax: | B60: =B12-B59 | D60: Largest Expense: | E60: =MAX(E17:E56)
A61: Tax Amount: | B61: =IF(B60>0,B60*$B$11,0)
A62: Net Profit: | B62: =B60-B61
A63: Net Loss: | B63: =IF(B62<0,ABS(B62),0)
A64: Tip: | B64: Enter every receipt on its own row so the summaries and chart stay accurate.

Sheet Job 114
A1: Hammer Brick & Home LLC - Job Tracker
A3: Job Name:
A4: Client:
A5: Address:
A6: Start Date:
A7: End Date:
A9: Contract Price:
A10: Change Orders:
A11: Tax Rate:
A12: Total Budget: | B12: =B9+B10
A15: Expense Log (enter one line per receipt)
A16: Date | B16: Type | C16: Description | D16: Vendor | E16: Cost
A59: Total Expenses: | B59: =SUM(E17:E56) | D59: Most Expensive Item: | E59: =IFERROR(INDEX(C17:C56,MATCH(MAX(E17:E56),E17:E56,0)),"")
A60: Profit Before Tax: | B60: =B12-B59 | D60: Largest Expense: | E60: =MAX(E17:E56)
A61: Tax Amount: | B61: =IF(B60>0,B60*$B$11,0)
A62: Net Profit: | B62: =B60-B61
A63: Net Loss: | B63: =IF(B62<0,ABS(B62),0)
A64: Tip: | B64: Enter every receipt on its own row so the summaries and chart stay accurate.

Sheet Job 115
A1: Hammer Brick & Home LLC - Job Tracker
A3: Job Name:
A4: Client:
A5: Address:
A6: Start Date:
A7: End Date:
A9: Contract Price:
A10: Change Orders:
A11: Tax Rate:
A12: Total Budget: | B12: =B9+B10
A15: Expense Log (enter one line per receipt)
A16: Date | B16: Type | C16: Description | D16: Vendor | E16: Cost
A59: Total Expenses: | B59: =SUM(E17:E56) | D59: Most Expensive Item: | E59: =IFERROR(INDEX(C17:C56,MATCH(MAX(E17:E56),E17:E56,0)),"")
A60: Profit Before Tax: | B60: =B12-B59 | D60: Largest Expense: | E60: =MAX(E17:E56)
A61: Tax Amount: | B61: =IF(B60>0,B60*$B$11,0)
A62: Net Profit: | B62: =B60-B61
A63: Net Loss: | B63: =IF(B62<0,ABS(B62),0)
A64: Tip: | B64: Enter every receipt on its own row so the summaries and chart stay accurate.

Sheet Job 116
A1: Hammer Brick & Home LLC - Job Tracker
A3: Job Name:
A4: Client:
A5: Address:
A6: Start Date:
A7: End Date:
A9: Contract Price:
A10: Change Orders:
A11: Tax Rate:
A12: Total Budget: | B12: =B9+B10
A15: Expense Log (enter one line per receipt)
A16: Date | B16: Type | C16: Description | D16: Vendor | E16: Cost
A59: Total Expenses: | B59: =SUM(E17:E56) | D59: Most Expensive Item: | E59: =IFERROR(INDEX(C17:C56,MATCH(MAX(E17:E56),E17:E56,0)),"")
A60: Profit Before Tax: | B60: =B12-B59 | D60: Largest Expense: | E60: =MAX(E17:E56)
A61: Tax Amount: | B61: =IF(B60>0,B60*$B$11,0)
A62: Net Profit: | B62: =B60-B61
A63: Net Loss: | B63: =IF(B62<0,ABS(B62),0)
A64: Tip: | B64: Enter every receipt on its own row so the summaries and chart stay accurate.

Sheet Job 117
A1: Hammer Brick & Home LLC - Job Tracker
A3: Job Name:
A4: Client:
A5: Address:
A6: Start Date:
A7: End Date:
A9: Contract Price:
A10: Change Orders:
A11: Tax Rate:
A12: Total Budget: | B12: =B9+B10
A15: Expense Log (enter one line per receipt)
A16: Date | B16: Type | C16: Description | D16: Vendor | E16: Cost
A59: Total Expenses: | B59: =SUM(E17:E56) | D59: Most Expensive Item: | E59: =IFERROR(INDEX(C17:C56,MATCH(MAX(E17:E56),E17:E56,0)),"")
A60: Profit Before Tax: | B60: =B12-B59 | D60: Largest Expense: | E60: =MAX(E17:E56)
A61: Tax Amount: | B61: =IF(B60>0,B60*$B$11,0)
A62: Net Profit: | B62: =B60-B61
A63: Net Loss: | B63: =IF(B62<0,ABS(B62),0)
A64: Tip: | B64: Enter every receipt on its own row so the summaries and chart stay accurate.

Sheet Job 118
A1: Hammer Brick & Home LLC - Job Tracker
A3: Job Name:
A4: Client:
A5: Address:
A6: Start Date:
A7: End Date:
A9: Contract Price:
A10: Change Orders:
A11: Tax Rate:
A12: Total Budget: | B12: =B9+B10
A15: Expense Log (enter one line per receipt)
A16: Date | B16: Type | C16: Description | D16: Vendor | E16: Cost
A59: Total Expenses: | B59: =SUM(E17:E56) | D59: Most Expensive Item: | E59: =IFERROR(INDEX(C17:C56,MATCH(MAX(E17:E56),E17:E56,0)),"")
A60: Profit Before Tax: | B60: =B12-B59 | D60: Largest Expense: | E60: =MAX(E17:E56)
A61: Tax Amount: | B61: =IF(B60>0,B60*$B$11,0)
A62: Net Profit: | B62: =B60-B61
A63: Net Loss: | B63: =IF(B62<0,ABS(B62),0)
A64: Tip: | B64: Enter every receipt on its own row so the summaries and chart stay accurate.

Sheet Job 119
A1: Hammer Brick & Home LLC - Job Tracker
A3: Job Name:
A4: Client:
A5: Address:
A6: Start Date:
A7: End Date:
A9: Contract Price:
A10: Change Orders:
A11: Tax Rate:
A12: Total Budget: | B12: =B9+B10
A15: Expense Log (enter one line per receipt)
A16: Date | B16: Type | C16: Description | D16: Vendor | E16: Cost
A59: Total Expenses: | B59: =SUM(E17:E56) | D59: Most Expensive Item: | E59: =IFERROR(INDEX(C17:C56,MATCH(MAX(E17:E56),E17:E56,0)),"")
A60: Profit Before Tax: | B60: =B12-B59 | D60: Largest Expense: | E60: =MAX(E17:E56)
A61: Tax Amount: | B61: =IF(B60>0,B60*$B$11,0)
A62: Net Profit: | B62: =B60-B61
A63: Net Loss: | B63: =IF(B62<0,ABS(B62),0)
A64: Tip: | B64: Enter every receipt on its own row so the summaries and chart stay accurate.

Sheet Job 120
A1: Hammer Brick & Home LLC - Job Tracker
A3: Job Name:
A4: Client:
A5: Address:
A6: Start Date:
A7: End Date:
A9: Contract Price:
A10: Change Orders:
A11: Tax Rate:
A12: Total Budget: | B12: =B9+B10
A15: Expense Log (enter one line per receipt)
A16: Date | B16: Type | C16: Description | D16: Vendor | E16: Cost
A59: Total Expenses: | B59: =SUM(E17:E56) | D59: Most Expensive Item: | E59: =IFERROR(INDEX(C17:C56,MATCH(MAX(E17:E56),E17:E56,0)),"")
A60: Profit Before Tax: | B60: =B12-B59 | D60: Largest Expense: | E60: =MAX(E17:E56)
A61: Tax Amount: | B61: =IF(B60>0,B60*$B$11,0)
A62: Net Profit: | B62: =B60-B61
A63: Net Loss: | B63: =IF(B62<0,ABS(B62),0)
A64: Tip: | B64: Enter every receipt on its own row so the summaries and chart stay accurate.

Sheet Job 121
A1: Hammer Brick & Home LLC - Job Tracker
A3: Job Name:
A4: Client:
A5: Address:
A6: Start Date:
A7: End Date:
A9: Contract Price:
A10: Change Orders:
A11: Tax Rate:
A12: Total Budget: | B12: =B9+B10
A15: Expense Log (enter one line per receipt)
A16: Date | B16: Type | C16: Description | D16: Vendor | E16: Cost
A59: Total Expenses: | B59: =SUM(E17:E56) | D59: Most Expensive Item: | E59: =IFERROR(INDEX(C17:C56,MATCH(MAX(E17:E56),E17:E56,0)),"")
A60: Profit Before Tax: | B60: =B12-B59 | D60: Largest Expense: | E60: =MAX(E17:E56)
A61: Tax Amount: | B61: =IF(B60>0,B60*$B$11,0)
A62: Net Profit: | B62: =B60-B61
A63: Net Loss: | B63: =IF(B62<0,ABS(B62),0)
A64: Tip: | B64: Enter every receipt on its own row so the summaries and chart stay accurate.

Sheet Job 122
A1: Hammer Brick & Home LLC - Job Tracker
A3: Job Name:
A4: Client:
A5: Address:
A6: Start Date:
A7: End Date:
A9: Contract Price:
A10: Change Orders:
A11: Tax Rate:
A12: Total Budget: | B12: =B9+B10
A15: Expense Log (enter one line per receipt)
A16: Date | B16: Type | C16: Description | D16: Vendor | E16: Cost
A59: Total Expenses: | B59: =SUM(E17:E56) | D59: Most Expensive Item: | E59: =IFERROR(INDEX(C17:C56,MATCH(MAX(E17:E56),E17:E56,0)),"")
A60: Profit Before Tax: | B60: =B12-B59 | D60: Largest Expense: | E60: =MAX(E17:E56)
A61: Tax Amount: | B61: =IF(B60>0,B60*$B$11,0)
A62: Net Profit: | B62: =B60-B61
A63: Net Loss: | B63: =IF(B62<0,ABS(B62),0)
A64: Tip: | B64: Enter every receipt on its own row so the summaries and chart stay accurate.

Sheet Job 123
A1: Hammer Brick & Home LLC - Job Tracker
A3: Job Name:
A4: Client:
A5: Address:
A6: Start Date:
A7: End Date:
A9: Contract Price:
A10: Change Orders:
A11: Tax Rate:
A12: Total Budget: | B12: =B9+B10
A15: Expense Log (enter one line per receipt)
A16: Date | B16: Type | C16: Description | D16: Vendor | E16: Cost
A59: Total Expenses: | B59: =SUM(E17:E56) | D59: Most Expensive Item: | E59: =IFERROR(INDEX(C17:C56,MATCH(MAX(E17:E56),E17:E56,0)),"")
A60: Profit Before Tax: | B60: =B12-B59 | D60: Largest Expense: | E60: =MAX(E17:E56)
A61: Tax Amount: | B61: =IF(B60>0,B60*$B$11,0)
A62: Net Profit: | B62: =B60-B61
A63: Net Loss: | B63: =IF(B62<0,ABS(B62),0)
A64: Tip: | B64: Enter every receipt on its own row so the summaries and chart stay accurate.

Sheet Job 124
A1: Hammer Brick & Home LLC - Job Tracker
A3: Job Name:
A4: Client:
A5: Address:
A6: Start Date:
A7: End Date:
A9: Contract Price:
A10: Change Orders:
A11: Tax Rate:
A12: Total Budget: | B12: =B9+B10
A15: Expense Log (enter one line per receipt)
A16: Date | B16: Type | C16: Description | D16: Vendor | E16: Cost
A59: Total Expenses: | B59: =SUM(E17:E56) | D59: Most Expensive Item: | E59: =IFERROR(INDEX(C17:C56,MATCH(MAX(E17:E56),E17:E56,0)),"")
A60: Profit Before Tax: | B60: =B12-B59 | D60: Largest Expense: | E60: =MAX(E17:E56)
A61: Tax Amount: | B61: =IF(B60>0,B60*$B$11,0)
A62: Net Profit: | B62: =B60-B61
A63: Net Loss: | B63: =IF(B62<0,ABS(B62),0)
A64: Tip: | B64: Enter every receipt on its own row so the summaries and chart stay accurate.

Sheet Job 125
A1: Hammer Brick & Home LLC - Job Tracker
A3: Job Name:
A4: Client:
A5: Address:
A6: Start Date:
A7: End Date:
A9: Contract Price:
A10: Change Orders:
A11: Tax Rate:
A12: Total Budget: | B12: =B9+B10
A15: Expense Log (enter one line per receipt)
A16: Date | B16: Type | C16: Description | D16: Vendor | E16: Cost
A59: Total Expenses: | B59: =SUM(E17:E56) | D59: Most Expensive Item: | E59: =IFERROR(INDEX(C17:C56,MATCH(MAX(E17:E56),E17:E56,0)),"")
A60: Profit Before Tax: | B60: =B12-B59 | D60: Largest Expense: | E60: =MAX(E17:E56)
A61: Tax Amount: | B61: =IF(B60>0,B60*$B$11,0)
A62: Net Profit: | B62: =B60-B61
A63: Net Loss: | B63: =IF(B62<0,ABS(B62),0)
A64: Tip: | B64: Enter every receipt on its own row so the summaries and chart stay accurate.

Sheet Job 126
A1: Hammer Brick & Home LLC - Job Tracker
A3: Job Name:
A4: Client:
A5: Address:
A6: Start Date:
A7: End Date:
A9: Contract Price:
A10: Change Orders:
A11: Tax Rate:
A12: Total Budget: | B12: =B9+B10
A15: Expense Log (enter one line per receipt)
A16: Date | B16: Type | C16: Description | D16: Vendor | E16: Cost
A59: Total Expenses: | B59: =SUM(E17:E56) | D59: Most Expensive Item: | E59: =IFERROR(INDEX(C17:C56,MATCH(MAX(E17:E56),E17:E56,0)),"")
A60: Profit Before Tax: | B60: =B12-B59 | D60: Largest Expense: | E60: =MAX(E17:E56)
A61: Tax Amount: | B61: =IF(B60>0,B60*$B$11,0)
A62: Net Profit: | B62: =B60-B61
A63: Net Loss: | B63: =IF(B62<0,ABS(B62),0)
A64: Tip: | B64: Enter every receipt on its own row so the summaries and chart stay accurate.

Sheet Job 127
A1: Hammer Brick & Home LLC - Job Tracker
A3: Job Name:
A4: Client:
A5: Address:
A6: Start Date:
A7: End Date:
A9: Contract Price:
A10: Change Orders:
A11: Tax Rate:
A12: Total Budget: | B12: =B9+B10
A15: Expense Log (enter one line per receipt)
A16: Date | B16: Type | C16: Description | D16: Vendor | E16: Cost
A59: Total Expenses: | B59: =SUM(E17:E56) | D59: Most Expensive Item: | E59: =IFERROR(INDEX(C17:C56,MATCH(MAX(E17:E56),E17:E56,0)),"")
A60: Profit Before Tax: | B60: =B12-B59 | D60: Largest Expense: | E60: =MAX(E17:E56)
A61: Tax Amount: | B61: =IF(B60>0,B60*$B$11,0)
A62: Net Profit: | B62: =B60-B61
A63: Net Loss: | B63: =IF(B62<0,ABS(B62),0)
A64: Tip: | B64: Enter every receipt on its own row so the summaries and chart stay accurate.

Sheet Job 128
A1: Hammer Brick & Home LLC - Job Tracker
A3: Job Name:
A4: Client:
A5: Address:
A6: Start Date:
A7: End Date:
A9: Contract Price:
A10: Change Orders:
A11: Tax Rate:
A12: Total Budget: | B12: =B9+B10
A15: Expense Log (enter one line per receipt)
A16: Date | B16: Type | C16: Description | D16: Vendor | E16: Cost
A59: Total Expenses: | B59: =SUM(E17:E56) | D59: Most Expensive Item: | E59: =IFERROR(INDEX(C17:C56,MATCH(MAX(E17:E56),E17:E56,0)),"")
A60: Profit Before Tax: | B60: =B12-B59 | D60: Largest Expense: | E60: =MAX(E17:E56)
A61: Tax Amount: | B61: =IF(B60>0,B60*$B$11,0)
A62: Net Profit: | B62: =B60-B61
A63: Net Loss: | B63: =IF(B62<0,ABS(B62),0)
A64: Tip: | B64: Enter every receipt on its own row so the summaries and chart stay accurate.

Sheet Job 129
A1: Hammer Brick & Home LLC - Job Tracker
A3: Job Name:
A4: Client:
A5: Address:
A6: Start Date:
A7: End Date:
A9: Contract Price:
A10: Change Orders:
A11: Tax Rate:
A12: Total Budget: | B12: =B9+B10
A15: Expense Log (enter one line per receipt)
A16: Date | B16: Type | C16: Description | D16: Vendor | E16: Cost
A59: Total Expenses: | B59: =SUM(E17:E56) | D59: Most Expensive Item: | E59: =IFERROR(INDEX(C17:C56,MATCH(MAX(E17:E56),E17:E56,0)),"")
A60: Profit Before Tax: | B60: =B12-B59 | D60: Largest Expense: | E60: =MAX(E17:E56)
A61: Tax Amount: | B61: =IF(B60>0,B60*$B$11,0)
A62: Net Profit: | B62: =B60-B61
A63: Net Loss: | B63: =IF(B62<0,ABS(B62),0)
A64: Tip: | B64: Enter every receipt on its own row so the summaries and chart stay accurate.

Sheet Job 130
A1: Hammer Brick & Home LLC - Job Tracker
A3: Job Name:
A4: Client:
A5: Address:
A6: Start Date:
A7: End Date:
A9: Contract Price:
A10: Change Orders:
A11: Tax Rate:
A12: Total Budget: | B12: =B9+B10
A15: Expense Log (enter one line per receipt)
A16: Date | B16: Type | C16: Description | D16: Vendor | E16: Cost
A59: Total Expenses: | B59: =SUM(E17:E56) | D59: Most Expensive Item: | E59: =IFERROR(INDEX(C17:C56,MATCH(MAX(E17:E56),E17:E56,0)),"")
A60: Profit Before Tax: | B60: =B12-B59 | D60: Largest Expense: | E60: =MAX(E17:E56)
A61: Tax Amount: | B61: =IF(B60>0,B60*$B$11,0)
A62: Net Profit: | B62: =B60-B61
A63: Net Loss: | B63: =IF(B62<0,ABS(B62),0)
A64: Tip: | B64: Enter every receipt on its own row so the summaries and chart stay accurate.

Sheet Job 131
A1: Hammer Brick & Home LLC - Job Tracker
A3: Job Name:
A4: Client:
A5: Address:
A6: Start Date:
A7: End Date:
A9: Contract Price:
A10: Change Orders:
A11: Tax Rate:
A12: Total Budget: | B12: =B9+B10
A15: Expense Log (enter one line per receipt)
A16: Date | B16: Type | C16: Description | D16: Vendor | E16: Cost
A59: Total Expenses: | B59: =SUM(E17:E56) | D59: Most Expensive Item: | E59: =IFERROR(INDEX(C17:C56,MATCH(MAX(E17:E56),E17:E56,0)),"")
A60: Profit Before Tax: | B60: =B12-B59 | D60: Largest Expense: | E60: =MAX(E17:E56)
A61: Tax Amount: | B61: =IF(B60>0,B60*$B$11,0)
A62: Net Profit: | B62: =B60-B61
A63: Net Loss: | B63: =IF(B62<0,ABS(B62),0)
A64: Tip: | B64: Enter every receipt on its own row so the summaries and chart stay accurate.

Sheet Job 132
A1: Hammer Brick & Home LLC - Job Tracker
A3: Job Name:
A4: Client:
A5: Address:
A6: Start Date:
A7: End Date:
A9: Contract Price:
A10: Change Orders:
A11: Tax Rate:
A12: Total Budget: | B12: =B9+B10
A15: Expense Log (enter one line per receipt)
A16: Date | B16: Type | C16: Description | D16: Vendor | E16: Cost
A59: Total Expenses: | B59: =SUM(E17:E56) | D59: Most Expensive Item: | E59: =IFERROR(INDEX(C17:C56,MATCH(MAX(E17:E56),E17:E56,0)),"")
A60: Profit Before Tax: | B60: =B12-B59 | D60: Largest Expense: | E60: =MAX(E17:E56)
A61: Tax Amount: | B61: =IF(B60>0,B60*$B$11,0)
A62: Net Profit: | B62: =B60-B61
A63: Net Loss: | B63: =IF(B62<0,ABS(B62),0)
A64: Tip: | B64: Enter every receipt on its own row so the summaries and chart stay accurate.

Sheet Job 133
A1: Hammer Brick & Home LLC - Job Tracker
A3: Job Name:
A4: Client:
A5: Address:
A6: Start Date:
A7: End Date:
A9: Contract Price:
A10: Change Orders:
A11: Tax Rate:
A12: Total Budget: | B12: =B9+B10
A15: Expense Log (enter one line per receipt)
A16: Date | B16: Type | C16: Description | D16: Vendor | E16: Cost
A59: Total Expenses: | B59: =SUM(E17:E56) | D59: Most Expensive Item: | E59: =IFERROR(INDEX(C17:C56,MATCH(MAX(E17:E56),E17:E56,0)),"")
A60: Profit Before Tax: | B60: =B12-B59 | D60: Largest Expense: | E60: =MAX(E17:E56)
A61: Tax Amount: | B61: =IF(B60>0,B60*$B$11,0)
A62: Net Profit: | B62: =B60-B61
A63: Net Loss: | B63: =IF(B62<0,ABS(B62),0)
A64: Tip: | B64: Enter every receipt on its own row so the summaries and chart stay accurate.

Sheet Job 134
A1: Hammer Brick & Home LLC - Job Tracker
A3: Job Name:
A4: Client:
A5: Address:
A6: Start Date:
A7: End Date:
A9: Contract Price:
A10: Change Orders:
A11: Tax Rate:
A12: Total Budget: | B12: =B9+B10
A15: Expense Log (enter one line per receipt)
A16: Date | B16: Type | C16: Description | D16: Vendor | E16: Cost
A59: Total Expenses: | B59: =SUM(E17:E56) | D59: Most Expensive Item: | E59: =IFERROR(INDEX(C17:C56,MATCH(MAX(E17:E56),E17:E56,0)),"")
A60: Profit Before Tax: | B60: =B12-B59 | D60: Largest Expense: | E60: =MAX(E17:E56)
A61: Tax Amount: | B61: =IF(B60>0,B60*$B$11,0)
A62: Net Profit: | B62: =B60-B61
A63: Net Loss: | B63: =IF(B62<0,ABS(B62),0)
A64: Tip: | B64: Enter every receipt on its own row so the summaries and chart stay accurate.

Sheet Job 135
A1: Hammer Brick & Home LLC - Job Tracker
A3: Job Name:
A4: Client:
A5: Address:
A6: Start Date:
A7: End Date:
A9: Contract Price:
A10: Change Orders:
A11: Tax Rate:
A12: Total Budget: | B12: =B9+B10
A15: Expense Log (enter one line per receipt)
A16: Date | B16: Type | C16: Description | D16: Vendor | E16: Cost
A59: Total Expenses: | B59: =SUM(E17:E56) | D59: Most Expensive Item: | E59: =IFERROR(INDEX(C17:C56,MATCH(MAX(E17:E56),E17:E56,0)),"")
A60: Profit Before Tax: | B60: =B12-B59 | D60: Largest Expense: | E60: =MAX(E17:E56)
A61: Tax Amount: | B61: =IF(B60>0,B60*$B$11,0)
A62: Net Profit: | B62: =B60-B61
A63: Net Loss: | B63: =IF(B62<0,ABS(B62),0)
A64: Tip: | B64: Enter every receipt on its own row so the summaries and chart stay accurate.

Sheet Job 136
A1: Hammer Brick & Home LLC - Job Tracker
A3: Job Name:
A4: Client:
A5: Address:
A6: Start Date:
A7: End Date:
A9: Contract Price:
A10: Change Orders:
A11: Tax Rate:
A12: Total Budget: | B12: =B9+B10
A15: Expense Log (enter one line per receipt)
A16: Date | B16: Type | C16: Description | D16: Vendor | E16: Cost
A59: Total Expenses: | B59: =SUM(E17:E56) | D59: Most Expensive Item: | E59: =IFERROR(INDEX(C17:C56,MATCH(MAX(E17:E56),E17:E56,0)),"")
A60: Profit Before Tax: | B60: =B12-B59 | D60: Largest Expense: | E60: =MAX(E17:E56)
A61: Tax Amount: | B61: =IF(B60>0,B60*$B$11,0)
A62: Net Profit: | B62: =B60-B61
A63: Net Loss: | B63: =IF(B62<0,ABS(B62),0)
A64: Tip: | B64: Enter every receipt on its own row so the summaries and chart stay accurate.

Sheet Job 137
A1: Hammer Brick & Home LLC - Job Tracker
A3: Job Name:
A4: Client:
A5: Address:
A6: Start Date:
A7: End Date:
A9: Contract Price:
A10: Change Orders:
A11: Tax Rate:
A12: Total Budget: | B12: =B9+B10
A15: Expense Log (enter one line per receipt)
A16: Date | B16: Type | C16: Description | D16: Vendor | E16: Cost
A59: Total Expenses: | B59: =SUM(E17:E56) | D59: Most Expensive Item: | E59: =IFERROR(INDEX(C17:C56,MATCH(MAX(E17:E56),E17:E56,0)),"")
A60: Profit Before Tax: | B60: =B12-B59 | D60: Largest Expense: | E60: =MAX(E17:E56)
A61: Tax Amount: | B61: =IF(B60>0,B60*$B$11,0)
A62: Net Profit: | B62: =B60-B61
A63: Net Loss: | B63: =IF(B62<0,ABS(B62),0)
A64: Tip: | B64: Enter every receipt on its own row so the summaries and chart stay accurate.

Sheet Job 138
A1: Hammer Brick & Home LLC - Job Tracker
A3: Job Name:
A4: Client:
A5: Address:
A6: Start Date:
A7: End Date:
A9: Contract Price:
A10: Change Orders:
A11: Tax Rate:
A12: Total Budget: | B12: =B9+B10
A15: Expense Log (enter one line per receipt)
A16: Date | B16: Type | C16: Description | D16: Vendor | E16: Cost
A59: Total Expenses: | B59: =SUM(E17:E56) | D59: Most Expensive Item: | E59: =IFERROR(INDEX(C17:C56,MATCH(MAX(E17:E56),E17:E56,0)),"")
A60: Profit Before Tax: | B60: =B12-B59 | D60: Largest Expense: | E60: =MAX(E17:E56)
A61: Tax Amount: | B61: =IF(B60>0,B60*$B$11,0)
A62: Net Profit: | B62: =B60-B61
A63: Net Loss: | B63: =IF(B62<0,ABS(B62),0)
A64: Tip: | B64: Enter every receipt on its own row so the summaries and chart stay accurate.

Sheet Job 139
A1: Hammer Brick & Home LLC - Job Tracker
A3: Job Name:
A4: Client:
A5: Address:
A6: Start Date:
A7: End Date:
A9: Contract Price:
A10: Change Orders:
A11: Tax Rate:
A12: Total Budget: | B12: =B9+B10
A15: Expense Log (enter one line per receipt)
A16: Date | B16: Type | C16: Description | D16: Vendor | E16: Cost
A59: Total Expenses: | B59: =SUM(E17:E56) | D59: Most Expensive Item: | E59: =IFERROR(INDEX(C17:C56,MATCH(MAX(E17:E56),E17:E56,0)),"")
A60: Profit Before Tax: | B60: =B12-B59 | D60: Largest Expense: | E60: =MAX(E17:E56)
A61: Tax Amount: | B61: =IF(B60>0,B60*$B$11,0)
A62: Net Profit: | B62: =B60-B61
A63: Net Loss: | B63: =IF(B62<0,ABS(B62),0)
A64: Tip: | B64: Enter every receipt on its own row so the summaries and chart stay accurate.

Sheet Job 140
A1: Hammer Brick & Home LLC - Job Tracker
A3: Job Name:
A4: Client:
A5: Address:
A6: Start Date:
A7: End Date:
A9: Contract Price:
A10: Change Orders:
A11: Tax Rate:
A12: Total Budget: | B12: =B9+B10
A15: Expense Log (enter one line per receipt)
A16: Date | B16: Type | C16: Description | D16: Vendor | E16: Cost
A59: Total Expenses: | B59: =SUM(E17:E56) | D59: Most Expensive Item: | E59: =IFERROR(INDEX(C17:C56,MATCH(MAX(E17:E56),E17:E56,0)),"")
A60: Profit Before Tax: | B60: =B12-B59 | D60: Largest Expense: | E60: =MAX(E17:E56)
A61: Tax Amount: | B61: =IF(B60>0,B60*$B$11,0)
A62: Net Profit: | B62: =B60-B61
A63: Net Loss: | B63: =IF(B62<0,ABS(B62),0)
A64: Tip: | B64: Enter every receipt on its own row so the summaries and chart stay accurate.

Sheet Job 141
A1: Hammer Brick & Home LLC - Job Tracker
A3: Job Name:
A4: Client:
A5: Address:
A6: Start Date:
A7: End Date:
A9: Contract Price:
A10: Change Orders:
A11: Tax Rate:
A12: Total Budget: | B12: =B9+B10
A15: Expense Log (enter one line per receipt)
A16: Date | B16: Type | C16: Description | D16: Vendor | E16: Cost
A59: Total Expenses: | B59: =SUM(E17:E56) | D59: Most Expensive Item: | E59: =IFERROR(INDEX(C17:C56,MATCH(MAX(E17:E56),E17:E56,0)),"")
A60: Profit Before Tax: | B60: =B12-B59 | D60: Largest Expense: | E60: =MAX(E17:E56)
A61: Tax Amount: | B61: =IF(B60>0,B60*$B$11,0)
A62: Net Profit: | B62: =B60-B61
A63: Net Loss: | B63: =IF(B62<0,ABS(B62),0)
A64: Tip: | B64: Enter every receipt on its own row so the summaries and chart stay accurate.

Sheet Job 142
A1: Hammer Brick & Home LLC - Job Tracker
A3: Job Name:
A4: Client:
A5: Address:
A6: Start Date:
A7: End Date:
A9: Contract Price:
A10: Change Orders:
A11: Tax Rate:
A12: Total Budget: | B12: =B9+B10
A15: Expense Log (enter one line per receipt)
A16: Date | B16: Type | C16: Description | D16: Vendor | E16: Cost
A59: Total Expenses: | B59: =SUM(E17:E56) | D59: Most Expensive Item: | E59: =IFERROR(INDEX(C17:C56,MATCH(MAX(E17:E56),E17:E56,0)),"")
A60: Profit Before Tax: | B60: =B12-B59 | D60: Largest Expense: | E60: =MAX(E17:E56)
A61: Tax Amount: | B61: =IF(B60>0,B60*$B$11,0)
A62: Net Profit: | B62: =B60-B61
A63: Net Loss: | B63: =IF(B62<0,ABS(B62),0)
A64: Tip: | B64: Enter every receipt on its own row so the summaries and chart stay accurate.

Sheet Job 143
A1: Hammer Brick & Home LLC - Job Tracker
A3: Job Name:
A4: Client:
A5: Address:
A6: Start Date:
A7: End Date:
A9: Contract Price:
A10: Change Orders:
A11: Tax Rate:
A12: Total Budget: | B12: =B9+B10
A15: Expense Log (enter one line per receipt)
A16: Date | B16: Type | C16: Description | D16: Vendor | E16: Cost
A59: Total Expenses: | B59: =SUM(E17:E56) | D59: Most Expensive Item: | E59: =IFERROR(INDEX(C17:C56,MATCH(MAX(E17:E56),E17:E56,0)),"")
A60: Profit Before Tax: | B60: =B12-B59 | D60: Largest Expense: | E60: =MAX(E17:E56)
A61: Tax Amount: | B61: =IF(B60>0,B60*$B$11,0)
A62: Net Profit: | B62: =B60-B61
A63: Net Loss: | B63: =IF(B62<0,ABS(B62),0)
A64: Tip: | B64: Enter every receipt on its own row so the summaries and chart stay accurate.

Sheet Job 144
A1: Hammer Brick & Home LLC - Job Tracker
A3: Job Name:
A4: Client:
A5: Address:
A6: Start Date:
A7: End Date:
A9: Contract Price:
A10: Change Orders:
A11: Tax Rate:
A12: Total Budget: | B12: =B9+B10
A15: Expense Log (enter one line per receipt)
A16: Date | B16: Type | C16: Description | D16: Vendor | E16: Cost
A59: Total Expenses: | B59: =SUM(E17:E56) | D59: Most Expensive Item: | E59: =IFERROR(INDEX(C17:C56,MATCH(MAX(E17:E56),E17:E56,0)),"")
A60: Profit Before Tax: | B60: =B12-B59 | D60: Largest Expense: | E60: =MAX(E17:E56)
A61: Tax Amount: | B61: =IF(B60>0,B60*$B$11,0)
A62: Net Profit: | B62: =B60-B61
A63: Net Loss: | B63: =IF(B62<0,ABS(B62),0)
A64: Tip: | B64: Enter every receipt on its own row so the summaries and chart stay accurate.

Sheet Job 145
A1: Hammer Brick & Home LLC - Job Tracker
A3: Job Name:
A4: Client:
A5: Address:
A6: Start Date:
A7: End Date:
A9: Contract Price:
A10: Change Orders:
A11: Tax Rate:
A12: Total Budget: | B12: =B9+B10
A15: Expense Log (enter one line per receipt)
A16: Date | B16: Type | C16: Description | D16: Vendor | E16: Cost
A59: Total Expenses: | B59: =SUM(E17:E56) | D59: Most Expensive Item: | E59: =IFERROR(INDEX(C17:C56,MATCH(MAX(E17:E56),E17:E56,0)),"")
A60: Profit Before Tax: | B60: =B12-B59 | D60: Largest Expense: | E60: =MAX(E17:E56)
A61: Tax Amount: | B61: =IF(B60>0,B60*$B$11,0)
A62: Net Profit: | B62: =B60-B61
A63: Net Loss: | B63: =IF(B62<0,ABS(B62),0)
A64: Tip: | B64: Enter every receipt on its own row so the summaries and chart stay accurate.

Sheet Job 146
A1: Hammer Brick & Home LLC - Job Tracker
A3: Job Name:
A4: Client:
A5: Address:
A6: Start Date:
A7: End Date:
A9: Contract Price:
A10: Change Orders:
A11: Tax Rate:
A12: Total Budget: | B12: =B9+B10
A15: Expense Log (enter one line per receipt)
A16: Date | B16: Type | C16: Description | D16: Vendor | E16: Cost
A59: Total Expenses: | B59: =SUM(E17:E56) | D59: Most Expensive Item: | E59: =IFERROR(INDEX(C17:C56,MATCH(MAX(E17:E56),E17:E56,0)),"")
A60: Profit Before Tax: | B60: =B12-B59 | D60: Largest Expense: | E60: =MAX(E17:E56)
A61: Tax Amount: | B61: =IF(B60>0,B60*$B$11,0)
A62: Net Profit: | B62: =B60-B61
A63: Net Loss: | B63: =IF(B62<0,ABS(B62),0)
A64: Tip: | B64: Enter every receipt on its own row so the summaries and chart stay accurate.

Sheet Job 147
A1: Hammer Brick & Home LLC - Job Tracker
A3: Job Name:
A4: Client:
A5: Address:
A6: Start Date:
A7: End Date:
A9: Contract Price:
A10: Change Orders:
A11: Tax Rate:
A12: Total Budget: | B12: =B9+B10
A15: Expense Log (enter one line per receipt)
A16: Date | B16: Type | C16: Description | D16: Vendor | E16: Cost
A59: Total Expenses: | B59: =SUM(E17:E56) | D59: Most Expensive Item: | E59: =IFERROR(INDEX(C17:C56,MATCH(MAX(E17:E56),E17:E56,0)),"")
A60: Profit Before Tax: | B60: =B12-B59 | D60: Largest Expense: | E60: =MAX(E17:E56)
A61: Tax Amount: | B61: =IF(B60>0,B60*$B$11,0)
A62: Net Profit: | B62: =B60-B61
A63: Net Loss: | B63: =IF(B62<0,ABS(B62),0)
A64: Tip: | B64: Enter every receipt on its own row so the summaries and chart stay accurate.

Sheet Job 148
A1: Hammer Brick & Home LLC - Job Tracker
A3: Job Name:
A4: Client:
A5: Address:
A6: Start Date:
A7: End Date:
A9: Contract Price:
A10: Change Orders:
A11: Tax Rate:
A12: Total Budget: | B12: =B9+B10
A15: Expense Log (enter one line per receipt)
A16: Date | B16: Type | C16: Description | D16: Vendor | E16: Cost
A59: Total Expenses: | B59: =SUM(E17:E56) | D59: Most Expensive Item: | E59: =IFERROR(INDEX(C17:C56,MATCH(MAX(E17:E56),E17:E56,0)),"")
A60: Profit Before Tax: | B60: =B12-B59 | D60: Largest Expense: | E60: =MAX(E17:E56)
A61: Tax Amount: | B61: =IF(B60>0,B60*$B$11,0)
A62: Net Profit: | B62: =B60-B61
A63: Net Loss: | B63: =IF(B62<0,ABS(B62),0)
A64: Tip: | B64: Enter every receipt on its own row so the summaries and chart stay accurate.

Sheet Job 149
A1: Hammer Brick & Home LLC - Job Tracker
A3: Job Name:
A4: Client:
A5: Address:
A6: Start Date:
A7: End Date:
A9: Contract Price:
A10: Change Orders:
A11: Tax Rate:
A12: Total Budget: | B12: =B9+B10
A15: Expense Log (enter one line per receipt)
A16: Date | B16: Type | C16: Description | D16: Vendor | E16: Cost
A59: Total Expenses: | B59: =SUM(E17:E56) | D59: Most Expensive Item: | E59: =IFERROR(INDEX(C17:C56,MATCH(MAX(E17:E56),E17:E56,0)),"")
A60: Profit Before Tax: | B60: =B12-B59 | D60: Largest Expense: | E60: =MAX(E17:E56)
A61: Tax Amount: | B61: =IF(B60>0,B60*$B$11,0)
A62: Net Profit: | B62: =B60-B61
A63: Net Loss: | B63: =IF(B62<0,ABS(B62),0)
A64: Tip: | B64: Enter every receipt on its own row so the summaries and chart stay accurate.

Sheet Job 150
A1: Hammer Brick & Home LLC - Job Tracker
A3: Job Name:
A4: Client:
A5: Address:
A6: Start Date:
A7: End Date:
A9: Contract Price:
A10: Change Orders:
A11: Tax Rate:
A12: Total Budget: | B12: =B9+B10
A15: Expense Log (enter one line per receipt)
A16: Date | B16: Type | C16: Description | D16: Vendor | E16: Cost
A59: Total Expenses: | B59: =SUM(E17:E56) | D59: Most Expensive Item: | E59: =IFERROR(INDEX(C17:C56,MATCH(MAX(E17:E56),E17:E56,0)),"")
A60: Profit Before Tax: | B60: =B12-B59 | D60: Largest Expense: | E60: =MAX(E17:E56)
A61: Tax Amount: | B61: =IF(B60>0,B60*$B$11,0)
A62: Net Profit: | B62: =B60-B61
A63: Net Loss: | B63: =IF(B62<0,ABS(B62),0)
A64: Tip: | B64: Enter every receipt on its own row so the summaries and chart stay accurate.

Sheet Job 151
A1: Hammer Brick & Home LLC - Job Tracker
A3: Job Name:
A4: Client:
A5: Address:
A6: Start Date:
A7: End Date:
A9: Contract Price:
A10: Change Orders:
A11: Tax Rate:
A12: Total Budget: | B12: =B9+B10
A15: Expense Log (enter one line per receipt)
A16: Date | B16: Type | C16: Description | D16: Vendor | E16: Cost
A59: Total Expenses: | B59: =SUM(E17:E56) | D59: Most Expensive Item: | E59: =IFERROR(INDEX(C17:C56,MATCH(MAX(E17:E56),E17:E56,0)),"")
A60: Profit Before Tax: | B60: =B12-B59 | D60: Largest Expense: | E60: =MAX(E17:E56)
A61: Tax Amount: | B61: =IF(B60>0,B60*$B$11,0)
A62: Net Profit: | B62: =B60-B61
A63: Net Loss: | B63: =IF(B62<0,ABS(B62),0)
A64: Tip: | B64: Enter every receipt on its own row so the summaries and chart stay accurate.

Sheet Job 152
A1: Hammer Brick & Home LLC - Job Tracker
A3: Job Name:
A4: Client:
A5: Address:
A6: Start Date:
A7: End Date:
A9: Contract Price:
A10: Change Orders:
A11: Tax Rate:
A12: Total Budget: | B12: =B9+B10
A15: Expense Log (enter one line per receipt)
A16: Date | B16: Type | C16: Description | D16: Vendor | E16: Cost
A59: Total Expenses: | B59: =SUM(E17:E56) | D59: Most Expensive Item: | E59: =IFERROR(INDEX(C17:C56,MATCH(MAX(E17:E56),E17:E56,0)),"")
A60: Profit Before Tax: | B60: =B12-B59 | D60: Largest Expense: | E60: =MAX(E17:E56)
A61: Tax Amount: | B61: =IF(B60>0,B60*$B$11,0)
A62: Net Profit: | B62: =B60-B61
A63: Net Loss: | B63: =IF(B62<0,ABS(B62),0)
A64: Tip: | B64: Enter every receipt on its own row so the summaries and chart stay accurate.

Sheet Job 153
A1: Hammer Brick & Home LLC - Job Tracker
A3: Job Name:
A4: Client:
A5: Address:
A6: Start Date:
A7: End Date:
A9: Contract Price:
A10: Change Orders:
A11: Tax Rate:
A12: Total Budget: | B12: =B9+B10
A15: Expense Log (enter one line per receipt)
A16: Date | B16: Type | C16: Description | D16: Vendor | E16: Cost
A59: Total Expenses: | B59: =SUM(E17:E56) | D59: Most Expensive Item: | E59: =IFERROR(INDEX(C17:C56,MATCH(MAX(E17:E56),E17:E56,0)),"")
A60: Profit Before Tax: | B60: =B12-B59 | D60: Largest Expense: | E60: =MAX(E17:E56)
A61: Tax Amount: | B61: =IF(B60>0,B60*$B$11,0)
A62: Net Profit: | B62: =B60-B61
A63: Net Loss: | B63: =IF(B62<0,ABS(B62),0)
A64: Tip: | B64: Enter every receipt on its own row so the summaries and chart stay accurate.

Sheet Job 154
A1: Hammer Brick & Home LLC - Job Tracker
A3: Job Name:
A4: Client:
A5: Address:
A6: Start Date:
A7: End Date:
A9: Contract Price:
A10: Change Orders:
A11: Tax Rate:
A12: Total Budget: | B12: =B9+B10
A15: Expense Log (enter one line per receipt)
A16: Date | B16: Type | C16: Description | D16: Vendor | E16: Cost
A59: Total Expenses: | B59: =SUM(E17:E56) | D59: Most Expensive Item: | E59: =IFERROR(INDEX(C17:C56,MATCH(MAX(E17:E56),E17:E56,0)),"")
A60: Profit Before Tax: | B60: =B12-B59 | D60: Largest Expense: | E60: =MAX(E17:E56)
A61: Tax Amount: | B61: =IF(B60>0,B60*$B$11,0)
A62: Net Profit: | B62: =B60-B61
A63: Net Loss: | B63: =IF(B62<0,ABS(B62),0)
A64: Tip: | B64: Enter every receipt on its own row so the summaries and chart stay accurate.

Sheet Job 155
A1: Hammer Brick & Home LLC - Job Tracker
A3: Job Name:
A4: Client:
A5: Address:
A6: Start Date:
A7: End Date:
A9: Contract Price:
A10: Change Orders:
A11: Tax Rate:
A12: Total Budget: | B12: =B9+B10
A15: Expense Log (enter one line per receipt)
A16: Date | B16: Type | C16: Description | D16: Vendor | E16: Cost
A59: Total Expenses: | B59: =SUM(E17:E56) | D59: Most Expensive Item: | E59: =IFERROR(INDEX(C17:C56,MATCH(MAX(E17:E56),E17:E56,0)),"")
A60: Profit Before Tax: | B60: =B12-B59 | D60: Largest Expense: | E60: =MAX(E17:E56)
A61: Tax Amount: | B61: =IF(B60>0,B60*$B$11,0)
A62: Net Profit: | B62: =B60-B61
A63: Net Loss: | B63: =IF(B62<0,ABS(B62),0)
A64: Tip: | B64: Enter every receipt on its own row so the summaries and chart stay accurate.

Sheet Job 156
A1: Hammer Brick & Home LLC - Job Tracker
A3: Job Name:
A4: Client:
A5: Address:
A6: Start Date:
A7: End Date:
A9: Contract Price:
A10: Change Orders:
A11: Tax Rate:
A12: Total Budget: | B12: =B9+B10
A15: Expense Log (enter one line per receipt)
A16: Date | B16: Type | C16: Description | D16: Vendor | E16: Cost
A59: Total Expenses: | B59: =SUM(E17:E56) | D59: Most Expensive Item: | E59: =IFERROR(INDEX(C17:C56,MATCH(MAX(E17:E56),E17:E56,0)),"")
A60: Profit Before Tax: | B60: =B12-B59 | D60: Largest Expense: | E60: =MAX(E17:E56)
A61: Tax Amount: | B61: =IF(B60>0,B60*$B$11,0)
A62: Net Profit: | B62: =B60-B61
A63: Net Loss: | B63: =IF(B62<0,ABS(B62),0)
A64: Tip: | B64: Enter every receipt on its own row so the summaries and chart stay accurate.

Sheet Job 157
A1: Hammer Brick & Home LLC - Job Tracker
A3: Job Name:
A4: Client:
A5: Address:
A6: Start Date:
A7: End Date:
A9: Contract Price:
A10: Change Orders:
A11: Tax Rate:
A12: Total Budget: | B12: =B9+B10
A15: Expense Log (enter one line per receipt)
A16: Date | B16: Type | C16: Description | D16: Vendor | E16: Cost
A59: Total Expenses: | B59: =SUM(E17:E56) | D59: Most Expensive Item: | E59: =IFERROR(INDEX(C17:C56,MATCH(MAX(E17:E56),E17:E56,0)),"")
A60: Profit Before Tax: | B60: =B12-B59 | D60: Largest Expense: | E60: =MAX(E17:E56)
A61: Tax Amount: | B61: =IF(B60>0,B60*$B$11,0)
A62: Net Profit: | B62: =B60-B61
A63: Net Loss: | B63: =IF(B62<0,ABS(B62),0)
A64: Tip: | B64: Enter every receipt on its own row so the summaries and chart stay accurate.

Sheet Job 158
A1: Hammer Brick & Home LLC - Job Tracker
A3: Job Name:
A4: Client:
A5: Address:
A6: Start Date:
A7: End Date:
A9: Contract Price:
A10: Change Orders:
A11: Tax Rate:
A12: Total Budget: | B12: =B9+B10
A15: Expense Log (enter one line per receipt)
A16: Date | B16: Type | C16: Description | D16: Vendor | E16: Cost
A59: Total Expenses: | B59: =SUM(E17:E56) | D59: Most Expensive Item: | E59: =IFERROR(INDEX(C17:C56,MATCH(MAX(E17:E56),E17:E56,0)),"")
A60: Profit Before Tax: | B60: =B12-B59 | D60: Largest Expense: | E60: =MAX(E17:E56)
A61: Tax Amount: | B61: =IF(B60>0,B60*$B$11,0)
A62: Net Profit: | B62: =B60-B61
A63: Net Loss: | B63: =IF(B62<0,ABS(B62),0)
A64: Tip: | B64: Enter every receipt on its own row so the summaries and chart stay accurate.

Sheet Job 159
A1: Hammer Brick & Home LLC - Job Tracker
A3: Job Name:
A4: Client:
A5: Address:
A6: Start Date:
A7: End Date:
A9: Contract Price:
A10: Change Orders:
A11: Tax Rate:
A12: Total Budget: | B12: =B9+B10
A15: Expense Log (enter one line per receipt)
A16: Date | B16: Type | C16: Description | D16: Vendor | E16: Cost
A59: Total Expenses: | B59: =SUM(E17:E56) | D59: Most Expensive Item: | E59: =IFERROR(INDEX(C17:C56,MATCH(MAX(E17:E56),E17:E56,0)),"")
A60: Profit Before Tax: | B60: =B12-B59 | D60: Largest Expense: | E60: =MAX(E17:E56)
A61: Tax Amount: | B61: =IF(B60>0,B60*$B$11,0)
A62: Net Profit: | B62: =B60-B61
A63: Net Loss: | B63: =IF(B62<0,ABS(B62),0)
A64: Tip: | B64: Enter every receipt on its own row so the summaries and chart stay accurate.

Sheet Job 160
A1: Hammer Brick & Home LLC - Job Tracker
A3: Job Name:
A4: Client:
A5: Address:
A6: Start Date:
A7: End Date:
A9: Contract Price:
A10: Change Orders:
A11: Tax Rate:
A12: Total Budget: | B12: =B9+B10
A15: Expense Log (enter one line per receipt)
A16: Date | B16: Type | C16: Description | D16: Vendor | E16: Cost
A59: Total Expenses: | B59: =SUM(E17:E56) | D59: Most Expensive Item: | E59: =IFERROR(INDEX(C17:C56,MATCH(MAX(E17:E56),E17:E56,0)),"")
A60: Profit Before Tax: | B60: =B12-B59 | D60: Largest Expense: | E60: =MAX(E17:E56)
A61: Tax Amount: | B61: =IF(B60>0,B60*$B$11,0)
A62: Net Profit: | B62: =B60-B61
A63: Net Loss: | B63: =IF(B62<0,ABS(B62),0)
A64: Tip: | B64: Enter every receipt on its own row so the summaries and chart stay accurate.

Sheet Job 161
A1: Hammer Brick & Home LLC - Job Tracker
A3: Job Name:
A4: Client:
A5: Address:
A6: Start Date:
A7: End Date:
A9: Contract Price:
A10: Change Orders:
A11: Tax Rate:
A12: Total Budget: | B12: =B9+B10
A15: Expense Log (enter one line per receipt)
A16: Date | B16: Type | C16: Description | D16: Vendor | E16: Cost
A59: Total Expenses: | B59: =SUM(E17:E56) | D59: Most Expensive Item: | E59: =IFERROR(INDEX(C17:C56,MATCH(MAX(E17:E56),E17:E56,0)),"")
A60: Profit Before Tax: | B60: =B12-B59 | D60: Largest Expense: | E60: =MAX(E17:E56)
A61: Tax Amount: | B61: =IF(B60>0,B60*$B$11,0)
A62: Net Profit: | B62: =B60-B61
A63: Net Loss: | B63: =IF(B62<0,ABS(B62),0)
A64: Tip: | B64: Enter every receipt on its own row so the summaries and chart stay accurate.

Sheet Job 162
A1: Hammer Brick & Home LLC - Job Tracker
A3: Job Name:
A4: Client:
A5: Address:
A6: Start Date:
A7: End Date:
A9: Contract Price:
A10: Change Orders:
A11: Tax Rate:
A12: Total Budget: | B12: =B9+B10
A15: Expense Log (enter one line per receipt)
A16: Date | B16: Type | C16: Description | D16: Vendor | E16: Cost
A59: Total Expenses: | B59: =SUM(E17:E56) | D59: Most Expensive Item: | E59: =IFERROR(INDEX(C17:C56,MATCH(MAX(E17:E56),E17:E56,0)),"")
A60: Profit Before Tax: | B60: =B12-B59 | D60: Largest Expense: | E60: =MAX(E17:E56)
A61: Tax Amount: | B61: =IF(B60>0,B60*$B$11,0)
A62: Net Profit: | B62: =B60-B61
A63: Net Loss: | B63: =IF(B62<0,ABS(B62),0)
A64: Tip: | B64: Enter every receipt on its own row so the summaries and chart stay accurate.

Sheet Job 163
A1: Hammer Brick & Home LLC - Job Tracker
A3: Job Name:
A4: Client:
A5: Address:
A6: Start Date:
A7: End Date:
A9: Contract Price:
A10: Change Orders:
A11: Tax Rate:
A12: Total Budget: | B12: =B9+B10
A15: Expense Log (enter one line per receipt)
A16: Date | B16: Type | C16: Description | D16: Vendor | E16: Cost
A59: Total Expenses: | B59: =SUM(E17:E56) | D59: Most Expensive Item: | E59: =IFERROR(INDEX(C17:C56,MATCH(MAX(E17:E56),E17:E56,0)),"")
A60: Profit Before Tax: | B60: =B12-B59 | D60: Largest Expense: | E60: =MAX(E17:E56)
A61: Tax Amount: | B61: =IF(B60>0,B60*$B$11,0)
A62: Net Profit: | B62: =B60-B61
A63: Net Loss: | B63: =IF(B62<0,ABS(B62),0)
A64: Tip: | B64: Enter every receipt on its own row so the summaries and chart stay accurate.

Sheet Job 164
A1: Hammer Brick & Home LLC - Job Tracker
A3: Job Name:
A4: Client:
A5: Address:
A6: Start Date:
A7: End Date:
A9: Contract Price:
A10: Change Orders:
A11: Tax Rate:
A12: Total Budget: | B12: =B9+B10
A15: Expense Log (enter one line per receipt)
A16: Date | B16: Type | C16: Description | D16: Vendor | E16: Cost
A59: Total Expenses: | B59: =SUM(E17:E56) | D59: Most Expensive Item: | E59: =IFERROR(INDEX(C17:C56,MATCH(MAX(E17:E56),E17:E56,0)),"")
A60: Profit Before Tax: | B60: =B12-B59 | D60: Largest Expense: | E60: =MAX(E17:E56)
A61: Tax Amount: | B61: =IF(B60>0,B60*$B$11,0)
A62: Net Profit: | B62: =B60-B61
A63: Net Loss: | B63: =IF(B62<0,ABS(B62),0)
A64: Tip: | B64: Enter every receipt on its own row so the summaries and chart stay accurate.

Sheet Job 165
A1: Hammer Brick & Home LLC - Job Tracker
A3: Job Name:
A4: Client:
A5: Address:
A6: Start Date:
A7: End Date:
A9: Contract Price:
A10: Change Orders:
A11: Tax Rate:
A12: Total Budget: | B12: =B9+B10
A15: Expense Log (enter one line per receipt)
A16: Date | B16: Type | C16: Description | D16: Vendor | E16: Cost
A59: Total Expenses: | B59: =SUM(E17:E56) | D59: Most Expensive Item: | E59: =IFERROR(INDEX(C17:C56,MATCH(MAX(E17:E56),E17:E56,0)),"")
A60: Profit Before Tax: | B60: =B12-B59 | D60: Largest Expense: | E60: =MAX(E17:E56)
A61: Tax Amount: | B61: =IF(B60>0,B60*$B$11,0)
A62: Net Profit: | B62: =B60-B61
A63: Net Loss: | B63: =IF(B62<0,ABS(B62),0)
A64: Tip: | B64: Enter every receipt on its own row so the summaries and chart stay accurate.

Sheet Job 166
A1: Hammer Brick & Home LLC - Job Tracker
A3: Job Name:
A4: Client:
A5: Address:
A6: Start Date:
A7: End Date:
A9: Contract Price:
A10: Change Orders:
A11: Tax Rate:
A12: Total Budget: | B12: =B9+B10
A15: Expense Log (enter one line per receipt)
A16: Date | B16: Type | C16: Description | D16: Vendor | E16: Cost
A59: Total Expenses: | B59: =SUM(E17:E56) | D59: Most Expensive Item: | E59: =IFERROR(INDEX(C17:C56,MATCH(MAX(E17:E56),E17:E56,0)),"")
A60: Profit Before Tax: | B60: =B12-B59 | D60: Largest Expense: | E60: =MAX(E17:E56)
A61: Tax Amount: | B61: =IF(B60>0,B60*$B$11,0)
A62: Net Profit: | B62: =B60-B61
A63: Net Loss: | B63: =IF(B62<0,ABS(B62),0)
A64: Tip: | B64: Enter every receipt on its own row so the summaries and chart stay accurate.

Sheet Job 167
A1: Hammer Brick & Home LLC - Job Tracker
A3: Job Name:
A4: Client:
A5: Address:
A6: Start Date:
A7: End Date:
A9: Contract Price:
A10: Change Orders:
A11: Tax Rate:
A12: Total Budget: | B12: =B9+B10
A15: Expense Log (enter one line per receipt)
A16: Date | B16: Type | C16: Description | D16: Vendor | E16: Cost
A59: Total Expenses: | B59: =SUM(E17:E56) | D59: Most Expensive Item: | E59: =IFERROR(INDEX(C17:C56,MATCH(MAX(E17:E56),E17:E56,0)),"")
A60: Profit Before Tax: | B60: =B12-B59 | D60: Largest Expense: | E60: =MAX(E17:E56)
A61: Tax Amount: | B61: =IF(B60>0,B60*$B$11,0)
A62: Net Profit: | B62: =B60-B61
A63: Net Loss: | B63: =IF(B62<0,ABS(B62),0)
A64: Tip: | B64: Enter every receipt on its own row so the summaries and chart stay accurate.

Sheet Job 168
A1: Hammer Brick & Home LLC - Job Tracker
A3: Job Name:
A4: Client:
A5: Address:
A6: Start Date:
A7: End Date:
A9: Contract Price:
A10: Change Orders:
A11: Tax Rate:
A12: Total Budget: | B12: =B9+B10
A15: Expense Log (enter one line per receipt)
A16: Date | B16: Type | C16: Description | D16: Vendor | E16: Cost
A59: Total Expenses: | B59: =SUM(E17:E56) | D59: Most Expensive Item: | E59: =IFERROR(INDEX(C17:C56,MATCH(MAX(E17:E56),E17:E56,0)),"")
A60: Profit Before Tax: | B60: =B12-B59 | D60: Largest Expense: | E60: =MAX(E17:E56)
A61: Tax Amount: | B61: =IF(B60>0,B60*$B$11,0)
A62: Net Profit: | B62: =B60-B61
A63: Net Loss: | B63: =IF(B62<0,ABS(B62),0)
A64: Tip: | B64: Enter every receipt on its own row so the summaries and chart stay accurate.

Sheet Job 169
A1: Hammer Brick & Home LLC - Job Tracker
A3: Job Name:
A4: Client:
A5: Address:
A6: Start Date:
A7: End Date:
A9: Contract Price:
A10: Change Orders:
A11: Tax Rate:
A12: Total Budget: | B12: =B9+B10
A15: Expense Log (enter one line per receipt)
A16: Date | B16: Type | C16: Description | D16: Vendor | E16: Cost
A59: Total Expenses: | B59: =SUM(E17:E56) | D59: Most Expensive Item: | E59: =IFERROR(INDEX(C17:C56,MATCH(MAX(E17:E56),E17:E56,0)),"")
A60: Profit Before Tax: | B60: =B12-B59 | D60: Largest Expense: | E60: =MAX(E17:E56)
A61: Tax Amount: | B61: =IF(B60>0,B60*$B$11,0)
A62: Net Profit: | B62: =B60-B61
A63: Net Loss: | B63: =IF(B62<0,ABS(B62),0)
A64: Tip: | B64: Enter every receipt on its own row so the summaries and chart stay accurate.

Sheet Job 170
A1: Hammer Brick & Home LLC - Job Tracker
A3: Job Name:
A4: Client:
A5: Address:
A6: Start Date:
A7: End Date:
A9: Contract Price:
A10: Change Orders:
A11: Tax Rate:
A12: Total Budget: | B12: =B9+B10
A15: Expense Log (enter one line per receipt)
A16: Date | B16: Type | C16: Description | D16: Vendor | E16: Cost
A59: Total Expenses: | B59: =SUM(E17:E56) | D59: Most Expensive Item: | E59: =IFERROR(INDEX(C17:C56,MATCH(MAX(E17:E56),E17:E56,0)),"")
A60: Profit Before Tax: | B60: =B12-B59 | D60: Largest Expense: | E60: =MAX(E17:E56)
A61: Tax Amount: | B61: =IF(B60>0,B60*$B$11,0)
A62: Net Profit: | B62: =B60-B61
A63: Net Loss: | B63: =IF(B62<0,ABS(B62),0)
A64: Tip: | B64: Enter every receipt on its own row so the summaries and chart stay accurate.

Sheet Job 171
A1: Hammer Brick & Home LLC - Job Tracker
A3: Job Name:
A4: Client:
A5: Address:
A6: Start Date:
A7: End Date:
A9: Contract Price:
A10: Change Orders:
A11: Tax Rate:
A12: Total Budget: | B12: =B9+B10
A15: Expense Log (enter one line per receipt)
A16: Date | B16: Type | C16: Description | D16: Vendor | E16: Cost
A59: Total Expenses: | B59: =SUM(E17:E56) | D59: Most Expensive Item: | E59: =IFERROR(INDEX(C17:C56,MATCH(MAX(E17:E56),E17:E56,0)),"")
A60: Profit Before Tax: | B60: =B12-B59 | D60: Largest Expense: | E60: =MAX(E17:E56)
A61: Tax Amount: | B61: =IF(B60>0,B60*$B$11,0)
A62: Net Profit: | B62: =B60-B61
A63: Net Loss: | B63: =IF(B62<0,ABS(B62),0)
A64: Tip: | B64: Enter every receipt on its own row so the summaries and chart stay accurate.

Sheet Job 172
A1: Hammer Brick & Home LLC - Job Tracker
A3: Job Name:
A4: Client:
A5: Address:
A6: Start Date:
A7: End Date:
A9: Contract Price:
A10: Change Orders:
A11: Tax Rate:
A12: Total Budget: | B12: =B9+B10
A15: Expense Log (enter one line per receipt)
A16: Date | B16: Type | C16: Description | D16: Vendor | E16: Cost
A59: Total Expenses: | B59: =SUM(E17:E56) | D59: Most Expensive Item: | E59: =IFERROR(INDEX(C17:C56,MATCH(MAX(E17:E56),E17:E56,0)),"")
A60: Profit Before Tax: | B60: =B12-B59 | D60: Largest Expense: | E60: =MAX(E17:E56)
A61: Tax Amount: | B61: =IF(B60>0,B60*$B$11,0)
A62: Net Profit: | B62: =B60-B61
A63: Net Loss: | B63: =IF(B62<0,ABS(B62),0)
A64: Tip: | B64: Enter every receipt on its own row so the summaries and chart stay accurate.

Sheet Job 173
A1: Hammer Brick & Home LLC - Job Tracker
A3: Job Name:
A4: Client:
A5: Address:
A6: Start Date:
A7: End Date:
A9: Contract Price:
A10: Change Orders:
A11: Tax Rate:
A12: Total Budget: | B12: =B9+B10
A15: Expense Log (enter one line per receipt)
A16: Date | B16: Type | C16: Description | D16: Vendor | E16: Cost
A59: Total Expenses: | B59: =SUM(E17:E56) | D59: Most Expensive Item: | E59: =IFERROR(INDEX(C17:C56,MATCH(MAX(E17:E56),E17:E56,0)),"")
A60: Profit Before Tax: | B60: =B12-B59 | D60: Largest Expense: | E60: =MAX(E17:E56)
A61: Tax Amount: | B61: =IF(B60>0,B60*$B$11,0)
A62: Net Profit: | B62: =B60-B61
A63: Net Loss: | B63: =IF(B62<0,ABS(B62),0)
A64: Tip: | B64: Enter every receipt on its own row so the summaries and chart stay accurate.

Sheet Job 174
A1: Hammer Brick & Home LLC - Job Tracker
A3: Job Name:
A4: Client:
A5: Address:
A6: Start Date:
A7: End Date:
A9: Contract Price:
A10: Change Orders:
A11: Tax Rate:
A12: Total Budget: | B12: =B9+B10
A15: Expense Log (enter one line per receipt)
A16: Date | B16: Type | C16: Description | D16: Vendor | E16: Cost
A59: Total Expenses: | B59: =SUM(E17:E56) | D59: Most Expensive Item: | E59: =IFERROR(INDEX(C17:C56,MATCH(MAX(E17:E56),E17:E56,0)),"")
A60: Profit Before Tax: | B60: =B12-B59 | D60: Largest Expense: | E60: =MAX(E17:E56)
A61: Tax Amount: | B61: =IF(B60>0,B60*$B$11,0)
A62: Net Profit: | B62: =B60-B61
A63: Net Loss: | B63: =IF(B62<0,ABS(B62),0)
A64: Tip: | B64: Enter every receipt on its own row so the summaries and chart stay accurate.

Sheet Job 175
A1: Hammer Brick & Home LLC - Job Tracker
A3: Job Name:
A4: Client:
A5: Address:
A6: Start Date:
A7: End Date:
A9: Contract Price:
A10: Change Orders:
A11: Tax Rate:
A12: Total Budget: | B12: =B9+B10
A15: Expense Log (enter one line per receipt)
A16: Date | B16: Type | C16: Description | D16: Vendor | E16: Cost
A59: Total Expenses: | B59: =SUM(E17:E56) | D59: Most Expensive Item: | E59: =IFERROR(INDEX(C17:C56,MATCH(MAX(E17:E56),E17:E56,0)),"")
A60: Profit Before Tax: | B60: =B12-B59 | D60: Largest Expense: | E60: =MAX(E17:E56)
A61: Tax Amount: | B61: =IF(B60>0,B60*$B$11,0)
A62: Net Profit: | B62: =B60-B61
A63: Net Loss: | B63: =IF(B62<0,ABS(B62),0)
A64: Tip: | B64: Enter every receipt on its own row so the summaries and chart stay accurate.

Sheet Job 176
A1: Hammer Brick & Home LLC - Job Tracker
A3: Job Name:
A4: Client:
A5: Address:
A6: Start Date:
A7: End Date:
A9: Contract Price:
A10: Change Orders:
A11: Tax Rate:
A12: Total Budget: | B12: =B9+B10
A15: Expense Log (enter one line per receipt)
A16: Date | B16: Type | C16: Description | D16: Vendor | E16: Cost
A59: Total Expenses: | B59: =SUM(E17:E56) | D59: Most Expensive Item: | E59: =IFERROR(INDEX(C17:C56,MATCH(MAX(E17:E56),E17:E56,0)),"")
A60: Profit Before Tax: | B60: =B12-B59 | D60: Largest Expense: | E60: =MAX(E17:E56)
A61: Tax Amount: | B61: =IF(B60>0,B60*$B$11,0)
A62: Net Profit: | B62: =B60-B61
A63: Net Loss: | B63: =IF(B62<0,ABS(B62),0)
A64: Tip: | B64: Enter every receipt on its own row so the summaries and chart stay accurate.

Sheet Job 177
A1: Hammer Brick & Home LLC - Job Tracker
A3: Job Name:
A4: Client:
A5: Address:
A6: Start Date:
A7: End Date:
A9: Contract Price:
A10: Change Orders:
A11: Tax Rate:
A12: Total Budget: | B12: =B9+B10
A15: Expense Log (enter one line per receipt)
A16: Date | B16: Type | C16: Description | D16: Vendor | E16: Cost
A59: Total Expenses: | B59: =SUM(E17:E56) | D59: Most Expensive Item: | E59: =IFERROR(INDEX(C17:C56,MATCH(MAX(E17:E56),E17:E56,0)),"")
A60: Profit Before Tax: | B60: =B12-B59 | D60: Largest Expense: | E60: =MAX(E17:E56)
A61: Tax Amount: | B61: =IF(B60>0,B60*$B$11,0)
A62: Net Profit: | B62: =B60-B61
A63: Net Loss: | B63: =IF(B62<0,ABS(B62),0)
A64: Tip: | B64: Enter every receipt on its own row so the summaries and chart stay accurate.

Sheet Job 178
A1: Hammer Brick & Home LLC - Job Tracker
A3: Job Name:
A4: Client:
A5: Address:
A6: Start Date:
A7: End Date:
A9: Contract Price:
A10: Change Orders:
A11: Tax Rate:
A12: Total Budget: | B12: =B9+B10
A15: Expense Log (enter one line per receipt)
A16: Date | B16: Type | C16: Description | D16: Vendor | E16: Cost
A59: Total Expenses: | B59: =SUM(E17:E56) | D59: Most Expensive Item: | E59: =IFERROR(INDEX(C17:C56,MATCH(MAX(E17:E56),E17:E56,0)),"")
A60: Profit Before Tax: | B60: =B12-B59 | D60: Largest Expense: | E60: =MAX(E17:E56)
A61: Tax Amount: | B61: =IF(B60>0,B60*$B$11,0)
A62: Net Profit: | B62: =B60-B61
A63: Net Loss: | B63: =IF(B62<0,ABS(B62),0)
A64: Tip: | B64: Enter every receipt on its own row so the summaries and chart stay accurate.

Sheet Job 179
A1: Hammer Brick & Home LLC - Job Tracker
A3: Job Name:
A4: Client:
A5: Address:
A6: Start Date:
A7: End Date:
A9: Contract Price:
A10: Change Orders:
A11: Tax Rate:
A12: Total Budget: | B12: =B9+B10
A15: Expense Log (enter one line per receipt)
A16: Date | B16: Type | C16: Description | D16: Vendor | E16: Cost
A59: Total Expenses: | B59: =SUM(E17:E56) | D59: Most Expensive Item: | E59: =IFERROR(INDEX(C17:C56,MATCH(MAX(E17:E56),E17:E56,0)),"")
A60: Profit Before Tax: | B60: =B12-B59 | D60: Largest Expense: | E60: =MAX(E17:E56)
A61: Tax Amount: | B61: =IF(B60>0,B60*$B$11,0)
A62: Net Profit: | B62: =B60-B61
A63: Net Loss: | B63: =IF(B62<0,ABS(B62),0)
A64: Tip: | B64: Enter every receipt on its own row so the summaries and chart stay accurate.

Sheet Job 180
A1: Hammer Brick & Home LLC - Job Tracker
A3: Job Name:
A4: Client:
A5: Address:
A6: Start Date:
A7: End Date:
A9: Contract Price:
A10: Change Orders:
A11: Tax Rate:
A12: Total Budget: | B12: =B9+B10
A15: Expense Log (enter one line per receipt)
A16: Date | B16: Type | C16: Description | D16: Vendor | E16: Cost
A59: Total Expenses: | B59: =SUM(E17:E56) | D59: Most Expensive Item: | E59: =IFERROR(INDEX(C17:C56,MATCH(MAX(E17:E56),E17:E56,0)),"")
A60: Profit Before Tax: | B60: =B12-B59 | D60: Largest Expense: | E60: =MAX(E17:E56)
A61: Tax Amount: | B61: =IF(B60>0,B60*$B$11,0)
A62: Net Profit: | B62: =B60-B61
A63: Net Loss: | B63: =IF(B62<0,ABS(B62),0)
A64: Tip: | B64: Enter every receipt on its own row so the summaries and chart stay accurate.

Sheet Job 181
A1: Hammer Brick & Home LLC - Job Tracker
A3: Job Name:
A4: Client:
A5: Address:
A6: Start Date:
A7: End Date:
A9: Contract Price:
A10: Change Orders:
A11: Tax Rate:
A12: Total Budget: | B12: =B9+B10
A15: Expense Log (enter one line per receipt)
A16: Date | B16: Type | C16: Description | D16: Vendor | E16: Cost
A59: Total Expenses: | B59: =SUM(E17:E56) | D59: Most Expensive Item: | E59: =IFERROR(INDEX(C17:C56,MATCH(MAX(E17:E56),E17:E56,0)),"")
A60: Profit Before Tax: | B60: =B12-B59 | D60: Largest Expense: | E60: =MAX(E17:E56)
A61: Tax Amount: | B61: =IF(B60>0,B60*$B$11,0)
A62: Net Profit: | B62: =B60-B61
A63: Net Loss: | B63: =IF(B62<0,ABS(B62),0)
A64: Tip: | B64: Enter every receipt on its own row so the summaries and chart stay accurate.

Sheet Job 182
A1: Hammer Brick & Home LLC - Job Tracker
A3: Job Name:
A4: Client:
A5: Address:
A6: Start Date:
A7: End Date:
A9: Contract Price:
A10: Change Orders:
A11: Tax Rate:
A12: Total Budget: | B12: =B9+B10
A15: Expense Log (enter one line per receipt)
A16: Date | B16: Type | C16: Description | D16: Vendor | E16: Cost
A59: Total Expenses: | B59: =SUM(E17:E56) | D59: Most Expensive Item: | E59: =IFERROR(INDEX(C17:C56,MATCH(MAX(E17:E56),E17:E56,0)),"")
A60: Profit Before Tax: | B60: =B12-B59 | D60: Largest Expense: | E60: =MAX(E17:E56)
A61: Tax Amount: | B61: =IF(B60>0,B60*$B$11,0)
A62: Net Profit: | B62: =B60-B61
A63: Net Loss: | B63: =IF(B62<0,ABS(B62),0)
A64: Tip: | B64: Enter every receipt on its own row so the summaries and chart stay accurate.

Sheet Job 183
A1: Hammer Brick & Home LLC - Job Tracker
A3: Job Name:
A4: Client:
A5: Address:
A6: Start Date:
A7: End Date:
A9: Contract Price:
A10: Change Orders:
A11: Tax Rate:
A12: Total Budget: | B12: =B9+B10
A15: Expense Log (enter one line per receipt)
A16: Date | B16: Type | C16: Description | D16: Vendor | E16: Cost
A59: Total Expenses: | B59: =SUM(E17:E56) | D59: Most Expensive Item: | E59: =IFERROR(INDEX(C17:C56,MATCH(MAX(E17:E56),E17:E56,0)),"")
A60: Profit Before Tax: | B60: =B12-B59 | D60: Largest Expense: | E60: =MAX(E17:E56)
A61: Tax Amount: | B61: =IF(B60>0,B60*$B$11,0)
A62: Net Profit: | B62: =B60-B61
A63: Net Loss: | B63: =IF(B62<0,ABS(B62),0)
A64: Tip: | B64: Enter every receipt on its own row so the summaries and chart stay accurate.

Sheet Job 184
A1: Hammer Brick & Home LLC - Job Tracker
A3: Job Name:
A4: Client:
A5: Address:
A6: Start Date:
A7: End Date:
A9: Contract Price:
A10: Change Orders:
A11: Tax Rate:
A12: Total Budget: | B12: =B9+B10
A15: Expense Log (enter one line per receipt)
A16: Date | B16: Type | C16: Description | D16: Vendor | E16: Cost
A59: Total Expenses: | B59: =SUM(E17:E56) | D59: Most Expensive Item: | E59: =IFERROR(INDEX(C17:C56,MATCH(MAX(E17:E56),E17:E56,0)),"")
A60: Profit Before Tax: | B60: =B12-B59 | D60: Largest Expense: | E60: =MAX(E17:E56)
A61: Tax Amount: | B61: =IF(B60>0,B60*$B$11,0)
A62: Net Profit: | B62: =B60-B61
A63: Net Loss: | B63: =IF(B62<0,ABS(B62),0)
A64: Tip: | B64: Enter every receipt on its own row so the summaries and chart stay accurate.

Sheet Job 185
A1: Hammer Brick & Home LLC - Job Tracker
A3: Job Name:
A4: Client:
A5: Address:
A6: Start Date:
A7: End Date:
A9: Contract Price:
A10: Change Orders:
A11: Tax Rate:
A12: Total Budget: | B12: =B9+B10
A15: Expense Log (enter one line per receipt)
A16: Date | B16: Type | C16: Description | D16: Vendor | E16: Cost
A59: Total Expenses: | B59: =SUM(E17:E56) | D59: Most Expensive Item: | E59: =IFERROR(INDEX(C17:C56,MATCH(MAX(E17:E56),E17:E56,0)),"")
A60: Profit Before Tax: | B60: =B12-B59 | D60: Largest Expense: | E60: =MAX(E17:E56)
A61: Tax Amount: | B61: =IF(B60>0,B60*$B$11,0)
A62: Net Profit: | B62: =B60-B61
A63: Net Loss: | B63: =IF(B62<0,ABS(B62),0)
A64: Tip: | B64: Enter every receipt on its own row so the summaries and chart stay accurate.

Sheet Job 186
A1: Hammer Brick & Home LLC - Job Tracker
A3: Job Name:
A4: Client:
A5: Address:
A6: Start Date:
A7: End Date:
A9: Contract Price:
A10: Change Orders:
A11: Tax Rate:
A12: Total Budget: | B12: =B9+B10
A15: Expense Log (enter one line per receipt)
A16: Date | B16: Type | C16: Description | D16: Vendor | E16: Cost
A59: Total Expenses: | B59: =SUM(E17:E56) | D59: Most Expensive Item: | E59: =IFERROR(INDEX(C17:C56,MATCH(MAX(E17:E56),E17:E56,0)),"")
A60: Profit Before Tax: | B60: =B12-B59 | D60: Largest Expense: | E60: =MAX(E17:E56)
A61: Tax Amount: | B61: =IF(B60>0,B60*$B$11,0)
A62: Net Profit: | B62: =B60-B61
A63: Net Loss: | B63: =IF(B62<0,ABS(B62),0)
A64: Tip: | B64: Enter every receipt on its own row so the summaries and chart stay accurate.

Sheet Job 187
A1: Hammer Brick & Home LLC - Job Tracker
A3: Job Name:
A4: Client:
A5: Address:
A6: Start Date:
A7: End Date:
A9: Contract Price:
A10: Change Orders:
A11: Tax Rate:
A12: Total Budget: | B12: =B9+B10
A15: Expense Log (enter one line per receipt)
A16: Date | B16: Type | C16: Description | D16: Vendor | E16: Cost
A59: Total Expenses: | B59: =SUM(E17:E56) | D59: Most Expensive Item: | E59: =IFERROR(INDEX(C17:C56,MATCH(MAX(E17:E56),E17:E56,0)),"")
A60: Profit Before Tax: | B60: =B12-B59 | D60: Largest Expense: | E60: =MAX(E17:E56)
A61: Tax Amount: | B61: =IF(B60>0,B60*$B$11,0)
A62: Net Profit: | B62: =B60-B61
A63: Net Loss: | B63: =IF(B62<0,ABS(B62),0)
A64: Tip: | B64: Enter every receipt on its own row so the summaries and chart stay accurate.

Sheet Job 188
A1: Hammer Brick & Home LLC - Job Tracker
A3: Job Name:
A4: Client:
A5: Address:
A6: Start Date:
A7: End Date:
A9: Contract Price:
A10: Change Orders:
A11: Tax Rate:
A12: Total Budget: | B12: =B9+B10
A15: Expense Log (enter one line per receipt)
A16: Date | B16: Type | C16: Description | D16: Vendor | E16: Cost
A59: Total Expenses: | B59: =SUM(E17:E56) | D59: Most Expensive Item: | E59: =IFERROR(INDEX(C17:C56,MATCH(MAX(E17:E56),E17:E56,0)),"")
A60: Profit Before Tax: | B60: =B12-B59 | D60: Largest Expense: | E60: =MAX(E17:E56)
A61: Tax Amount: | B61: =IF(B60>0,B60*$B$11,0)
A62: Net Profit: | B62: =B60-B61
A63: Net Loss: | B63: =IF(B62<0,ABS(B62),0)
A64: Tip: | B64: Enter every receipt on its own row so the summaries and chart stay accurate.

Sheet Job 189
A1: Hammer Brick & Home LLC - Job Tracker
A3: Job Name:
A4: Client:
A5: Address:
A6: Start Date:
A7: End Date:
A9: Contract Price:
A10: Change Orders:
A11: Tax Rate:
A12: Total Budget: | B12: =B9+B10
A15: Expense Log (enter one line per receipt)
A16: Date | B16: Type | C16: Description | D16: Vendor | E16: Cost
A59: Total Expenses: | B59: =SUM(E17:E56) | D59: Most Expensive Item: | E59: =IFERROR(INDEX(C17:C56,MATCH(MAX(E17:E56),E17:E56,0)),"")
A60: Profit Before Tax: | B60: =B12-B59 | D60: Largest Expense: | E60: =MAX(E17:E56)
A61: Tax Amount: | B61: =IF(B60>0,B60*$B$11,0)
A62: Net Profit: | B62: =B60-B61
A63: Net Loss: | B63: =IF(B62<0,ABS(B62),0)
A64: Tip: | B64: Enter every receipt on its own row so the summaries and chart stay accurate.

Sheet Job 190
A1: Hammer Brick & Home LLC - Job Tracker
A3: Job Name:
A4: Client:
A5: Address:
A6: Start Date:
A7: End Date:
A9: Contract Price:
A10: Change Orders:
A11: Tax Rate:
A12: Total Budget: | B12: =B9+B10
A15: Expense Log (enter one line per receipt)
A16: Date | B16: Type | C16: Description | D16: Vendor | E16: Cost
A59: Total Expenses: | B59: =SUM(E17:E56) | D59: Most Expensive Item: | E59: =IFERROR(INDEX(C17:C56,MATCH(MAX(E17:E56),E17:E56,0)),"")
A60: Profit Before Tax: | B60: =B12-B59 | D60: Largest Expense: | E60: =MAX(E17:E56)
A61: Tax Amount: | B61: =IF(B60>0,B60*$B$11,0)
A62: Net Profit: | B62: =B60-B61
A63: Net Loss: | B63: =IF(B62<0,ABS(B62),0)
A64: Tip: | B64: Enter every receipt on its own row so the summaries and chart stay accurate.

Sheet Job 191
A1: Hammer Brick & Home LLC - Job Tracker
A3: Job Name:
A4: Client:
A5: Address:
A6: Start Date:
A7: End Date:
A9: Contract Price:
A10: Change Orders:
A11: Tax Rate:
A12: Total Budget: | B12: =B9+B10
A15: Expense Log (enter one line per receipt)
A16: Date | B16: Type | C16: Description | D16: Vendor | E16: Cost
A59: Total Expenses: | B59: =SUM(E17:E56) | D59: Most Expensive Item: | E59: =IFERROR(INDEX(C17:C56,MATCH(MAX(E17:E56),E17:E56,0)),"")
A60: Profit Before Tax: | B60: =B12-B59 | D60: Largest Expense: | E60: =MAX(E17:E56)
A61: Tax Amount: | B61: =IF(B60>0,B60*$B$11,0)
A62: Net Profit: | B62: =B60-B61
A63: Net Loss: | B63: =IF(B62<0,ABS(B62),0)
A64: Tip: | B64: Enter every receipt on its own row so the summaries and chart stay accurate.

Sheet Job 192
A1: Hammer Brick & Home LLC - Job Tracker
A3: Job Name:
A4: Client:
A5: Address:
A6: Start Date:
A7: End Date:
A9: Contract Price:
A10: Change Orders:
A11: Tax Rate:
A12: Total Budget: | B12: =B9+B10
A15: Expense Log (enter one line per receipt)
A16: Date | B16: Type | C16: Description | D16: Vendor | E16: Cost
A59: Total Expenses: | B59: =SUM(E17:E56) | D59: Most Expensive Item: | E59: =IFERROR(INDEX(C17:C56,MATCH(MAX(E17:E56),E17:E56,0)),"")
A60: Profit Before Tax: | B60: =B12-B59 | D60: Largest Expense: | E60: =MAX(E17:E56)
A61: Tax Amount: | B61: =IF(B60>0,B60*$B$11,0)
A62: Net Profit: | B62: =B60-B61
A63: Net Loss: | B63: =IF(B62<0,ABS(B62),0)
A64: Tip: | B64: Enter every receipt on its own row so the summaries and chart stay accurate.

Sheet Job 193
A1: Hammer Brick & Home LLC - Job Tracker
A3: Job Name:
A4: Client:
A5: Address:
A6: Start Date:
A7: End Date:
A9: Contract Price:
A10: Change Orders:
A11: Tax Rate:
A12: Total Budget: | B12: =B9+B10
A15: Expense Log (enter one line per receipt)
A16: Date | B16: Type | C16: Description | D16: Vendor | E16: Cost
A59: Total Expenses: | B59: =SUM(E17:E56) | D59: Most Expensive Item: | E59: =IFERROR(INDEX(C17:C56,MATCH(MAX(E17:E56),E17:E56,0)),"")
A60: Profit Before Tax: | B60: =B12-B59 | D60: Largest Expense: | E60: =MAX(E17:E56)
A61: Tax Amount: | B61: =IF(B60>0,B60*$B$11,0)
A62: Net Profit: | B62: =B60-B61
A63: Net Loss: | B63: =IF(B62<0,ABS(B62),0)
A64: Tip: | B64: Enter every receipt on its own row so the summaries and chart stay accurate.

Sheet Job 194
A1: Hammer Brick & Home LLC - Job Tracker
A3: Job Name:
A4: Client:
A5: Address:
A6: Start Date:
A7: End Date:
A9: Contract Price:
A10: Change Orders:
A11: Tax Rate:
A12: Total Budget: | B12: =B9+B10
A15: Expense Log (enter one line per receipt)
A16: Date | B16: Type | C16: Description | D16: Vendor | E16: Cost
A59: Total Expenses: | B59: =SUM(E17:E56) | D59: Most Expensive Item: | E59: =IFERROR(INDEX(C17:C56,MATCH(MAX(E17:E56),E17:E56,0)),"")
A60: Profit Before Tax: | B60: =B12-B59 | D60: Largest Expense: | E60: =MAX(E17:E56)
A61: Tax Amount: | B61: =IF(B60>0,B60*$B$11,0)
A62: Net Profit: | B62: =B60-B61
A63: Net Loss: | B63: =IF(B62<0,ABS(B62),0)
A64: Tip: | B64: Enter every receipt on its own row so the summaries and chart stay accurate.

Sheet Job 195
A1: Hammer Brick & Home LLC - Job Tracker
A3: Job Name:
A4: Client:
A5: Address:
A6: Start Date:
A7: End Date:
A9: Contract Price:
A10: Change Orders:
A11: Tax Rate:
A12: Total Budget: | B12: =B9+B10
A15: Expense Log (enter one line per receipt)
A16: Date | B16: Type | C16: Description | D16: Vendor | E16: Cost
A59: Total Expenses: | B59: =SUM(E17:E56) | D59: Most Expensive Item: | E59: =IFERROR(INDEX(C17:C56,MATCH(MAX(E17:E56),E17:E56,0)),"")
A60: Profit Before Tax: | B60: =B12-B59 | D60: Largest Expense: | E60: =MAX(E17:E56)
A61: Tax Amount: | B61: =IF(B60>0,B60*$B$11,0)
A62: Net Profit: | B62: =B60-B61
A63: Net Loss: | B63: =IF(B62<0,ABS(B62),0)
A64: Tip: | B64: Enter every receipt on its own row so the summaries and chart stay accurate.

Sheet Job 196
A1: Hammer Brick & Home LLC - Job Tracker
A3: Job Name:
A4: Client:
A5: Address:
A6: Start Date:
A7: End Date:
A9: Contract Price:
A10: Change Orders:
A11: Tax Rate:
A12: Total Budget: | B12: =B9+B10
A15: Expense Log (enter one line per receipt)
A16: Date | B16: Type | C16: Description | D16: Vendor | E16: Cost
A59: Total Expenses: | B59: =SUM(E17:E56) | D59: Most Expensive Item: | E59: =IFERROR(INDEX(C17:C56,MATCH(MAX(E17:E56),E17:E56,0)),"")
A60: Profit Before Tax: | B60: =B12-B59 | D60: Largest Expense: | E60: =MAX(E17:E56)
A61: Tax Amount: | B61: =IF(B60>0,B60*$B$11,0)
A62: Net Profit: | B62: =B60-B61
A63: Net Loss: | B63: =IF(B62<0,ABS(B62),0)
A64: Tip: | B64: Enter every receipt on its own row so the summaries and chart stay accurate.

Sheet Job 197
A1: Hammer Brick & Home LLC - Job Tracker
A3: Job Name:
A4: Client:
A5: Address:
A6: Start Date:
A7: End Date:
A9: Contract Price:
A10: Change Orders:
A11: Tax Rate:
A12: Total Budget: | B12: =B9+B10
A15: Expense Log (enter one line per receipt)
A16: Date | B16: Type | C16: Description | D16: Vendor | E16: Cost
A59: Total Expenses: | B59: =SUM(E17:E56) | D59: Most Expensive Item: | E59: =IFERROR(INDEX(C17:C56,MATCH(MAX(E17:E56),E17:E56,0)),"")
A60: Profit Before Tax: | B60: =B12-B59 | D60: Largest Expense: | E60: =MAX(E17:E56)
A61: Tax Amount: | B61: =IF(B60>0,B60*$B$11,0)
A62: Net Profit: | B62: =B60-B61
A63: Net Loss: | B63: =IF(B62<0,ABS(B62),0)
A64: Tip: | B64: Enter every receipt on its own row so the summaries and chart stay accurate.

Sheet Job 198
A1: Hammer Brick & Home LLC - Job Tracker
A3: Job Name:
A4: Client:
A5: Address:
A6: Start Date:
A7: End Date:
A9: Contract Price:
A10: Change Orders:
A11: Tax Rate:
A12: Total Budget: | B12: =B9+B10
A15: Expense Log (enter one line per receipt)
A16: Date | B16: Type | C16: Description | D16: Vendor | E16: Cost
A59: Total Expenses: | B59: =SUM(E17:E56) | D59: Most Expensive Item: | E59: =IFERROR(INDEX(C17:C56,MATCH(MAX(E17:E56),E17:E56,0)),"")
A60: Profit Before Tax: | B60: =B12-B59 | D60: Largest Expense: | E60: =MAX(E17:E56)
A61: Tax Amount: | B61: =IF(B60>0,B60*$B$11,0)
A62: Net Profit: | B62: =B60-B61
A63: Net Loss: | B63: =IF(B62<0,ABS(B62),0)
A64: Tip: | B64: Enter every receipt on its own row so the summaries and chart stay accurate.

Sheet Job 199
A1: Hammer Brick & Home LLC - Job Tracker
A3: Job Name:
A4: Client:
A5: Address:
A6: Start Date:
A7: End Date:
A9: Contract Price:
A10: Change Orders:
A11: Tax Rate:
A12: Total Budget: | B12: =B9+B10
A15: Expense Log (enter one line per receipt)
A16: Date | B16: Type | C16: Description | D16: Vendor | E16: Cost
A59: Total Expenses: | B59: =SUM(E17:E56) | D59: Most Expensive Item: | E59: =IFERROR(INDEX(C17:C56,MATCH(MAX(E17:E56),E17:E56,0)),"")
A60: Profit Before Tax: | B60: =B12-B59 | D60: Largest Expense: | E60: =MAX(E17:E56)
A61: Tax Amount: | B61: =IF(B60>0,B60*$B$11,0)
A62: Net Profit: | B62: =B60-B61
A63: Net Loss: | B63: =IF(B62<0,ABS(B62),0)
A64: Tip: | B64: Enter every receipt on its own row so the summaries and chart stay accurate.

Sheet Job 200
A1: Hammer Brick & Home LLC - Job Tracker
A3: Job Name:
A4: Client:
A5: Address:
A6: Start Date:
A7: End Date:
A9: Contract Price:
A10: Change Orders:
A11: Tax Rate:
A12: Total Budget: | B12: =B9+B10
A15: Expense Log (enter one line per receipt)
A16: Date | B16: Type | C16: Description | D16: Vendor | E16: Cost
A59: Total Expenses: | B59: =SUM(E17:E56) | D59: Most Expensive Item: | E59: =IFERROR(INDEX(C17:C56,MATCH(MAX(E17:E56),E17:E56,0)),"")
A60: Profit Before Tax: | B60: =B12-B59 | D60: Largest Expense: | E60: =MAX(E17:E56)
A61: Tax Amount: | B61: =IF(B60>0,B60*$B$11,0)
A62: Net Profit: | B62: =B60-B61
A63: Net Loss: | B63: =IF(B62<0,ABS(B62),0)
A64: Tip: | B64: Enter every receipt on its own row so the summaries and chart stay accurate.

Sheet _Data
A1: Date | B1: Type | C1: Description | D1: Vendor | E1: Cost | F1: Job Sheet
A2: ='Job Tracker'!A17 | B2: ='Job Tracker'!B17 | C2: ='Job Tracker'!C17 | D2: ='Job Tracker'!D17 | E2: ='Job Tracker'!E17 | F2: Job Tracker
A3: ='Job Tracker'!A18 | B3: ='Job Tracker'!B18 | C3: ='Job Tracker'!C18 | D3: ='Job Tracker'!D18 | E3: ='Job Tracker'!E18 | F3: Job Tracker
A4: ='Job Tracker'!A19 | B4: ='Job Tracker'!B19 | C4: ='Job Tracker'!C19 | D4: ='Job Tracker'!D19 | E4: ='Job Tracker'!E19 | F4: Job Tracker
A5: ='Job Tracker'!A20 | B5: ='Job Tracker'!B20 | C5: ='Job Tracker'!C20 | D5: ='Job Tracker'!D20 | E5: ='Job Tracker'!E20 | F5: Job Tracker
A6: ='Job Tracker'!A21 | B6: ='Job Tracker'!B21 | C6: ='Job Tracker'!C21 | D6: ='Job Tracker'!D21 | E6: ='Job Tracker'!E21 | F6: Job Tracker
A7: ='Job Tracker'!A22 | B7: ='Job Tracker'!B22 | C7: ='Job Tracker'!C22 | D7: ='Job Tracker'!D22 | E7: ='Job Tracker'!E22 | F7: Job Tracker
A8: ='Job Tracker'!A23 | B8: ='Job Tracker'!B23 | C8: ='Job Tracker'!C23 | D8: ='Job Tracker'!D23 | E8: ='Job Tracker'!E23 | F8: Job Tracker
A9: ='Job Tracker'!A24 | B9: ='Job Tracker'!B24 | C9: ='Job Tracker'!C24 | D9: ='Job Tracker'!D24 | E9: ='Job Tracker'!E24 | F9: Job Tracker
A10: ='Job Tracker'!A25 | B10: ='Job Tracker'!B25 | C10: ='Job Tracker'!C25 | D10: ='Job Tracker'!D25 | E10: ='Job Tracker'!E25 | F10: Job Tracker
A11: ='Job Tracker'!A26 | B11: ='Job Tracker'!B26 | C11: ='Job Tracker'!C26 | D11: ='Job Tracker'!D26 | E11: ='Job Tracker'!E26 | F11: Job Tracker
A12: ='Job Tracker'!A27 | B12: ='Job Tracker'!B27 | C12: ='Job Tracker'!C27 | D12: ='Job Tracker'!D27 | E12: ='Job Tracker'!E27 | F12: Job Tracker
A13: ='Job Tracker'!A28 | B13: ='Job Tracker'!B28 | C13: ='Job Tracker'!C28 | D13: ='Job Tracker'!D28 | E13: ='Job Tracker'!E28 | F13: Job Tracker
... A41: ='Job Tracker'!A56 | B41: ='Job Tracker'!B56 | C41: ='Job Tracker'!C56 | D41: ='Job Tracker'!D56 | E41: ='Job Tracker'!E56 | F41: Job Tracker
A42: ='Job 002'!A17 | B42: ='Job 002'!B17 | C42: ='Job 002'!C17 | D42: ='Job 002'!D17 | E42: ='Job 002'!E17 | F42: Job 002
A43: ='Job 002'!A18 | B43: ='Job 002'!B18 | C43: ='Job 002'!C18 | D43: ='Job 002'!D18 | E43: ='Job 002'!E18 | F43: Job 002
A44: ='Job 002'!A19 | B44: ='Job 002'!B19 | C44: ='Job 002'!C19 | D44: ='Job 002'!D19 | E44: ='Job 002'!E19 | F44: Job 002
A45: ='Job 002'!A20 | B45: ='Job 002'!B20 | C45: ='Job 002'!C20 | D45: ='Job 002'!D20 | E45: ='Job 002'!E20 | F45: Job 002
A46: ='Job 002'!A21 | B46: ='Job 002'!B21 | C46: ='Job 002'!C21 | D46: ='Job 002'!D21 | E46: ='Job 002'!E21 | F46: Job 002
A47: ='Job 002'!A22 | B47: ='Job 002'!B22 | C47: ='Job 002'!C22 | D47: ='Job 002'!D22 | E47: ='Job 002'!E22 | F47: Job 002
A48: ='Job 002'!A23 | B48: ='Job 002'!B23 | C48: ='Job 002'!C23 | D48: ='Job 002'!D23 | E48: ='Job 002'!E23 | F48: Job 002
A49: ='Job 002'!A24 | B49: ='Job 002'!B24 | C49: ='Job 002'!C24 | D49: ='Job 002'!D24 | E49: ='Job 002'!E24 | F49: Job 002
A50: ='Job 002'!A25 | B50: ='Job 002'!B25 | C50: ='Job 002'!C25 | D50: ='Job 002'!D25 | E50: ='Job 002'!E25 | F50: Job 002
A51: ='Job 002'!A26 | B51: ='Job 002'!B26 | C51: ='Job 002'!C26 | D51: ='Job 002'!D26 | E51: ='Job 002'!E26 | F51: Job 002
A52: ='Job 002'!A27 | B52: ='Job 002'!B27 | C52: ='Job 002'!C27 | D52: ='Job 002'!D27 | E52: ='Job 002'!E27 | F52: Job 002
A53: ='Job 002'!A28 | B53: ='Job 002'!B28 | C53: ='Job 002'!C28 | D53: ='Job 002'!D28 | E53: ='Job 002'!E28 | F53: Job 002
... A81: ='Job 002'!A56 | B81: ='Job 002'!B56 | C81: ='Job 002'!C56 | D81: ='Job 002'!D56 | E81: ='Job 002'!E56 | F81: Job 002
A82: ='Job 003'!A17 | B82: ='Job 003'!B17 | C82: ='Job 003'!C17 | D82: ='Job 003'!D17 | E82: ='Job 003'!E17 | F82: Job 003
A83: ='Job 003'!A18 | B83: ='Job 003'!B18 | C83: ='Job 003'!C18 | D83: ='Job 003'!D18 | E83: ='Job 003'!E18 | F83: Job 003
A84: ='Job 003'!A19 | B84: ='Job 003'!B19 | C84: ='Job 003'!C19 | D84: ='Job 003'!D19 | E84: ='Job 003'!E19 | F84: Job 003
A85: ='Job 003'!A20 | B85: ='Job 003'!B20 | C85: ='Job 003'!C20 | D85: ='Job 003'!D20 | E85: ='Job 003'!E20 | F85: Job 003
A86: ='Job 003'!A21 | B86: ='Job 003'!B21 | C86: ='Job 003'!C21 | D86: ='Job 003'!D21 | E86: ='Job 003'!E21 | F86: Job 003
A87: ='Job 003'!A22 | B87: ='Job 003'!B22 | C87: ='Job 003'!C22 | D87: ='Job 003'!D22 | E87: ='Job 003'!E22 | F87: Job 003
A88: ='Job 003'!A23 | B88: ='Job 003'!B23 | C88: ='Job 003'!C23 | D88: ='Job 003'!D23 | E88: ='Job 003'!E23 | F88: Job 003
A89: ='Job 003'!A24 | B89: ='Job 003'!B24 | C89: ='Job 003'!C24 | D89: ='Job 003'!D24 | E89: ='Job 003'!E24 | F89: Job 003
A90: ='Job 003'!A25 | B90: ='Job 003'!B25 | C90: ='Job 003'!C25 | D90: ='Job 003'!D25 | E90: ='Job 003'!E25 | F90: Job 003
A91: ='Job 003'!A26 | B91: ='Job 003'!B26 | C91: ='Job 003'!C26 | D91: ='Job 003'!D26 | E91: ='Job 003'!E26 | F91: Job 003
A92: ='Job 003'!A27 | B92: ='Job 003'!B27 | C92: ='Job 003'!C27 | D92: ='Job 003'!D27 | E92: ='Job 003'!E27 | F92: Job 003
A93: ='Job 003'!A28 | B93: ='Job 003'!B28 | C93: ='Job 003'!C28 | D93: ='Job 003'!D28 | E93: ='Job 003'!E28 | F93: Job 003
... A121: ='Job 003'!A56 | B121: ='Job 003'!B56 | C121: ='Job 003'!C56 | D121: ='Job 003'!D56 | E121: ='Job 003'!E56 | F121: Job 003
A122: ='Job 004'!A17 | B122: ='Job 004'!B17 | C122: ='Job 004'!C17 | D122: ='Job 004'!D17 | E122: ='Job 004'!E17 | F122: Job 004
A123: ='Job 004'!A18 | B123: ='Job 004'!B18 | C123: ='Job 004'!C18 | D123: ='Job 004'!D18 | E123: ='Job 004'!E18 | F123: Job 004
A124: ='Job 004'!A19 | B124: ='Job 004'!B19 | C124: ='Job 004'!C19 | D124: ='Job 004'!D19 | E124: ='Job 004'!E19 | F124: Job 004
A125: ='Job 004'!A20 | B125: ='Job 004'!B20 | C125: ='Job 004'!C20 | D125: ='Job 004'!D20 | E125: ='Job 004'!E20 | F125: Job 004
A126: ='Job 004'!A21 | B126: ='Job 004'!B21 | C126: ='Job 004'!C21 | D126: ='Job 004'!D21 | E126: ='Job 004'!E21 | F126: Job 004
A127: ='Job 004'!A22 | B127: ='Job 004'!B22 | C127: ='Job 004'!C22 | D127: ='Job 004'!D22 | E127: ='Job 004'!E22 | F127: Job 004
A128: ='Job 004'!A23 | B128: ='Job 004'!B23 | C128: ='Job 004'!C23 | D128: ='Job 004'!D23 | E128: ='Job 004'!E23 | F128: Job 004
A129: ='Job 004'!A24 | B129: ='Job 004'!B24 | C129: ='Job 004'!C24 | D129: ='Job 004'!D24 | E129: ='Job 004'!E24 | F129: Job 004
A130: ='Job 004'!A25 | B130: ='Job 004'!B25 | C130: ='Job 004'!C25 | D130: ='Job 004'!D25 | E130: ='Job 004'!E25 | F130: Job 004
A131: ='Job 004'!A26 | B131: ='Job 004'!B26 | C131: ='Job 004'!C26 | D131: ='Job 004'!D26 | E131: ='Job 004'!E26 | F131: Job 004
A132: ='Job 004'!A27 | B132: ='Job 004'!B27 | C132: ='Job 004'!C27 | D132: ='Job 004'!D27 | E132: ='Job 004'!E27 | F132: Job 004
A133: ='Job 004'!A28 | B133: ='Job 004'!B28 | C133: ='Job 004'!C28 | D133: ='Job 004'!D28 | E133: ='Job 004'!E28 | F133: Job 004
... A161: ='Job 004'!A56 | B161: ='Job 004'!B56 | C161: ='Job 004'!C56 | D161: ='Job 004'!D56 | E161: ='Job 004'!E56 | F161: Job 004
A162: ='Job 005'!A17 | B162: ='Job 005'!B17 | C162: ='Job 005'!C17 | D162: ='Job 005'!D17 | E162: ='Job 005'!E17 | F162: Job 005
A163: ='Job 005'!A18 | B163: ='Job 005'!B18 | C163: ='Job 005'!C18 | D163: ='Job 005'!D18 | E163: ='Job 005'!E18 | F163: Job 005
A164: ='Job 005'!A19 | B164: ='Job 005'!B19 | C164: ='Job 005'!C19 | D164: ='Job 005'!D19 | E164: ='Job 005'!E19 | F164: Job 005
A165: ='Job 005'!A20 | B165: ='Job 005'!B20 | C165: ='Job 005'!C20 | D165: ='Job 005'!D20 | E165: ='Job 005'!E20 | F165: Job 005
A166: ='Job 005'!A21 | B166: ='Job 005'!B21 | C166: ='Job 005'!C21 | D166: ='Job 005'!D21 | E166: ='Job 005'!E21 | F166: Job 005
A167: ='Job 005'!A22 | B167: ='Job 005'!B22 | C167: ='Job 005'!C22 | D167: ='Job 005'!D22 | E167: ='Job 005'!E22 | F167: Job 005
A168: ='Job 005'!A23 | B168: ='Job 005'!B23 | C168: ='Job 005'!C23 | D168: ='Job 005'!D23 | E168: ='Job 005'!E23 | F168: Job 005
A169: ='Job 005'!A24 | B169: ='Job 005'!B24 | C169: ='Job 005'!C24 | D169: ='Job 005'!D24 | E169: ='Job 005'!E24 | F169: Job 005
A170: ='Job 005'!A25 | B170: ='Job 005'!B25 | C170: ='Job 005'!C25 | D170: ='Job 005'!D25 | E170: ='Job 005'!E25 | F170: Job 005
A171: ='Job 005'!A26 | B171: ='Job 005'!B26 | C171: ='Job 005'!C26 | D171: ='Job 005'!D26 | E171: ='Job 005'!E26 | F171: Job 005
A172: ='Job 005'!A27 | B172: ='Job 005'!B27 | C172: ='Job 005'!C27 | D172: ='Job 005'!D27 | E172: ='Job 005'!E27 | F172: Job 005
A173: ='Job 005'!A28 | B173: ='Job 005'!B28 | C173: ='Job 005'!C28 | D173: ='Job 005'!D28 | E173: ='Job 005'!E28 | F173: Job 005
... A201: ='Job 005'!A56 | B201: ='Job 005'!B56 | C201: ='Job 005'!C56 | D201: ='Job 005'!D56 | E201: ='Job 005'!E56 | F201: Job 005
A202: ='Job 006'!A17 | B202: ='Job 006'!B17 | C202: ='Job 006'!C17 | D202: ='Job 006'!D17 | E202: ='Job 006'!E17 | F202: Job 006
A203: ='Job 006'!A18 | B203: ='Job 006'!B18 | C203: ='Job 006'!C18 | D203: ='Job 006'!D18 | E203: ='Job 006'!E18 | F203: Job 006
A204: ='Job 006'!A19 | B204: ='Job 006'!B19 | C204: ='Job 006'!C19 | D204: ='Job 006'!D19 | E204: ='Job 006'!E19 | F204: Job 006
A205: ='Job 006'!A20 | B205: ='Job 006'!B20 | C205: ='Job 006'!C20 | D205: ='Job 006'!D20 | E205: ='Job 006'!E20 | F205: Job 006
A206: ='Job 006'!A21 | B206: ='Job 006'!B21 | C206: ='Job 006'!C21 | D206: ='Job 006'!D21 | E206: ='Job 006'!E21 | F206: Job 006
A207: ='Job 006'!A22 | B207: ='Job 006'!B22 | C207: ='Job 006'!C22 | D207: ='Job 006'!D22 | E207: ='Job 006'!E22 | F207: Job 006
A208: ='Job 006'!A23 | B208: ='Job 006'!B23 | C208: ='Job 006'!C23 | D208: ='Job 006'!D23 | E208: ='Job 006'!E23 | F208: Job 006
A209: ='Job 006'!A24 | B209: ='Job 006'!B24 | C209: ='Job 006'!C24 | D209: ='Job 006'!D24 | E209: ='Job 006'!E24 | F209: Job 006
A210: ='Job 006'!A25 | B210: ='Job 006'!B25 | C210: ='Job 006'!C25 | D210: ='Job 006'!D25 | E210: ='Job 006'!E25 | F210: Job 006
A211: ='Job 006'!A26 | B211: ='Job 006'!B26 | C211: ='Job 006'!C26 | D211: ='Job 006'!D26 | E211: ='Job 006'!E26 | F211: Job 006
A212: ='Job 006'!A27 | B212: ='Job 006'!B27 | C212: ='Job 006'!C27 | D212: ='Job 006'!D27 | E212: ='Job 006'!E27 | F212: Job 006
A213: ='Job 006'!A28 | B213: ='Job 006'!B28 | C213: ='Job 006'!C28 | D213: ='Job 006'!D28 | E213: ='Job 006'!E28 | F213: Job 006
... A241: ='Job 006'!A56 | B241: ='Job 006'!B56 | C241: ='Job 006'!C56 | D241: ='Job 006'!D56 | E241: ='Job 006'!E56 | F241: Job 006
A242: ='Job 007'!A17 | B242: ='Job 007'!B17 | C242: ='Job 007'!C17 | D242: ='Job 007'!D17 | E242: ='Job 007'!E17 | F242: Job 007
A243: ='Job 007'!A18 | B243: ='Job 007'!B18 | C243: ='Job 007'!C18 | D243: ='Job 007'!D18 | E243: ='Job 007'!E18 | F243: Job 007
A244: ='Job 007'!A19 | B244: ='Job 007'!B19 | C244: ='Job 007'!C19 | D244: ='Job 007'!D19 | E244: ='Job 007'!E19 | F244: Job 007
A245: ='Job 007'!A20 | B245: ='Job 007'!B20 | C245: ='Job 007'!C20 | D245: ='Job 007'!D20 | E245: ='Job 007'!E20 | F245: Job 007
A246: ='Job 007'!A21 | B246: ='Job 007'!B21 | C246: ='Job 007'!C21 | D246: ='Job 007'!D21 | E246: ='Job 007'!E21 | F246: Job 007
A247: ='Job 007'!A22 | B247: ='Job 007'!B22 | C247: ='Job 007'!C22 | D247: ='Job 007'!D22 | E247: ='Job 007'!E22 | F247: Job 007
A248: ='Job 007'!A23 | B248: ='Job 007'!B23 | C248: ='Job 007'!C23 | D248: ='Job 007'!D23 | E248: ='Job 007'!E23 | F248: Job 007
A249: ='Job 007'!A24 | B249: ='Job 007'!B24 | C249: ='Job 007'!C24 | D249: ='Job 007'!D24 | E249: ='Job 007'!E24 | F249: Job 007
A250: ='Job 007'!A25 | B250: ='Job 007'!B25 | C250: ='Job 007'!C25 | D250: ='Job 007'!D25 | E250: ='Job 007'!E25 | F250: Job 007
A251: ='Job 007'!A26 | B251: ='Job 007'!B26 | C251: ='Job 007'!C26 | D251: ='Job 007'!D26 | E251: ='Job 007'!E26 | F251: Job 007
A252: ='Job 007'!A27 | B252: ='Job 007'!B27 | C252: ='Job 007'!C27 | D252: ='Job 007'!D27 | E252: ='Job 007'!E27 | F252: Job 007
A253: ='Job 007'!A28 | B253: ='Job 007'!B28 | C253: ='Job 007'!C28 | D253: ='Job 007'!D28 | E253: ='Job 007'!E28 | F253: Job 007
... A281: ='Job 007'!A56 | B281: ='Job 007'!B56 | C281: ='Job 007'!C56 | D281: ='Job 007'!D56 | E281: ='Job 007'!E56 | F281: Job 007
A282: ='Job 008'!A17 | B282: ='Job 008'!B17 | C282: ='Job 008'!C17 | D282: ='Job 008'!D17 | E282: ='Job 008'!E17 | F282: Job 008
A283: ='Job 008'!A18 | B283: ='Job 008'!B18 | C283: ='Job 008'!C18 | D283: ='Job 008'!D18 | E283: ='Job 008'!E18 | F283: Job 008
A284: ='Job 008'!A19 | B284: ='Job 008'!B19 | C284: ='Job 008'!C19 | D284: ='Job 008'!D19 | E284: ='Job 008'!E19 | F284: Job 008
A285: ='Job 008'!A20 | B285: ='Job 008'!B20 | C285: ='Job 008'!C20 | D285: ='Job 008'!D20 | E285: ='Job 008'!E20 | F285: Job 008
A286: ='Job 008'!A21 | B286: ='Job 008'!B21 | C286: ='Job 008'!C21 | D286: ='Job 008'!D21 | E286: ='Job 008'!E21 | F286: Job 008
A287: ='Job 008'!A22 | B287: ='Job 008'!B22 | C287: ='Job 008'!C22 | D287: ='Job 008'!D22 | E287: ='Job 008'!E22 | F287: Job 008
A288: ='Job 008'!A23 | B288: ='Job 008'!B23 | C288: ='Job 008'!C23 | D288: ='Job 008'!D23 | E288: ='Job 008'!E23 | F288: Job 008
A289: ='Job 008'!A24 | B289: ='Job 008'!B24 | C289: ='Job 008'!C24 | D289: ='Job 008'!D24 | E289: ='Job 008'!E24 | F289: Job 008
...
