Workbook

Sheet Expenses
A1: Date | B1: Description | C1: Category | D1: Amount ($)

Sheet Summary
A1: Category | B1: Total ($)
A2: Materials | B2: =IF(A2="","",SUMIF(Expenses!$C:$C,A2,Expenses!$D:$D))
A3: Tools | B3: =IF(A3="","",SUMIF(Expenses!$C:$C,A3,Expenses!$D:$D))
A4: Gas / Fuel | B4: =IF(A4="","",SUMIF(Expenses!$C:$C,A4,Expenses!$D:$D))
A5: Tolls | B5: =IF(A5="","",SUMIF(Expenses!$C:$C,A5,Expenses!$D:$D))
A6: Meals | B6: =IF(A6="","",SUMIF(Expenses!$C:$C,A6,Expenses!$D:$D))
A7: Job Supplies | B7: =IF(A7="","",SUMIF(Expenses!$C:$C,A7,Expenses!$D:$D))
A8: Subcontractor Payments | B8: =IF(A8="","",SUMIF(Expenses!$C:$C,A8,Expenses!$D:$D))
A9: Rental Equipment | B9: =IF(A9="","",SUMIF(Expenses!$C:$C,A9,Expenses!$D:$D))
A10: Marketing / Advertising | B10: =IF(A10="","",SUMIF(Expenses!$C:$C,A10,Expenses!$D:$D))
A11: Advertisements | B11: =IF(A11="","",SUMIF(Expenses!$C:$C,A11,Expenses!$D:$D))
A12: Website / Software | B12: =IF(A12="","",SUMIF(Expenses!$C:$C,A12,Expenses!$D:$D))
A13: Insurance | B13: =IF(A13="","",SUMIF(Expenses!$C:$C,A13,Expenses!$D:$D))
... A19: Extra 3 | B19: =IF(A19="","",SUMIF(Expenses!$C:$C,A19,Expenses!$D:$D))
B20: =IF(A20="","",SUMIF(Expenses!$C:$C,A20,Expenses!$D:$D))
B21: =IF(A21="","",SUMIF(Expenses!$C:$C,A21,Expenses!$D:$D))
B22: =IF(A22="","",SUMIF(Expenses!$C:$C,A22,Expenses!$D:$D))
B23: =IF(A23="","",SUMIF(Expenses!$C:$C,A23,Expenses!$D:$D))
B24: =IF(A24="","",SUMIF(Expenses!$C:$C,A24,Expenses!$D:$D))
B25: =IF(A25="","",SUMIF(Expenses!$C:$C,A25,Expenses!$D:$D))
B26: =IF(A26="","",SUMIF(Expenses!$C:$C,A26,Expenses!$D:$D))
B27: =IF(A27="","",SUMIF(Expenses!$C:$C,A27,Expenses!$D:$D))
B28: =IF(A28="","",SUMIF(Expenses!$C:$C,A28,Expenses!$D:$D))
B29: =IF(A29="","",SUMIF(Expenses!$C:$C,A29,Expenses!$D:$D))
B30: =IF(A30="","",SUMIF(Expenses!$C:$C,A30,Expenses!$D:$D))
B31: =IF(A31="","",SUMIF(Expenses!$C:$C,A31,Expenses!$D:$D))
... B40: =IF(A40="","",SUMIF(Expenses!$C:$C,A40,Expenses!$D:$D))

Sheet Monthly Totals
A1: Month | B1: Total ($)
A2: January | B2: =SUMPRODUCT((MONTH(Expenses!$A$2:$A$501)=1)*(Expenses!$D$2:$D$501))
A3: February | B3: =SUMPRODUCT((MONTH(Expenses!$A$2:$A$501)=2)*(Expenses!$D$2:$D$501))
A4: March | B4: =SUMPRODUCT((MONTH(Expenses!$A$2:$A$501)=3)*(Expenses!$D$2:$D$501))
A5: April | B5: =SUMPRODUCT((MONTH(Expenses!$A$2:$A$501)=4)*(Expenses!$D$2:$D$501))
A6: May | B6: =SUMPRODUCT((MONTH(Expenses!$A$2:$A$501)=5)*(Expenses!$D$2:$D$501))
A7: June | B7: =SUMPRODUCT((MONTH(Expenses!$A$2:$A$501)=6)*(Expenses!$D$2:$D$501))
A8: July | B8: =SUMPRODUCT((MONTH(Expenses!$A$2:$A$501)=7)*(Expenses!$D$2:$D$501))
A9: August | B9: =SUMPRODUCT((MONTH(Expenses!$A$2:$A$501)=8)*(Expenses!$D$2:$D$501))
A10: September | B10: =SUMPRODUCT((MONTH(Expenses!$A$2:$A$501)=9)*(Expenses!$D$2:$D$501))
A11: October | B11: =SUMPRODUCT((MONTH(Expenses!$A$2:$A$501)=10)*(Expenses!$D$2:$D$501))
A12: November | B12: =SUMPRODUCT((MONTH(Expenses!$A$2:$A$501)=11)*(Expenses!$D$2:$D$501))
A13: December | B13: =SUMPRODUCT((MONTH(Expenses!$A$2:$A$501)=12)*(Expenses!$D$2:$D$501))
A15: TOTAL (Year) | B15: =SUM(B2:B13)

Sheet Yearly Totals
A1: Year | B1: Total ($)
A2: 2024 | B2: =SUMPRODUCT((YEAR(Expenses!$A$2:$A$501)=A2)*(Expenses!$D$2:$D$501))
A3: 2025 | B3: =SUMPRODUCT((YEAR(Expenses!$A$2:$A$501)=A3)*(Expenses!$D$2:$D$501))
A4: 2026 | B4: =SUMPRODUCT((YEAR(Expenses!$A$2:$A$501)=A4)*(Expenses!$D$2:$D$501))
A5: 2027 | B5: =SUMPRODUCT((YEAR(Expenses!$A$2:$A$501)=A5)*(Expenses!$D$2:$D$501))
A6: 2028 | B6: =SUMPRODUCT((YEAR(Expenses!$A$2:$A$501)=A6)*(Expenses!$D$2:$D$501))

Sheet Job Expenses
A1: Job Name | B1: Client | C1: Date | D1: Category | E1: Description | F1: Amount ($) | G1: Revenue ($) | H1: Profit ($) | J1: Job | K1: Total Profit
H2: =G2-F2 | I2: Job Name: | J2: Job 1 | K2: =SUMIF(A2:A251, J2, H2:H251)
H3: =G3-F3 | I3: Total Cost: | J3: Job 2 | K3: =SUMIF(A2:A251, J3, H2:H251)
H4: =G4-F4 | J4: Job 3 | K4: =SUMIF(A2:A251, J4, H2:H251)
H5: =G5-F5 | J5: Job 4 | K5: =SUMIF(A2:A251, J5, H2:H251)
H6: =G6-F6 | J6: Job 5 | K6: =SUMIF(A2:A251, J6, H2:H251)
H7: =G7-F7 | J7: Job 6 | K7: =SUMIF(A2:A251, J7, H2:H251)
H8: =G8-F8 | J8: Job 7 | K8: =SUMIF(A2:A251, J8, H2:H251)
H9: =G9-F9 | J9: Job 8 | K9: =SUMIF(A2:A251, J9, H2:H251)
H10: =G10-F10 | J10: Job 9 | K10: =SUMIF(A2:A251, J10, H2:H251)
H11: =G11-F11 | J11: Job 10 | K11: =SUMIF(A2:A251, J11, H2:H251)
H12: =G12-F12
H13: =G13-F13
H14: =G14-F14
H15: =G15-F15
H16: =G16-F16
H17: =G17-F17
H18: =G18-F18
H19: =G19-F19
H20: =G20-F20
H21: =G21-F21
H22: =G22-F22
H23: =G23-F23
... H251: =G251-F251

Sheet Mileage Log
A1: Date | B1: Start Location | C1: End Location | D1: Miles Driven | E1: Purpose | F1: Job Name | G1: Deduction ($) | I1: Mileage Rate ($/mile) | J1: 0.67
G2: =D2*$J$1
G3: =D3*$J$1
G4: =D4*$J$1
G5: =D5*$J$1
G6: =D6*$J$1
G7: =D7*$J$1
G8: =D8*$J$1
G9: =D9*$J$1
G10: =D10*$J$1
G11: =D11*$J$1
G12: =D12*$J$1
G13: =D13*$J$1
... G251: =D251*$J$1

Sheet Profit & Loss
A1: Month | B1: Income ($) | C1: Expenses ($) | D1: Net Profit ($)
A2: January | C2: ='Monthly Totals'!B2 | D2: =B2-C2
A3: February | C3: ='Monthly Totals'!B3 | D3: =B3-C3
A4: March | C4: ='Monthly Totals'!B4 | D4: =B4-C4
A5: April | C5: ='Monthly Totals'!B5 | D5: =B5-C5
A6: May | C6: ='Monthly Totals'!B6 | D6: =B6-C6
A7: June | C7: ='Monthly Totals'!B7 | D7: =B7-C7
A8: July | C8: ='Monthly Totals'!B8 | D8: =B8-C8
A9: August | C9: ='Monthly Totals'!B9 | D9: =B9-C9
A10: September | C10: ='Monthly Totals'!B10 | D10: =B10-C10
A11: October | C11: ='Monthly Totals'!B11 | D11: =B11-C11
A12: November | C12: ='Monthly Totals'!B12 | D12: =B12-C12
A13: December | C13: ='Monthly Totals'!B13 | D13: =B13-C13

Sheet Cash Flow
A1: 📉 Cash Flow Dashboard
A3: Month | B3: Income ($) | C3: Expenses ($) | D3: Cash Flow ($)
A4: January | B4: ='Profit & Loss'!B4 | C4: ='Profit & Loss'!C4 | D4: =B4-C4
A5: February | B5: ='Profit & Loss'!B5 | C5: ='Profit & Loss'!C5 | D5: =B5-C5
A6: March | B6: ='Profit & Loss'!B6 | C6: ='Profit & Loss'!C6 | D6: =B6-C6
A7: April | B7: ='Profit & Loss'!B7 | C7: ='Profit & Loss'!C7 | D7: =B7-C7
A8: May | B8: ='Profit & Loss'!B8 | C8: ='Profit & Loss'!C8 | D8: =B8-C8
A9: June | B9: ='Profit & Loss'!B9 | C9: ='Profit & Loss'!C9 | D9: =B9-C9
A10: July | B10: ='Profit & Loss'!B10 | C10: ='Profit & Loss'!C10 | D10: =B10-C10
A11: August | B11: ='Profit & Loss'!B11 | C11: ='Profit & Loss'!C11 | D11: =B11-C11
A12: September | B12: ='Profit & Loss'!B12 | C12: ='Profit & Loss'!C12 | D12: =B12-C12
A13: October | B13: ='Profit & Loss'!B13 | C13: ='Profit & Loss'!C13 | D13: =B13-C13
A14: November | B14: ='Profit & Loss'!B14 | C14: ='Profit & Loss'!C14 | D14: =B14-C14
A15: December | B15: ='Profit & Loss'!B15 | C15: ='Profit & Loss'!C15 | D15: =B15-C15

Sheet Dashboard
A1: 📊 Hammer Brick & Home – Contractor Dashboard
A3: Metric | B3: Value
A4: Total Expenses (YTD) | B4: =SUM(Expenses!$D$2:$D$501) | D4: View Category Pie Chart on 'Summary' sheet.
A5: Total Income (YTD) | B5: =SUM('Profit & Loss'!$B$2:$B$13) | D5: View Net Profit Trend on 'Profit & Loss' sheet.
A6: Net Profit (YTD) | B6: =SUM('Profit & Loss'!$D$2:$D$13) | D6: View Cash Flow Chart on 'Cash Flow' sheet.
A7: Total Transactions | B7: =COUNTA(Expenses!$D$2:$D$501)
A8: Job Entries Logged | B8: =COUNTA('Job Expenses'!$A$2:$A$251)

Sheet Quarterly Totals
A1: Quarter | B1: Total ($) | D1: Highest Spending Month: | E1: =INDEX('Monthly Totals'!A2:A13, MATCH(MAX('Monthly Totals'!B2:B13), 'Monthly Totals'!B2:B13, 0))
A2: Q1 | B2: ='Monthly Totals'!B2+'Monthly Totals'!B3+'Monthly Totals'!B4 | D2: Average Monthly Spend: | E2: =AVERAGE('Monthly Totals'!B2:B13)
A3: Q2 | B3: ='Monthly Totals'!B5+'Monthly Totals'!B6+'Monthly Totals'!B7
A4: Q3 | B4: ='Monthly Totals'!B8+'Monthly Totals'!B9+'Monthly Totals'!B10
A5: Q4 | B5: ='Monthly Totals'!B11+'Monthly Totals'!B12+'Monthly Totals'!B13

Sheet Tax Report
A1: Category | B1: Total ($) | C1: Tax-Deductible? | D1: Notes
A2: Materials | B2: =Summary!B2 | C2: Yes
A3: Tools | B3: =Summary!B3 | C3: Yes
A4: Gas / Fuel | B4: =Summary!B4 | C4: Yes
A5: Tolls | B5: =Summary!B5 | C5: Yes
A6: Meals | B6: =Summary!B6 | C6: Yes
A7: Job Supplies | B7: =Summary!B7 | C7: Yes
A8: Subcontractor Payments | B8: =Summary!B8 | C8: Yes
A9: Rental Equipment | B9: =Summary!B9 | C9: Yes
A10: Marketing / Advertising | B10: =Summary!B10 | C10: Yes
A11: Advertisements | B11: =Summary!B11 | C11: Yes
A12: Website / Software | B12: =Summary!B12 | C12: Yes
A13: Insurance | B13: =Summary!B13 | C13: Yes
... A22: Extra 6 | B22: =Summary!B22 | C22: Yes
A24: Total Deductible | B24: =SUM(B2:B22)

Sheet Sales Tax Log
A1: Date | B1: Job/Client | C1: Material | D1: Amount ($) | E1: Tax Rate | F1: Sales Tax Owed
F2: =D2*E2 | H2: Total Sales Tax: | I2: =SUM(F2:F101)
F3: =D3*E3
F4: =D4*E4
F5: =D5*E5
F6: =D6*E6
F7: =D7*E7
F8: =D8*E8
F9: =D9*E9
F10: =D10*E10
F11: =D11*E11
F12: =D12*E12
F13: =D13*E13
F14: =D14*E14
... F101: =D101*E101

Sheet Vehicle Deduction
A1: Category | B1: Amount ($)
A2: Mileage Deduction
A3: Gas
A4: Repairs
A5: Insurance
A6: Registration
A7: Parking
A8: Tolls
A10: Total Vehicle Deduction | B10: =SUM(B2:B8)

Sheet Tax Bracket Calculator
A1: Taxable Income | B1: Bracket | C1: Estimated Fed Tax
A2: Enter Income | B2: =IF(A2<11000,"10%",IF(A2<44725,"12%",IF(A2<95375,"22%",IF(A2<182100,"24%","32%+")))) | C2: =A2*IF(B2="10%",0.10,IF(B2="12%",0.12,IF(B2="22%",0.22,IF(B2="24%",0.24,0.32))))

Sheet Net Taxable Income
A1: Description | B1: Amount ($)
A2: Total Income (from P&L)
A3: Total Expenses (from P&L)
A4: Vehicle Deduction
A5: Home Office Deduction
A6: Other Adjustments
A8: Net Taxable Income | B8: =B2-B3-B4-B5-B6

Sheet IRS Schedule C
A1: Line | B1: Category | C1: Amount ($) | D1: Notes
A2: 1 | B2: Gross Receipts
A3: 2 | B3: Returns and Allowances
A4: 3 | B4: Gross Income (= line 1 - 2)
A5: 4 | B5: Advertising
A6: 5 | B6: Car and Truck Expenses
A7: 6 | B7: Contract Labor (Subcontractors)
A8: 7 | B8: Depreciation
A9: 8 | B9: Insurance (other than health)
A10: 9 | B10: Legal & Professional Services
A11: 10 | B11: Office Expenses
A12: 11 | B12: Rent or Lease - Vehicles
A13: 12 | B13: Rent or Lease - Equipment
... A21: 20 | B21: Other Expenses
A23: Total Expenses | C23: =SUM(C4:C21)
A25: NET PROFIT (Gross Income - Total Expenses) | C25: =C3-C23

Sheet Payroll Tax Estimator
A1: Description | B1: Amount ($)
A2: Gross Wages
A3: Overtime Pay
A4: Bonuses
A5: Number of Employees
A7: Employer SS Tax (6.2%) | B7: =(B2+B3+B4)*0.062
A8: Employer Medicare Tax (1.45%) | B8: =(B2+B3+B4)*0.0145
A9: Estimated FUTA Tax | B9: =(B2*0.006)
A11: Total Employer Payroll Taxes | B11: =SUM(B7:B9)

Sheet Credit Card Reconciliation
A1: Description | B1: Amount ($)
A2: Statement Start Balance
A3: Statement End Balance
A4: Payments Made
A5: Credits / Refunds
A6: New Charges from Expenses Sheet
A7: Manual New Charges
A9: Calculated Ending Balance | B9: =B2-B3+B5+B6
A11: Difference (Should be $0) | B11: =B9-B3

Sheet Home Office Deduction
A1: Category | B1: Amount ($)
A2: Total home square footage
A3: Business-use square footage
A4: Percentage business use | B4: =B3/B2
A6: Rent or Mortgage Interest
A7: Utilities
A8: Internet
A9: Repairs & Maintenance
A10: Homeowners/Renters Insurance
A12: Total Home Office Deduction | B12: =SUM(B5:B10)*B4

Sheet Depreciation (4562)
A1: Asset | B1: Category | C1: Cost Basis | D1: Date Placed in Service | E1: Recovery Period (Years) | F1: Annual Depreciation ($)
F2: =IF(E2>0,C2/E2,"")
F3: =IF(E3>0,C3/E3,"")
F4: =IF(E4>0,C4/E4,"")
F5: =IF(E5>0,C5/E5,"")
F6: =IF(E6>0,C6/E6,"")
F7: =IF(E7>0,C7/E7,"")
F8: =IF(E8>0,C8/E8,"")
F9: =IF(E9>0,C9/E9,"")
F10: =IF(E10>0,C10/E10,"")
F11: =IF(E11>0,C11/E11,"")
F12: =IF(E12>0,C12/E12,"")
F13: =IF(E13>0,C13/E13,"")
... F51: =IF(E51>0,C51/E51,"")
A55: Total Annual Depreciation | F55: =SUM(F2:F51)
